Workbook
Name NativeTimeline_Order_Date: #N/A
Name Slicer_Region: #N/A

Sheet Summary
A1: SUMMARY
A2: Section1: Data Entry & Data Cleaning
A3: Customer Dim Sheet
A4: Name Colum trim and Proper done
A5: Customer ID had 4 inconsistent name as C-. Used find and Replace to correct it
A6: No Duplicate Values found in Customer ID
A7: Missing Values in Loyalty level were corrected using highest number of loyalty levels observed in that state
A9: Product Dim Sheet
A10: No need for proper or trimming
A11: No Duplicates found
A12: 3 Missing values in stock changed to 0 as no data found
A13: 6 Missing Values in Cost are corrected based on average sub categories and similar products
... A26: Sales Dashboard

Sheet Sales Dashboard
A1: Sales Dashboard

Sheet Customer_Dim (2)
A1: Customer_ID | B1: Name | C1: Proper name | D1: Trim | E1: Age | F1: Gender | G1: City | H1: State | I1: Country | J1: Loyalty_Level
A2: CUST1000 | B2: sheena bonilla | C2: =PROPER(Table26[[#This Row],[Name]]) -> Sheena Bonilla | D2: =TRIM(Table26[[#This Row],[Proper name]]) -> Sheena Bonilla | E2: 55 | F2: Male | G2: Donaldton | H2: North Carolina | I2: USA | J2: Platinum
A3: CUST1001 | B3: Eugene Nelson | C3: =PROPER(Table26[[#This Row],[Name]]) -> Eugene Nelson | D3: =TRIM(Table26[[#This Row],[Proper name]]) -> Eugene Nelson | E3: 26 | F3: Female | G3: Phillipsmouth | H3: North Dakota | I3: USA | J3: Platinum
A4: CUST1002 | B4: dr. Benjamin Price | C4: =PROPER(Table26[[#This Row],[Name]]) -> Dr. Benjamin Price | D4: =TRIM(Table26[[#This Row],[Proper name]]) -> Dr. Benjamin Price | E4: 29 | F4: Female | G4: Kylebury | H4: Alabama | I4: USA | J4: Platinum
A5: CUST1003 | B5: jeremy harris | C5: =PROPER(Table26[[#This Row],[Name]]) -> Jeremy Harris | D5: =TRIM(Table26[[#This Row],[Proper name]]) -> Jeremy Harris | E5: 59 | F5: Female | G5: Thomastown | H5: Ohio | I5: USA | J5: Bronze
A6: CUST1004 | B6: Caroline Collins | C6: =PROPER(Table26[[#This Row],[Name]]) -> Caroline Collins | D6: =TRIM(Table26[[#This Row],[Proper name]]) -> Caroline Collins | E6: 64 | F6: Female | G6: Nicholasshire | H6: California | I6: USA | J6: Silver
A7: CUST1005 | B7: Christine Vaughn | C7: =PROPER(Table26[[#This Row],[Name]]) -> Christine Vaughn | D7: =TRIM(Table26[[#This Row],[Proper name]]) -> Christine Vaughn | E7: 24 | F7: Male | G7: East Amandamouth | H7: Oregon | I7: USA | J7: Bronze
A8: CUST1006 | B8: Amber Jackson | C8: =PROPER(Table26[[#This Row],[Name]]) -> Amber Jackson | D8: =TRIM(Table26[[#This Row],[Proper name]]) -> Amber Jackson | E8: 29 | F8: Female | G8: Deborahborough | H8: South Dakota | I8: USA | J8: Platinum
A9: CUST1007 | B9: Daniel Boyd | C9: =PROPER(Table26[[#This Row],[Name]]) -> Daniel Boyd | D9: =TRIM(Table26[[#This Row],[Proper name]]) -> Daniel Boyd | E9: 29 | F9: Female | G9: West Pamelafurt | H9: West Virginia | I9: USA | J9: Bronze
A10: CUST1008 | B10: Melissa Howard | C10: =PROPER(Table26[[#This Row],[Name]]) -> Melissa Howard | D10: =TRIM(Table26[[#This Row],[Proper name]]) -> Melissa Howard | E10: 53 | F10: Female | G10: Maynardton | H10: New Hampshire | I10: USA | J10: Gold
A11: CUST1009 | B11: Ms. Maria Leach | C11: =PROPER(Table26[[#This Row],[Name]]) -> Ms. Maria Leach | D11: =TRIM(Table26[[#This Row],[Proper name]]) -> Ms. Maria Leach | E11: 64 | F11: Male | G11: Melissashire | H11: Pennsylvania | I11: USA | J11: Platinum
A12: CUST1010 | B12: Dominic Page | C12: =PROPER(Table26[[#This Row],[Name]]) -> Dominic Page | D12: =TRIM(Table26[[#This Row],[Proper name]]) -> Dominic Page | E12: 53 | F12: Male | G12: Port Michaelburgh | H12: Pennsylvania | I12: USA | J12: Bronze
A13: CUST1011 | B13: Brian Lopez | C13: =PROPER(Table26[[#This Row],[Name]]) -> Brian Lopez | D13: =TRIM(Table26[[#This Row],[Proper name]]) -> Brian Lopez | E13: 28 | F13: Female | G13: East Krista | H13: New York | I13: USA | J13: Gold
... A501: CUST1499 | B501: Philip Pennington | C501: =PROPER(Table26[[#This Row],[Name]]) -> Philip Pennington | D501: =TRIM(Table26[[#This Row],[Proper name]]) -> Philip Pennington | E501: 27 | F501: Female | G501: East Valerieview | H501: Oregon | I501: USA | J501: Platinum

Sheet Customer_Dim
A1: Customer_ID | B1: Name | C1: Age | D1: Gender | E1: City | F1: State | G1: Country | H1: Loyalty_Level
A2: CUST1000 | B2: Sheena Bonilla | C2: 55 | D2: Male | E2: Donaldton | F2: North Carolina | G2: USA | H2: Platinum
A3: CUST1001 | B3: Eugene Nelson | C3: 26 | D3: Female | E3: Phillipsmouth | F3: North Dakota | G3: USA | H3: Platinum
A4: CUST1002 | B4: Dr. Benjamin Price | C4: 29 | D4: Female | E4: Kylebury | F4: Alabama | G4: USA | H4: Platinum
A5: CUST1003 | B5: Jeremy Harris | C5: 59 | D5: Female | E5: Thomastown | F5: Ohio | G5: USA | H5: Bronze
A6: CUST1004 | B6: Caroline Collins | C6: 64 | D6: Female | E6: Nicholasshire | F6: California | G6: USA | H6: Silver
A7: CUST1005 | B7: Christine Vaughn | C7: 24 | D7: Male | E7: East Amandamouth | F7: Oregon | G7: USA | H7: Bronze
A8: CUST1006 | B8: Amber Jackson | C8: 29 | D8: Female | E8: Deborahborough | F8: South Dakota | G8: USA | H8: Platinum
A9: CUST1007 | B9: Daniel Boyd | C9: 29 | D9: Female | E9: West Pamelafurt | F9: West Virginia | G9: USA | H9: Bronze
A10: CUST1008 | B10: Melissa Howard | C10: 53 | D10: Female | E10: Maynardton | F10: New Hampshire | G10: USA | H10: Gold
A11: CUST1009 | B11: Ms. Maria Leach | C11: 64 | D11: Male | E11: Melissashire | F11: Pennsylvania | G11: USA | H11: Platinum
A12: CUST1010 | B12: Dominic Page | C12: 53 | D12: Male | E12: Port Michaelburgh | F12: Pennsylvania | G12: USA | H12: Bronze
A13: CUST1011 | B13: Brian Lopez | C13: 28 | D13: Female | E13: East Krista | F13: New York | G13: USA | H13: Gold
... A501: CUST1499 | B501: Philip Pennington | C501: 27 | D501: Female | E501: East Valerieview | F501: Oregon | G501: USA | H501: Platinum

Sheet Product_Dim
A1: Product_ID | B1: Product_Name | C1: Category | D1: Sub_Category | E1: Brand | F1: Cost | G1: Stock
A2: PROD0 | B2: Brother Laser Printer | C2: Electronics | D2: Computer | E2: Hunt Inc | F2: 112.42 | G2: 416
A3: PROD1 | B3: Men's Graphic T-Shirt | C3: Clothing | D3: Tops | E3: Terry-Moore | F3: 342.56 | G3: 181
A4: PROD2 | B4: Women's Casual Hoodie | C4: Clothing | D4: Outerwear | E4: Sims Inc | F4: 167.34 | G4: 352
A5: PROD3 | B5: Men's Running Jacket | C5: Clothing | D5: Outerwear | E5: Pineda Ltd | F5: 364.67 | G5: 452
A6: PROD4 | B6: Women's Yoga Pants | C6: Clothing | D6: Bottoms | E6: Gonzales-Davis | F6: 306.46 | G6: 487
A7: PROD5 | B7: Men's Leather Belt | C7: Clothing | D7: Accessories | E7: Baldwin, Garza and Gonzalez | F7: 261 | G7: 59
A8: PROD6 | B8: Herbal Face Moisturizer | C8: Beauty | D8: Skincare | E8: Davidson PLC | F8: 312.8 | G8: 350
A9: PROD7 | B9: LED Table Lamp | C9: Home | D9: Lighting | E9: Harrell LLC | F9: 218.86 | G9: 170
A10: PROD8 | B10: Wireless Bluetooth Earbuds | C10: Electronics | D10: Audio | E10: Perez-Johnston | F10: 439.07 | G10: 142
A11: PROD9 | B11: Adjustable Dumbbell Set | C11: Sports | D11: Fitness | E11: Hill PLC | F11: 495.72 | G11: 323
A12: PROD10 | B12: Ceramic Kitchen Bowl Set | C12: Home | D12: Kitchen | E12: Hamilton Group | F12: 298.86 | G12: 308
A13: PROD11 | B13: HD Smart TV Stick | C13: Electronics | D13: Accessories | E13: Gibson, Hobbs and Weaver | F13: 449.4 | G13: 0
... A101: PROD99 | B101: Stainless Steel Cookware Set | C101: Home | D101: Kitchen | E101: Campbell Ltd | F101: 201.41 | G101: 146

Sheet Store_Dim
A1: Store_ID | B1: Store_Name | C1: Region | D1: City | E1: Store_Type
A2: STORE0 | B2: Rivera-Warner | C2: East | D2: Washingtonfurt | E2: Flagship
A3: STORE1 | B3: Martinez, Adkins and Johnson | C3: North | D3: Danielmouth | E3: Flagship
A4: STORE2 | B4: Black-Horn | C4: South | D4: North Nancyview | E4: Outlet
A5: STORE3 | B5: Johnson-Wright | C5: North | D5: Hoodberg | E5: Outlet
A6: STORE4 | B6: Alexander Group | C6: South | D6: Port Sharon | E6: Online
A7: STORE5 | B7: Gray Ltd | C7: North | D7: New Michaelchester | E7: Outlet
A8: STORE6 | B8: Benson-Elliott | C8: East | D8: Port Josephberg | E8: Online
A9: STORE7 | B9: Martinez-Mullins | C9: South | D9: Williamsfurt | E9: Online
A10: STORE8 | B10: Bean, Jones and Park | C10: West | D10: Thompsonborough | E10: Online
A11: STORE9 | B11: Moore, Padilla and Butler | C11: South | D11: East Johnstad | E11: Flagship
A12: STORE10 | B12: Hill, Wagner and Ballard | C12: East | D12: East Davidville | E12: Online
... A21: STORE19 | B21: Mann-Austin | C21: East | D21: Vasquezborough | E21: Online

Sheet Sales_Fact
A1: Sales_ID | B1: Order_Date | C1: Customer_ID | D1: Product_ID | E1: Store_ID | F1: Quantity | G1: Unit_Price | H1: Discount | I1: Payment_Type | J1: Total_Amount
A2: SALE0 | B2: 45480 | C2: CUST1409 | D2: PROD97 | E2: STORE3 | F2: 1 | G2: 218.04 | H2: 0.09 | I2: Credit Card | J2: 198.4164
A3: SALE1 | B3: 45285 | C3: CUST1467 | D3: PROD74 | E3: STORE17 | F3: 3 | G3: 104.47 | H3: 0.27 | I3: PayPal | J3: 228.7893
A4: SALE2 | B4: 45446 | C4: CUST1056 | D4: PROD49 | E4: STORE8 | F4: 4 | G4: 914.05 | H4: 0.25 | I4: Credit Card | J4: 2742.15
A5: SALE3 | B5: 45259 | C5: CUST1346 | D5: PROD76 | E5: STORE8 | F5: 1 | G5: 921.51 | H5: 0.16 | I5: COD | J5: 774.0684
A6: SALE4 | B6: 45297 | C6: CUST1493 | D6: PROD59 | E6: STORE5 | F6: 3 | G6: 745.3 | H6: 0.18 | I6: Credit Card | J6: 1833.438
A7: SALE5 | B7: 45499 | C7: CUST1116 | D7: PROD15 | E7: STORE7 | F7: 3 | G7: 147.01 | H7: 0.19 | I7: COD | J7: 357.2343
A8: SALE6 | B8: 45850 | C8: CUST1016 | D8: PROD56 | E8: STORE4 | F8: 2 | G8: 785.31 | H8: 0.15 | I8: PayPal | J8: 1335.027
A9: SALE7 | B9: 45248 | C9: CUST1152 | D9: PROD70 | E9: STORE8 | F9: 4 | G9: 342.39 | H9: 0.23 | I9: PayPal | J9: 1054.5612
A10: SALE8 | B10: 45781 | C10: CUST1187 | D10: PROD99 | E10: STORE5 | F10: 3 | G10: 448.25 | H10: 0.07 | I10: PayPal | J10: 1250.6175 | L10: =Table1[[#This Row],[Unit_Price]]*(1-Table1[[#This Row],[Discount]]) -> 416.8725 | M10: =Table1[[#This Row],[Total_Amount]]/L10 -> 3
A11: SALE9 | B11: 45869 | C11: CUST1464 | D11: PROD33 | E11: STORE0 | F11: 2 | G11: 873.17 | H11: 0.23 | I11: PayPal | J11: 1344.6818 | L11: =Table1[[#This Row],[Unit_Price]]*(1-Table1[[#This Row],[Discount]]) -> 672.3409 | M11: =Table1[[#This Row],[Total_Amount]]/L11 -> 2
A12: SALE10 | B12: 45335 | C12: CUST1065 | D12: PROD24 | E12: STORE14 | F12: 1 | G12: 278.63 | H12: 0.07 | I12: Credit Card | J12: 259.1259 | L12: =Table1[[#This Row],[Unit_Price]]*(1-Table1[[#This Row],[Discount]]) -> 259.1259 | M12: =Table1[[#This Row],[Total_Amount]]/L12 -> 1
A13: SALE11 | B13: 45801 | C13: CUST1320 | D13: PROD39 | E13: STORE1 | F13: 4 | G13: 286.92 | H13: 0.17 | I13: Credit Card | J13: 952.5744 | L13: =Table1[[#This Row],[Unit_Price]]*(1-Table1[[#This Row],[Discount]]) -> 238.1436 | M13: =Table1[[#This Row],[Total_Amount]]/L13 -> 4
A14: SALE12 | B14: 45528 | C14: CUST1237 | D14: PROD88 | E14: STORE4 | F14: 4 | G14: 644.58 | H14: 0.01 | I14: Credit Card | J14: 2552.5368 | L14: =Table1[[#This Row],[Unit_Price]]*(1-Table1[[#This Row],[Discount]]) -> 638.1342 | M14: =Table1[[#This Row],[Total_Amount]]/L14 -> 4
A15: SALE13 | B15: 45875 | C15: CUST1443 | D15: PROD34 | E15: STORE16 | F15: 2 | G15: 316.9 | H15: 0.3 | I15: PayPal | J15: 443.66 | L15: =Table1[[#This Row],[Unit_Price]]*(1-Table1[[#This Row],[Discount]]) -> 221.83 | M15: =Table1[[#This Row],[Total_Amount]]/L15 -> 2
A16: SALE14 | B16: 45829 | C16: CUST1348 | D16: PROD24 | E16: STORE15 | F16: 4 | G16: 403.47 | H16: 0.29 | I16: PayPal | J16: 1145.8548 | L16: =Table1[[#This Row],[Unit_Price]]*(1-Table1[[#This Row],[Discount]]) -> 286.4637 | M16: =Table1[[#This Row],[Total_Amount]]/L16 -> 4
A17: SALE15 | B17: 45636 | C17: CUST1435 | D17: PROD36 | E17: STORE9 | F17: 3 | G17: 871.34 | H17: 0.04 | I17: COD | J17: 2509.4592 | L17: =Table1[[#This Row],[Unit_Price]]*(1-Table1[[#This Row],[Discount]]) -> 836.4864 | M17: =Table1[[#This Row],[Total_Amount]]/L17 -> 3
A18: SALE16 | B18: 45913 | C18: CUST1276 | D18: PROD65 | E18: STORE19 | F18: 2 | G18: 451.98 | H18: 0.25 | I18: Credit Card | J18: 677.97 | L18: =Table1[[#This Row],[Unit_Price]]*(1-Table1[[#This Row],[Discount]]) -> 338.985 | M18: =Table1[[#This Row],[Total_Amount]]/L18 -> 2
A19: SALE17 | B19: 45637 | C19: CUST1079 | D19: PROD27 | E19: STORE4 | F19: 2 | G19: 502.69 | H19: 0.23 | I19: Credit Card | J19: 774.1426 | L19: =Table1[[#This Row],[Unit_Price]]*(1-Table1[[#This Row],[Discount]]) -> 387.0713 | M19: =Table1[[#This Row],[Total_Amount]]/L19 -> 2
A20: SALE18 | B20: 45517 | C20: CUST1094 | D20: PROD39 | E20: STORE4 | F20: 2 | G20: 559.23 | H20: 0.25 | I20: COD | J20: 838.845 | L20: =Table1[[#This Row],[Unit_Price]]*(1-Table1[[#This Row],[Discount]]) -> 419.4225 | M20: =Table1[[#This Row],[Total_Amount]]/L20 -> 2
A21: SALE19 | B21: 45369 | C21: CUST1239 | D21: PROD60 | E21: STORE13 | F21: 4 | G21: 464.18 | H21: 0.04 | I21: COD | J21: 1782.4512 | L21: =Table1[[#This Row],[Unit_Price]]*(1-Table1[[#This Row],[Discount]]) -> 445.6128 | M21: =Table1[[#This Row],[Total_Amount]]/L21 -> 4
... A27: SALE25 | B27: 45552 | C27: CUST1381 | D27: PROD5 | E27: STORE3 | F27: 4 | G27: 852.71 | H27: 0.14 | I27: PayPal | J27: 2933.3224 | L27: =Table1[[#This Row],[Unit_Price]]*(1-Table1[[#This Row],[Discount]]) -> 733.3306 | M27: =Table1[[#This Row],[Total_Amount]]/L27 -> 4
A28: SALE26 | B28: 45294 | C28: CUST1213 | D28: PROD98 | E28: STORE8 | F28: 4 | G28: 156.16 | H28: =1-(Table1[[#This Row],[Total_Amount]]/(Table1[[#This Row],[Unit_Price]]*Table1[[#This Row],[Quantity]])) -> 0.04 | I28: Credit Card | J28: 599.6544 | L28: =Table1[[#This Row],[Unit_Price]]*(1-Table1[[#This Row],[Discount]]) -> 149.9136 | M28: =Table1[[#This Row],[Total_Amount]]/L28 -> 4
A29: SALE27 | B29: 45710 | C29: CUST1200 | D29: PROD77 | E29: STORE8 | F29: 3 | G29: 815.49 | H29: 0.17 | I29: Credit Card | J29: 2030.5701 | L29: =Table1[[#This Row],[Unit_Price]]*(1-Table1[[#This Row],[Discount]]) -> 676.8567 | M29: =Table1[[#This Row],[Total_Amount]]/L29 -> 3
A30: SALE28 | B30: 45923 | C30: CUST1148 | D30: PROD13 | E30: STORE2 | F30: 2 | G30: 74.21 | H30: 0.11 | I30: PayPal | J30: 132.0938 | L30: =Table1[[#This Row],[Unit_Price]]*(1-Table1[[#This Row],[Discount]]) -> 66.0469 | M30: =Table1[[#This Row],[Total_Amount]]/L30 -> 2
A31: SALE29 | B31: 45302 | C31: CUST1348 | D31: PROD99 | E31: STORE3 | F31: 4 | G31: 451.67 | H31: 0.15 | I31: Credit Card | J31: 1535.678 | L31: =Table1[[#This Row],[Unit_Price]]*(1-Table1[[#This Row],[Discount]]) -> 383.9195 | M31: =Table1[[#This Row],[Total_Amount]]/L31 -> 4
A32: SALE30 | B32: 45217 | C32: CUST1028 | D32: PROD5 | E32: STORE19 | F32: 1 | G32: 429.38 | H32: 0.13 | I32: PayPal | J32: 373.5606 | L32: =Table1[[#This Row],[Unit_Price]]*(1-Table1[[#This Row],[Discount]]) -> 373.5606 | M32: =Table1[[#This Row],[Total_Amount]]/L32 -> 1
A33: SALE31 | B33: 45593 | C33: CUST1412 | D33: PROD53 | E33: STORE12 | F33: 2 | G33: 148.96 | H33: 0.03 | I33: COD | J33: 288.9824 | L33: =Table1[[#This Row],[Unit_Price]]*(1-Table1[[#This Row],[Discount]]) -> 144.4912 | M33: =Table1[[#This Row],[Total_Amount]]/L33 -> 2
A34: SALE32 | B34: 45597 | C34: CUST1398 | D34: PROD75 | E34: STORE8 | F34: 4 | G34: 313.83 | H34: 0.08 | I34: Credit Card | J34: 1154.8944 | L34: =Table1[[#This Row],[Unit_Price]]*(1-Table1[[#This Row],[Discount]]) -> 288.7236 | M34: =Table1[[#This Row],[Total_Amount]]/L34 -> 4
A35: SALE33 | B35: 45620 | C35: CUST1453 | D35: PROD12 | E35: STORE6 | F35: 2 | G35: 717.31 | H35: 0.15 | I35: Credit Card | J35: 1219.427 | L35: =Table1[[#This Row],[Unit_Price]]*(1-Table1[[#This Row],[Discount]]) -> 609.7135 | M35: =Table1[[#This Row],[Total_Amount]]/L35 -> 2
A36: SALE34 | B36: 45215 | C36: CUST1344 | D36: PROD79 | E36: STORE1 | F36: 3 | G36: 873.22 | H36: 0.18 | I36: Credit Card | J36: 2148.1212 | L36: =Table1[[#This Row],[Unit_Price]]*(1-Table1[[#This Row],[Discount]]) -> 716.0404 | M36: =Table1[[#This Row],[Total_Amount]]/L36 -> 3
A37: SALE35 | B37: 45878 | C37: CUST1218 | D37: PROD16 | E37: STORE3 | F37: 4 | G37: 109.36 | H37: 0.19 | I37: COD | J37: 354.3264 | L37: =Table1[[#This Row],[Unit_Price]]*(1-Table1[[#This Row],[Discount]]) -> 88.5816 | M37: =Table1[[#This Row],[Total_Amount]]/L37 -> 4
A38: SALE36 | B38: 45635 | C38: CUST1086 | D38: PROD5 | E38: STORE7 | F38: 3 | G38: 559.52 | H38: 0.16 | I38: PayPal | J38: 1409.9904 | L38: =Table1[[#This Row],[Unit_Price]]*(1-Table1[[#This Row],[Discount]]) -> 469.9968 | M38: =Table1[[#This Row],[Total_Amount]]/L38 -> 3
A39: SALE37 | B39: 45329 | C39: CUST1492 | D39: PROD10 | E39: STORE17 | F39: 3 | G39: 121.76 | H39: 0.27 | I39: PayPal | J39: 266.6544 | L39: =Table1[[#This Row],[Unit_Price]]*(1-Table1[[#This Row],[Discount]]) -> 88.8848 | M39: =Table1[[#This Row],[Total_Amount]]/L39 -> 3
A40: SALE38 | B40: 45378 | C40: CUST1189 | D40: PROD33 | E40: STORE13 | F40: 4 | G40: 735.32 | H40: 0.06 | I40: COD | J40: 2764.8032 | L40: =Table1[[#This Row],[Unit_Price]]*(1-Table1[[#This Row],[Discount]]) -> 691.2008 | M40: =Table1[[#This Row],[Total_Amount]]/L40 -> 4
... A45: SALE43 | B45: 45677 | C45: CUST1084 | D45: PROD33 | E45: STORE17 | F45: 3 | G45: 863.11 | H45: 0.28 | I45: PayPal | J45: 1864.3176 | L45: =Table1[[#This Row],[Unit_Price]]*(1-Table1[[#This Row],[Discount]]) -> 621.4392 | M45: =Table1[[#This Row],[Total_Amount]]/L45 -> 3
A46: SALE44 | B46: 45538 | C46: CUST1203 | D46: PROD43 | E46: STORE12 | F46: 2 | G46: 209.32 | H46: 0.23 | I46: COD | J46: 322.3528
A47: SALE45 | B47: 45606 | C47: CUST1470 | D47: PROD59 | E47: STORE8 | F47: 4 | G47: 288.6 | H47: 0.09 | I47: PayPal | J47: 1050.504
A48: SALE46 | B48: 45570 | C48: CUST1070 | D48: PROD78 | E48: STORE16 | F48: 1 | G48: 418.69 | H48: 0.06 | I48: PayPal | J48: 393.5686
A49: SALE47 | B49: 45466 | C49: CUST1008 | D49: PROD30 | E49: STORE11 | F49: 1 | G49: 135.78 | H49: 0.14 | I49: PayPal | J49: 116.7708
A50: SALE48 | B50: 45218 | C50: CUST1203 | D50: PROD44 | E50: STORE17 | F50: 1 | G50: 517.13 | H50: 0.28 | I50: Credit Card | J50: 372.3336
A51: SALE49 | B51: 45607 | C51: CUST1420 | D51: PROD21 | E51: STORE16 | F51: 2 | G51: 384.66 | H51: 0.08 | I51: COD | J51: 707.7744
A52: SALE50 | B52: 45291 | C52: CUST1070 | D52: PROD52 | E52: STORE9 | F52: 3 | G52: 83.7 | H52: 0.24 | I52: PayPal | J52: 190.836
A53: SALE51 | B53: 45689 | C53: CUST1142 | D53: PROD69 | E53: STORE7 | F53: 3 | G53: 76.57 | H53: 0.26 | I53: Credit Card | J53: 169.9854
A54: SALE52 | B54: 45894 | C54: CUST1148 | D54: PROD89 | E54: STORE6 | F54: 3 | G54: =Table1[[#This Row],[Total_Amount]]/3 -> 162.0211 | H54: 0 | I54: Credit Card | J54: 486.0633
A55: SALE53 | B55: 45677 | C55: CUST1324 | D55: PROD20 | E55: STORE8 | F55: 1 | G55: 900.35 | H55: 0.13 | I55: COD | J55: 783.3045
A56: SALE54 | B56: 45706 | C56: CUST1095 | D56: PROD40 | E56: STORE10 | F56: 4 | G56: 428.09 | H56: 0.07 | I56: Credit Card | J56: 1592.4948
A57: SALE55 | B57: 45589 | C57: CUST1416 | D57: PROD49 | E57: STORE11 | F57: 2 | G57: 559.71 | H57: 0.3 | I57: COD | J57: 783.594
A58: SALE56 | B58: 45282 | C58: CUST1080 | D58: PROD34 | E58: STORE6 | F58: 2 | G58: 833.7 | H58: 0.06 | I58: PayPal | J58: 1567.356
A59: SALE57 | B59: 45462 | C59: CUST1467 | D59: PROD47 | E59: STORE14 | F59: 2 | G59: 680.16 | H59: 0.28 | I59: Credit Card | J59: 979.4304
A60: SALE58 | B60: 45633 | C60: CUST1404 | D60: PROD15 | E60: STORE7 | F60: 4 | G60: 733.42 | H60: =1-(Table1[[#This Row],[Total_Amount]]/(Table1[[#This Row],[Unit_Price]]*Table1[[#This Row],[Quantity]])) -> 0.13 | I60: PayPal | J60: 2552.3016
A61: SALE59 | B61: 45257 | C61: CUST1367 | D61: PROD89 | E61: STORE11 | F61: 1 | G61: 996.33 | H61: 0.23 | I61: PayPal | J61: 767.1741
A62: SALE60 | B62: 45854 | C62: CUST1408 | D62: PROD31 | E62: STORE10 | F62: 1 | G62: 198.83 | H62: 0.09 | I62: COD | J62: 180.9353
A63: SALE61 | B63: 45716 | C63: CUST1239 | D63: PROD19 | E63: STORE7 | F63: 1 | G63: 374.92 | H63: 0.18 | I63: PayPal | J63: 307.4344
A64: SALE62 | B64: 45515 | C64: CUST1464 | D64: PROD93 | E64: STORE16 | F64: 1 | G64: 468.94 | H64: 0.12 | I64: Credit Card | J64: 412.6672
A65: SALE63 | B65: 45927 | C65: CUST1126 | D65: PROD89 | E65: STORE12 | F65: 2 | G65: 121.37 | H65: 0.05 | I65: Credit Card | J65: 230.603
A66: SALE64 | B66: 45914 | C66: CUST1255 | D66: PROD53 | E66: STORE10 | F66: 3 | G66: 480.06 | H66: 0.01 | I66: Credit Card | J66: =(Table1[[#This Row],[Unit_Price]]*Table1[[#This Row],[Quantity]])*(1-Table1[[#This Row],[Discount]]) -> 1425.7782
A67: SALE65 | B67: 45290 | C67: CUST1162 | D67: PROD99 | E67: STORE17 | F67: 2 | G67: 856.57 | H67: 0.24 | I67: Credit Card | J67: 1301.9864
A68: SALE66 | B68: 45213 | C68: CUST1269 | D68: PROD77 | E68: STORE2 | F68: 4 | G68: 814.25 | H68: 0.18 | I68: Credit Card | J68: 2670.74
A69: SALE67 | B69: 45255 | C69: CUST1483 | D69: PROD12 | E69: STORE2 | F69: 1 | G69: 989.17 | H69: 0.2 | I69: PayPal | J69: 791.336
A70: SALE68 | B70: 45270 | C70: CUST1372 | D70: PROD72 | E70: STORE10 | F70: 4 | G70: 62.48 | H70: 0.18 | I70: Credit Card | J70: 204.9344
A71: SALE69 | B71: 45897 | C71: CUST1423 | D71: PROD13 | E71: STORE16 | F71: 4 | G71: 561.24 | H71: 0.24 | I71: Credit Card | J71: 1706.1696
A72: SALE70 | B72: 45849 | C72: CUST1058 | D72: PROD60 | E72: STORE5 | F72: 3 | G72: 92.24 | H72: 0.28 | I72: COD | J72: =(Table1[[#This Row],[Unit_Price]]*Table1[[#This Row],[Quantity]])*(1-Table1[[#This Row],[Discount]]) -> 199.2384
A73: SALE71 | B73: 45889 | C73: CUST1168 | D73: PROD72 | E73: STORE1 | F73: 2 | G73: 668.3 | H73: 0.07 | I73: Credit Card | J73: 1243.038
A74: SALE72 | B74: 45533 | C74: CUST1409 | D74: PROD38 | E74: STORE5 | F74: 1 | G74: 553.82 | H74: 0.09 | I74: Credit Card | J74: 503.9762
A75: SALE73 | B75: 45626 | C75: CUST1037 | D75: PROD45 | E75: STORE11 | F75: 2 | G75: 556.43 | H75: 0.13 | I75: Credit Card | J75: 968.1882
A76: SALE74 | B76: 45942 | C76: CUST1273 | D76: PROD20 | E76: STORE8 | F76: 1 | G76: 184.98 | H76: 0.1 | I76: COD | J76: 166.482
A77: SALE75 | B77: 45500 | C77: CUST1035 | D77: PROD97 | E77: STORE12 | F77: 4 | G77: 700.18 | H77: 0.23 | I77: Credit Card | J77: 2156.5544
A78: SALE76 | B78: 45285 | C78: CUST1019 | D78: PROD76 | E78: STORE10 | F78: 2 | G78: 686.31 | H78: 0.25 | I78: Credit Card | J78: 1029.465
A79: SALE77 | B79: 45800 | C79: CUST1007 | D79: PROD67 | E79: STORE15 | F79: 1 | G79: 687.82 | H79: 0.27 | I79: COD | J79: 502.1086
A80: SALE78 | B80: 45609 | C80: CUST1221 | D80: PROD83 | E80: STORE8 | F80: 2 | G80: 900.55 | H80: 0.16 | I80: Credit Card | J80: 1512.924
A81: SALE79 | B81: 45268 | C81: CUST1115 | D81: PROD21 | E81: STORE2 | F81: 1 | G81: 341.17 | H81: 0.15 | I81: Credit Card | J81: 289.9945
A82: SALE80 | B82: 45885 | C82: CUST1176 | D82: PROD52 | E82: STORE8 | F82: 1 | G82: 442.27 | H82: 0.06 | I82: COD | J82: 415.7338
A83: SALE81 | B83: 45616 | C83: CUST1253 | D83: PROD71 | E83: STORE9 | F83: 1 | G83: 363.73 | H83: 0.25 | I83: PayPal | J83: 272.7975
A84: SALE82 | B84: 45518 | C84: CUST1378 | D84: PROD91 | E84: STORE17 | F84: 2 | G84: 601.33 | H84: 0.16 | I84: PayPal | J84: 1010.2344
A85: SALE83 | B85: 45427 | C85: CUST1403 | D85: PROD17 | E85: STORE18 | F85: 4 | G85: 34.39 | H85: 0.03 | I85: PayPal | J85: 133.4332
A86: SALE84 | B86: 45268 | C86: CUST1423 | D86: PROD46 | E86: STORE17 | F86: 1 | G86: 773.57 | H86: 0.05 | I86: COD | J86: =(Table1[[#This Row],[Unit_Price]]*Table1[[#This Row],[Quantity]])*(1-Table1[[#This Row],[Discount]]) -> 734.8915
A87: SALE85 | B87: 45282 | C87: CUST1054 | D87: PROD88 | E87: STORE7 | F87: 4 | G87: 127.1 | H87: 0.24 | I87: COD | J87: 386.384
A88: SALE86 | B88: 45545 | C88: CUST1303 | D88: PROD20 | E88: STORE3 | F88: 3 | G88: 899.58 | H88: 0.28 | I88: PayPal | J88: 1943.0928
A89: SALE87 | B89: 45755 | C89: CUST1327 | D89: PROD1 | E89: STORE10 | F89: 3 | G89: 964.39 | H89: 0.04 | I89: Credit Card | J89: 2777.4432
A90: SALE88 | B90: 45588 | C90: CUST1183 | D90: PROD38 | E90: STORE0 | F90: 2 | G90: 217.83 | H90: 0.14 | I90: PayPal | J90: 374.6676
A91: SALE89 | B91: 45848 | C91: CUST1143 | D91: PROD17 | E91: STORE1 | F91: 4 | G91: 187.71 | H91: 0.06 | I91: COD | J91: 705.7896
A92: SALE90 | B92: 45577 | C92: CUST1010 | D92: PROD33 | E92: STORE18 | F92: 2 | G92: 350.12 | H92: 0.12 | I92: COD | J92: 616.2112
A93: SALE91 | B93: 45312 | C93: CUST1406 | D93: PROD16 | E93: STORE1 | F93: 4 | G93: 102.19 | H93: 0.17 | I93: PayPal | J93: 339.2708
A94: SALE92 | B94: 45350 | C94: CUST1007 | D94: PROD86 | E94: STORE4 | F94: 1 | G94: 696.53 | H94: 0.17 | I94: Credit Card | J94: 578.1199
A95: SALE93 | B95: 45657 | C95: CUST1065 | D95: PROD19 | E95: STORE4 | F95: 2 | G95: 327.52 | H95: 0.15 | I95: PayPal | J95: 556.784
A96: SALE94 | B96: 45530 | C96: CUST1298 | D96: PROD97 | E96: STORE19 | F96: 2 | G96: 569.36 | H96: 0.01 | I96: PayPal | J96: =(Table1[[#This Row],[Unit_Price]]*Table1[[#This Row],[Quantity]])*(1-Table1[[#This Row],[Discount]]) -> 1127.3328
A97: SALE95 | B97: 45556 | C97: CUST1321 | D97: PROD99 | E97: STORE6 | F97: 2 | G97: 68.29 | H97: 0.14 | I97: COD | J97: 117.4588
A98: SALE96 | B98: 45523 | C98: CUST1244 | D98: PROD50 | E98: STORE10 | F98: 1 | G98: 842.9 | H98: 0.06 | I98: COD | J98: 792.326
A99: SALE97 | B99: 45587 | C99: CUST1287 | D99: PROD3 | E99: STORE3 | F99: 3 | G99: 751.94 | H99: 0.26 | I99: PayPal | J99: 1669.3068
A100: SALE98 | B100: 45580 | C100: CUST1131 | D100: PROD56 | E100: STORE7 | F100: 4 | G100: 476.28 | H100: 0.17 | I100: Credit Card | J100: 1581.2496
A101: SALE99 | B101: 45479 | C101: CUST1325 | D101: PROD54 | E101: STORE3 | F101: 3 | G101: 541.99 | H101: 0.24 | I101: COD | J101: 1235.7372
A102: SALE100 | B102: 45677 | C102: CUST1369 | D102: PROD33 | E102: STORE5 | F102: 2 | G102: 401.5 | H102: 0.18 | I102: Credit Card | J102: 658.46
A103: SALE101 | B103: 45453 | C103: CUST1084 | D103: PROD25 | E103: STORE13 | F103: 3 | G103: 359.56 | H103: 0.17 | I103: PayPal | J103: 895.3044
A104: SALE102 | B104: 45552 | C104: CUST1097 | D104: PROD80 | E104: STORE12 | F104: 2 | G104: 471.88 | H104: 0.24 | I104: PayPal | J104: 717.2576
A105: SALE103 | B105: 45907 | C105: CUST1182 | D105: PROD34 | E105: STORE4 | F105: 4 | G105: 925.19 | H105: 0.19 | I105: PayPal | J105: 2997.6156
A106: SALE104 | B106: 45330 | C106: CUST1029 | D106: PROD86 | E106: STORE11 | F106: 2 | G106: 879.63 | H106: 0.07 | I106: COD | J106: 1636.1118
A107: SALE105 | B107: 45214 | C107: CUST1002 | D107: PROD79 | E107: STORE17 | F107: 2 | G107: 418.23 | H107: 0.28 | I107: Credit Card | J107: 602.2512
A108: SALE106 | B108: 45891 | C108: CUST1269 | D108: PROD19 | E108: STORE18 | F108: 3 | G108: 551.72 | H108: 0.03 | I108: COD | J108: 1605.5052
... A260: SALE258 | B260: 45300 | C260: CUST1136 | D260: PROD35 | E260: STORE17 | F260: 1 | G260: 222.94 | H260: 0.19 | I260: Credit Card | J260: 180.5814
...

Sheet Analysis- Unit Price
A1: Unit Price Analysis
A3: Mean | B3: 513.58279
A4: Standard Error | B4: 6.3134988
A5: Median | B5: 522.43
A6: Mode | B6: 871.34
A7: Standard Deviation | B7: 282.34825
A8: Sample Variance | B8: 79720.534
A9: Kurtosis | B9: -1.1931883
A10: Skewness | B10: -0.034813907
A11: Range | B11: 979.8
A12: Minimum | B12: 20.09
A13: Maximum | B13: 999.89
A14: Sum | B14: 1027165.6
... A16: Confidence Level(95.0%) | B16: 12.381727

Sheet Histogram - Total Amount
A1: Bin | B1: Frequency | C1: Cumulative % | D1: Bin | E1: Frequency | F1: Cumulative %
A2: 18.459 | B2: 1 | C2: 0.0005 | D2: 637.28824 | E2: 124 | F2: 0.062
A3: 106.86318 | B3: 99 | C3: 0.05 | D3: 372.07571 | E3: 115 | F3: 0.1195
A4: 195.26735 | B4: 108 | C4: 0.104 | D4: 195.26735 | E4: 108 | F4: 0.1735
A5: 283.67153 | B5: 105 | C5: 0.1565 | D5: 548.88406 | E5: 108 | F5: 0.2275
A6: 372.07571 | B6: 115 | C6: 0.214 | D6: 283.67153 | E6: 105 | F6: 0.28
A7: 460.47989 | B7: 103 | C7: 0.2655 | D7: 460.47989 | E7: 103 | F7: 0.3315
A8: 548.88406 | B8: 108 | C8: 0.3195 | D8: 106.86318 | E8: 99 | F8: 0.381
A9: 637.28824 | B9: 124 | C9: 0.3815 | D9: 814.0966 | E9: 97 | F9: 0.4295
A10: 725.69242 | B10: 91 | C10: 0.427 | D10: 725.69242 | E10: 91 | F10: 0.475
A11: 814.0966 | B11: 97 | C11: 0.4755 | D11: 902.50077 | E11: 77 | F11: 0.5135
A12: 902.50077 | B12: 77 | C12: 0.514 | D12: 990.90495 | E12: 72 | F12: 0.5495
A13: 990.90495 | B13: 72 | C13: 0.55 | D13: 1256.1175 | E13: 71 | F13: 0.585
... A45: 3819.8386 | B45: 3 | C45: 0.9995 | D45: 3731.4344 | E45: 1 | F45: 0.9995
A46: More | B46: 1 | C46: 1 | D46: More | E46: 1 | F46: 1

Sheet Analysis - Total Amount
A1: Column1
A3: Mean | B3: 1087.1973
A4: Standard Error | B4: 18.327237
A5: Median | B5: 868.7182
A6: Mode | B6: #N/A
A7: Standard Deviation | B7: 819.61896
A8: Sample Variance | B8: 671775.25
A9: Kurtosis | B9: 0.045826153
A10: Skewness | B10: 0.87904704
A11: Range | B11: 3889.7838
A12: Minimum | B12: 18.459
A13: Maximum | B13: 3908.2428
A14: Sum | B14: 2174394.7
A15: Count | B15: 2000
A16: Largest(1) | B16: 3908.2428
A17: Smallest(1) | B17: 18.459
A18: Confidence Level(95.0%) | B18: 35.942487

Sheet Sales_Fact (2)
A1: Sales_ID | B1: Order_Date | C1: Customer_ID | D1: Product_ID | E1: Store_ID | F1: Quantity | G1: Unit_Price | H1: Discount | I1: Payment_Type | J1: Total_Amount | K1: Name | L1: Age | M1: Age Group | N1: Gender | O1: City | P1: State | Q1: Country | R1: Loyalty_Level | S1: Store_Name | T1: Region | U1: City2 | V1: Store_Type | W1: Product_Name | X1: Category | Y1: Sub_Category | Z1: Brand | AA1: Cost | AB1: Stock
A2: SALE0 | B2: 45480 | C2: CUST1409 | D2: PROD97 | E2: STORE3 | F2: 1 | G2: 218.04 | H2: 0.09 | I2: Credit Card | J2: 198.4164 | K2: =_xlfn.XLOOKUP(Table17[[#This Row],[Customer_ID]],Customer_Dim!A:A,Customer_Dim!B:B,"False Data") -> Sarah Smith | L2: =_xlfn.XLOOKUP(Table17[[#This Row],[Customer_ID]],Customer_Dim!A:A,Customer_Dim!C:C,"False Data") -> 55 | M2: {=_xlfn.IFS(Table9[[#This Row],[Age]]<=35,"Youth",Table9[[#This Row],[Age]]<=55,"Adult",Table9[[#This Row],[Age]]>55,"Senior")} -> Adult | N2: =_xlfn.XLOOKUP(Table17[[#This Row],[Customer_ID]],Customer_Dim!A:A,Customer_Dim!D:D,"False Data") -> Male | O2: =_xlfn.XLOOKUP(Table17[[#This Row],[Customer_ID]],Customer_Dim!A:A,Customer_Dim!E:E,"False Data") -> Kathleenport | P2: =_xlfn.XLOOKUP(Table17[[#This Row],[Customer_ID]],Customer_Dim!A:A,Customer_Dim!F:F,"False Data") -> Wyoming | Q2: =_xlfn.XLOOKUP(Table17[[#This Row],[Customer_ID]],Customer_Dim!A:A,Customer_Dim!G:G,"False Data") -> USA | R2: =_xlfn.XLOOKUP(Table17[[#This Row],[Customer_ID]],Customer_Dim!A:A,Customer_Dim!H:H,"False Data") -> Gold | S2: =_xlfn.XLOOKUP(Table17[[#This Row],[Store_ID]],Store_Dim!A:A,Store_Dim!B:B) -> Johnson-Wright | T2: =_xlfn.XLOOKUP(Table17[[#This Row],[Store_ID]],Store_Dim!A:A,Store_Dim!C:C) -> North | U2: =_xlfn.XLOOKUP(Table17[[#This Row],[Store_ID]],Store_Dim!A:A,Store_Dim!D:D) -> Hoodberg | V2: =_xlfn.XLOOKUP(Table17[[#This Row],[Store_ID]],Store_Dim!A:A,Store_Dim!E:E) -> Outlet | W2: =_xlfn.XLOOKUP(Table17[[#This Row],[Product_ID]],Product_Dim!A:A,Product_Dim!B:B) -> Cricket Bat | X2: =_xlfn.XLOOKUP(Table17[[#This Row],[Product_ID]],Product_Dim!A:A,Product_Dim!C:C) -> Sports | Y2: =_xlfn.XLOOKUP(Table17[[#This Row],[Product_ID]],Product_Dim!A:A,Product_Dim!D:D) -> Team Sports | Z2: =_xlfn.XLOOKUP(Table17[[#This Row],[Product_ID]],Product_Dim!A:A,Product_Dim!E:E) -> Khan LLC | AA2: =_xlfn.XLOOKUP(Table17[[#This Row],[Product_ID]],Product_Dim!A:A,Product_Dim!F:F) -> 245.98 | AB2: =_xlfn.XLOOKUP(Table17[[#This Row],[Product_ID]],Product_Dim!A:A,Product_Dim!G:G) -> 471
A3: SALE1 | B3: 45285 | C3: CUST1467 | D3: PROD74 | E3: STORE17 | F3: 3 | G3: 104.47 | H3: 0.27 | I3: PayPal | J3: 228.7893 | K3: =_xlfn.XLOOKUP(Table17[[#This Row],[Customer_ID]],Customer_Dim!A:A,Customer_Dim!B:B,"False Data") -> Michael Foley | L3: =_xlfn.XLOOKUP(Table17[[#This Row],[Customer_ID]],Customer_Dim!A:A,Customer_Dim!C:C,"False Data") -> 63 | M3: {=_xlfn.IFS(Table9[[#This Row],[Age]]<=35,"Youth",Table9[[#This Row],[Age]]<=55,"Adult",Table9[[#This Row],[Age]]>55,"Senior")} -> Senior | N3: =_xlfn.XLOOKUP(Table17[[#This Row],[Customer_ID]],Customer_Dim!A:A,Customer_Dim!D:D,"False Data") -> Female | O3: =_xlfn.XLOOKUP(Table17[[#This Row],[Customer_ID]],Customer_Dim!A:A,Customer_Dim!E:E,"False Data") -> Oneillfurt | P3: =_xlfn.XLOOKUP(Table17[[#This Row],[Customer_ID]],Customer_Dim!A:A,Customer_Dim!F:F,"False Data") -> Vermont | Q3: =_xlfn.XLOOKUP(Table17[[#This Row],[Customer_ID]],Customer_Dim!A:A,Customer_Dim!G:G,"False Data") -> USA | R3: =_xlfn.XLOOKUP(Table17[[#This Row],[Customer_ID]],Customer_Dim!A:A,Customer_Dim!H:H,"False Data") -> Gold | S3: =_xlfn.XLOOKUP(Table17[[#This Row],[Store_ID]],Store_Dim!A:A,Store_Dim!B:B) -> Holloway Ltd | T3: =_xlfn.XLOOKUP(Table17[[#This Row],[Store_ID]],Store_Dim!A:A,Store_Dim!C:C) -> North | U3: =_xlfn.XLOOKUP(Table17[[#This Row],[Store_ID]],Store_Dim!A:A,Store_Dim!D:D) -> Bensonhaven | V3: =_xlfn.XLOOKUP(Table17[[#This Row],[Store_ID]],Store_Dim!A:A,Store_Dim!E:E) -> Flagship | W3: =_xlfn.XLOOKUP(Table17[[#This Row],[Product_ID]],Product_Dim!A:A,Product_Dim!B:B) -> Bluetooth Car Audio System | X3: =_xlfn.XLOOKUP(Table17[[#This Row],[Product_ID]],Product_Dim!A:A,Product_Dim!C:C) -> Electronics | Y3: =_xlfn.XLOOKUP(Table17[[#This Row],[Product_ID]],Product_Dim!A:A,Product_Dim!D:D) -> Audio | Z3: =_xlfn.XLOOKUP(Table17[[#This Row],[Product_ID]],Product_Dim!A:A,Product_Dim!E:E) -> Bruce-Bowen | AA3: =_xlfn.XLOOKUP(Table17[[#This Row],[Product_ID]],Product_Dim!A:A,Product_Dim!F:F) -> 403.71 | AB3: =_xlfn.XLOOKUP(Table17[[#This Row],[Product_ID]],Product_Dim!A:A,Product_Dim!G:G) -> 159
A4: SALE2 | B4: 45446 | C4: CUST1056 | D4: PROD49 | E4: STORE8 | F4: 4 | G4: 914.05 | H4: 0.25 | I4: Credit Card | J4: 2742.15 | K4: =_xlfn.XLOOKUP(Table17[[#This Row],[Customer_ID]],Customer_Dim!A:A,Customer_Dim!B:B,"False Data") -> Christopher Sutton | L4: =_xlfn.XLOOKUP(Table17[[#This Row],[Customer_ID]],Customer_Dim!A:A,Customer_Dim!C:C,"False Data") -> 49 | M4: {=_xlfn.IFS(Table9[[#This Row],[Age]]<=35,"Youth",Table9[[#This Row],[Age]]<=55,"Adult",Table9[[#This Row],[Age]]>55,"Senior")} -> Adult | N4: =_xlfn.XLOOKUP(Table17[[#This Row],[Customer_ID]],Customer_Dim!A:A,Customer_Dim!D:D,"False Data") -> Female | O4: =_xlfn.XLOOKUP(Table17[[#This Row],[Customer_ID]],Customer_Dim!A:A,Customer_Dim!E:E,"False Data") -> Deborahberg | P4: =_xlfn.XLOOKUP(Table17[[#This Row],[Customer_ID]],Customer_Dim!A:A,Customer_Dim!F:F,"False Data") -> Pennsylvania | Q4: =_xlfn.XLOOKUP(Table17[[#This Row],[Customer_ID]],Customer_Dim!A:A,Customer_Dim!G:G,"False Data") -> USA | R4: =_xlfn.XLOOKUP(Table17[[#This Row],[Customer_ID]],Customer_Dim!A:A,Customer_Dim!H:H,"False Data") -> Gold | S4: =_xlfn.XLOOKUP(Table17[[#This Row],[Store_ID]],Store_Dim!A:A,Store_Dim!B:B) -> Bean, Jones and Park | T4: =_xlfn.XLOOKUP(Table17[[#This Row],[Store_ID]],Store_Dim!A:A,Store_Dim!C:C) -> West | U4: =_xlfn.XLOOKUP(Table17[[#This Row],[Store_ID]],Store_Dim!A:A,Store_Dim!D:D) -> Thompsonborough | V4: =_xlfn.XLOOKUP(Table17[[#This Row],[Store_ID]],Store_Dim!A:A,Store_Dim!E:E) -> Online | W4: =_xlfn.XLOOKUP(Table17[[#This Row],[Product_ID]],Product_Dim!A:A,Product_Dim!B:B) -> Men's Roll-On Perfume | X4: =_xlfn.XLOOKUP(Table17[[#This Row],[Product_ID]],Product_Dim!A:A,Product_Dim!C:C) -> Beauty | Y4: =_xlfn.XLOOKUP(Table17[[#This Row],[Product_ID]],Product_Dim!A:A,Product_Dim!D:D) -> Fragrance | Z4: =_xlfn.XLOOKUP(Table17[[#This Row],[Product_ID]],Product_Dim!A:A,Product_Dim!E:E) -> Sullivan and Sons | AA4: =_xlfn.XLOOKUP(Table17[[#This Row],[Product_ID]],Product_Dim!A:A,Product_Dim!F:F) -> 43.29 | AB4: =_xlfn.XLOOKUP(Table17[[#This Row],[Product_ID]],Product_Dim!A:A,Product_Dim!G:G) -> 267
A5: SALE3 | B5: 45259 | C5: CUST1346 | D5: PROD76 | E5: STORE8 | F5: 1 | G5: 921.51 | H5: 0.16 | I5: COD | J5: 774.0684 | K5: =_xlfn.XLOOKUP(Table17[[#This Row],[Customer_ID]],Customer_Dim!A:A,Customer_Dim!B:B,"False Data") -> John Jordan | L5: =_xlfn.XLOOKUP(Table17[[#This Row],[Customer_ID]],Customer_Dim!A:A,Customer_Dim!C:C,"False Data") -> 58 | M5: {=_xlfn.IFS(Table9[[#This Row],[Age]]<=35,"Youth",Table9[[#This Row],[Age]]<=55,"Adult",Table9[[#This Row],[Age]]>55,"Senior")} -> Senior | N5: =_xlfn.XLOOKUP(Table17[[#This Row],[Customer_ID]],Customer_Dim!A:A,Customer_Dim!D:D,"False Data") -> Female | O5: =_xlfn.XLOOKUP(Table17[[#This Row],[Customer_ID]],Customer_Dim!A:A,Customer_Dim!E:E,"False Data") -> Port Crystalberg | P5: =_xlfn.XLOOKUP(Table17[[#This Row],[Customer_ID]],Customer_Dim!A:A,Customer_Dim!F:F,"False Data") -> Tennessee | Q5: =_xlfn.XLOOKUP(Table17[[#This Row],[Customer_ID]],Customer_Dim!A:A,Customer_Dim!G:G,"False Data") -> USA | R5: =_xlfn.XLOOKUP(Table17[[#This Row],[Customer_ID]],Customer_Dim!A:A,Customer_Dim!H:H,"False Data") -> Platinum | S5: =_xlfn.XLOOKUP(Table17[[#This Row],[Store_ID]],Store_Dim!A:A,Store_Dim!B:B) -> Bean, Jones and Park | T5: =_xlfn.XLOOKUP(Table17[[#This Row],[Store_ID]],Store_Dim!A:A,Store_Dim!C:C) -> West | U5: =_xlfn.XLOOKUP(Table17[[#This Row],[Store_ID]],Store_Dim!A:A,Store_Dim!D:D) -> Thompsonborough | V5: =_xlfn.XLOOKUP(Table17[[#This Row],[Store_ID]],Store_Dim!A:A,Store_Dim!E:E) -> Online | W5: =_xlfn.XLOOKUP(Table17[[#This Row],[Product_ID]],Product_Dim!A:A,Product_Dim!B:B) -> Wireless Mouse | X5: =_xlfn.XLOOKUP(Table17[[#This Row],[Product_ID]],Product_Dim!A:A,Product_Dim!C:C) -> Electronics | Y5: =_xlfn.XLOOKUP(Table17[[#This Row],[Product_ID]],Product_Dim!A:A,Product_Dim!D:D) -> Computer | Z5: =_xlfn.XLOOKUP(Table17[[#This Row],[Product_ID]],Product_Dim!A:A,Product_Dim!E:E) -> Larson Ltd | AA5: =_xlfn.XLOOKUP(Table17[[#This Row],[Product_ID]],Product_Dim!A:A,Product_Dim!F:F) -> 392.89 | AB5: =_xlfn.XLOOKUP(Table17[[#This Row],[Product_ID]],Product_Dim!A:A,Product_Dim!G:G) -> 320
A6: SALE4 | B6: 45297 | C6: CUST1493 | D6: PROD59 | E6: STORE5 | F6: 3 | G6: 745.3 | H6: 0.18 | I6: Credit Card | J6: 1833.438 | K6: =_xlfn.XLOOKUP(Table17[[#This Row],[Customer_ID]],Customer_Dim!A:A,Customer_Dim!B:B,"False Data") -> Amanda Powell | L6: =_xlfn.XLOOKUP(Table17[[#This Row],[Customer_ID]],Customer_Dim!A:A,Customer_Dim!C:C,"False Data") -> 28 | M6: {=_xlfn.IFS(Table9[[#This Row],[Age]]<=35,"Youth",Table9[[#This Row],[Age]]<=55,"Adult",Table9[[#This Row],[Age]]>55,"Senior")} -> Youth | N6: =_xlfn.XLOOKUP(Table17[[#This Row],[Customer_ID]],Customer_Dim!A:A,Customer_Dim!D:D,"False Data") -> Male | O6: =_xlfn.XLOOKUP(Table17[[#This Row],[Customer_ID]],Customer_Dim!A:A,Customer_Dim!E:E,"False Data") -> South William | P6: =_xlfn.XLOOKUP(Table17[[#This Row],[Customer_ID]],Customer_Dim!A:A,Customer_Dim!F:F,"False Data") -> Alabama | Q6: =_xlfn.XLOOKUP(Table17[[#This Row],[Customer_ID]],Customer_Dim!A:A,Customer_Dim!G:G,"False Data") -> USA | R6: =_xlfn.XLOOKUP(Table17[[#This Row],[Customer_ID]],Customer_Dim!A:A,Customer_Dim!H:H,"False Data") -> Silver | S6: =_xlfn.XLOOKUP(Table17[[#This Row],[Store_ID]],Store_Dim!A:A,Store_Dim!B:B) -> Gray Ltd | T6: =_xlfn.XLOOKUP(Table17[[#This Row],[Store_ID]],Store_Dim!A:A,Store_Dim!C:C) -> North | U6: =_xlfn.XLOOKUP(Table17[[#This Row],[Store_ID]],Store_Dim!A:A,Store_Dim!D:D) -> New Michaelchester | V6: =_xlfn.XLOOKUP(Table17[[#This Row],[Store_ID]],Store_Dim!A:A,Store_Dim!E:E) -> Outlet | W6: =_xlfn.XLOOKUP(Table17[[#This Row],[Product_ID]],Product_Dim!A:A,Product_Dim!B:B) -> Men's Hair Styling Gel | X6: =_xlfn.XLOOKUP(Table17[[#This Row],[Product_ID]],Product_Dim!A:A,Product_Dim!C:C) -> Beauty | Y6: =_xlfn.XLOOKUP(Table17[[#This Row],[Product_ID]],Product_Dim!A:A,Product_Dim!D:D) -> Haircare | Z6: =_xlfn.XLOOKUP(Table17[[#This Row],[Product_ID]],Product_Dim!A:A,Product_Dim!E:E) -> Cline-Mccarthy | AA6: =_xlfn.XLOOKUP(Table17[[#This Row],[Product_ID]],Product_Dim!A:A,Product_Dim!F:F) -> 17.31 | AB6: =_xlfn.XLOOKUP(Table17[[#This Row],[Product_ID]],Product_Dim!A:A,Product_Dim!G:G) -> 399
A7: SALE5 | B7: 45499 | C7: CUST1116 | D7: PROD15 | E7: STORE7 | F7: 3 | G7: 147.01 | H7: 0.19 | I7: COD | J7: 357.2343 | K7: =_xlfn.XLOOKUP(Table17[[#This Row],[Customer_ID]],Customer_Dim!A:A,Customer_Dim!B:B,"False Data") -> Anthony Phillips | L7: =_xlfn.XLOOKUP(Table17[[#This Row],[Customer_ID]],Customer_Dim!A:A,Customer_Dim!C:C,"False Data") -> 18 | M7: {=_xlfn.IFS(Table9[[#This Row],[Age]]<=35,"Youth",Table9[[#This Row],[Age]]<=55,"Adult",Table9[[#This Row],[Age]]>55,"Senior")} -> Youth | N7: =_xlfn.XLOOKUP(Table17[[#This Row],[Customer_ID]],Customer_Dim!A:A,Customer_Dim!D:D,"False Data") -> Female | O7: =_xlfn.XLOOKUP(Table17[[#This Row],[Customer_ID]],Customer_Dim!A:A,Customer_Dim!E:E,"False Data") -> North Davidport | P7: =_xlfn.XLOOKUP(Table17[[#This Row],[Customer_ID]],Customer_Dim!A:A,Customer_Dim!F:F,"False Data") -> Rhode Island | Q7: =_xlfn.XLOOKUP(Table17[[#This Row],[Customer_ID]],Customer_Dim!A:A,Customer_Dim!G:G,"False Data") -> USA | R7: =_xlfn.XLOOKUP(Table17[[#This Row],[Customer_ID]],Customer_Dim!A:A,Customer_Dim!H:H,"False Data") -> Platinum | S7: =_xlfn.XLOOKUP(Table17[[#This Row],[Store_ID]],Store_Dim!A:A,Store_Dim!B:B) -> Martinez-Mullins | T7: =_xlfn.XLOOKUP(Table17[[#This Row],[Store_ID]],Store_Dim!A:A,Store_Dim!C:C) -> South | U7: =_xlfn.XLOOKUP(Table17[[#This Row],[Store_ID]],Store_Dim!A:A,Store_Dim!D:D) -> Williamsfurt | V7: =_xlfn.XLOOKUP(Table17[[#This Row],[Store_ID]],Store_Dim!A:A,Store_Dim!E:E) -> Online | W7: =_xlfn.XLOOKUP(Table17[[#This Row],[Product_ID]],Product_Dim!A:A,Product_Dim!B:B) -> 4K Home Projector | X7: =_xlfn.XLOOKUP(Table17[[#This Row],[Product_ID]],Product_Dim!A:A,Product_Dim!C:C) -> Electronics | Y7: =_xlfn.XLOOKUP(Table17[[#This Row],[Product_ID]],Product_Dim!A:A,Product_Dim!D:D) -> Appliances | Z7: =_xlfn.XLOOKUP(Table17[[#This Row],[Product_ID]],Product_Dim!A:A,Product_Dim!E:E) -> Thomas LLC | AA7: =_xlfn.XLOOKUP(Table17[[#This Row],[Product_ID]],Product_Dim!A:A,Product_Dim!F:F) -> 465.34 | AB7: =_xlfn.XLOOKUP(Table17[[#This Row],[Product_ID]],Product_Dim!A:A,Product_Dim!G:G) -> 301
A8: SALE6 | B8: 45850 | C8: CUST1016 | D8: PROD56 | E8: STORE4 | F8: 2 | G8: 785.31 | H8: 0.15 | I8: PayPal | J8: 1335.027 | K8: =_xlfn.XLOOKUP(Table17[[#This Row],[Customer_ID]],Customer_Dim!A:A,Customer_Dim!B:B,"False Data") -> John Scott | L8: =_xlfn.XLOOKUP(Table17[[#This Row],[Customer_ID]],Customer_Dim!A:A,Customer_Dim!C:C,"False Data") -> 24 | M8: {=_xlfn.IFS(Table9[[#This Row],[Age]]<=35,"Youth",Table9[[#This Row],[Age]]<=55,"Adult",Table9[[#This Row],[Age]]>55,"Senior")} -> Youth | N8: =_xlfn.XLOOKUP(Table17[[#This Row],[Customer_ID]],Customer_Dim!A:A,Customer_Dim!D:D,"False Data") -> Female | O8: =_xlfn.XLOOKUP(Table17[[#This Row],[Customer_ID]],Customer_Dim!A:A,Customer_Dim!E:E,"False Data") -> South Christopher | P8: =_xlfn.XLOOKUP(Table17[[#This Row],[Customer_ID]],Customer_Dim!A:A,Customer_Dim!F:F,"False Data") -> Pennsylvania | Q8: =_xlfn.XLOOKUP(Table17[[#This Row],[Customer_ID]],Customer_Dim!A:A,Customer_Dim!G:G,"False Data") -> USA | R8: =_xlfn.XLOOKUP(Table17[[#This Row],[Customer_ID]],Customer_Dim!A:A,Customer_Dim!H:H,"False Data") -> Bronze | S8: =_xlfn.XLOOKUP(Table17[[#This Row],[Store_ID]],Store_Dim!A:A,Store_Dim!B:B) -> Alexander Group | T8: =_xlfn.XLOOKUP(Table17[[#This Row],[Store_ID]],Store_Dim!A:A,Store_Dim!C:C) -> South | U8: =_xlfn.XLOOKUP(Table17[[#This Row],[Store_ID]],Store_Dim!A:A,Store_Dim!D:D) -> Port Sharon | V8: =_xlfn.XLOOKUP(Table17[[#This Row],[Store_ID]],Store_Dim!A:A,Store_Dim!E:E) -> Online | W8: =_xlfn.XLOOKUP(Table17[[#This Row],[Product_ID]],Product_Dim!A:A,Product_Dim!B:B) -> Premium Blanket Throw | X8: =_xlfn.XLOOKUP(Table17[[#This Row],[Product_ID]],Product_Dim!A:A,Product_Dim!C:C) -> Home | Y8: =_xlfn.XLOOKUP(Table17[[#This Row],[Product_ID]],Product_Dim!A:A,Product_Dim!D:D) -> Decor | Z8: =_xlfn.XLOOKUP(Table17[[#This Row],[Product_ID]],Product_Dim!A:A,Product_Dim!E:E) -> Hernandez, Kennedy and Porter | AA8: =_xlfn.XLOOKUP(Table17[[#This Row],[Product_ID]],Product_Dim!A:A,Product_Dim!F:F) -> 461.47 | AB8: =_xlfn.XLOOKUP(Table17[[#This Row],[Product_ID]],Product_Dim!A:A,Product_Dim!G:G) -> 190
A9: SALE7 | B9: 45248 | C9: CUST1152 | D9: PROD70 | E9: STORE8 | F9: 4 | G9: 342.39 | H9: 0.23 | I9: PayPal | J9: 1054.5612 | K9: =_xlfn.XLOOKUP(Table17[[#This Row],[Customer_ID]],Customer_Dim!A:A,Customer_Dim!B:B,"False Data") -> Patrick Roberts | L9: =_xlfn.XLOOKUP(Table17[[#This Row],[Customer_ID]],Customer_Dim!A:A,Customer_Dim!C:C,"False Data") -> 41 | M9: {=_xlfn.IFS(Table9[[#This Row],[Age]]<=35,"Youth",Table9[[#This Row],[Age]]<=55,"Adult",Table9[[#This Row],[Age]]>55,"Senior")} -> Adult | N9: =_xlfn.XLOOKUP(Table17[[#This Row],[Customer_ID]],Customer_Dim!A:A,Customer_Dim!D:D,"False Data") -> Female | O9: =_xlfn.XLOOKUP(Table17[[#This Row],[Customer_ID]],Customer_Dim!A:A,Customer_Dim!E:E,"False Data") -> Jaredville | P9: =_xlfn.XLOOKUP(Table17[[#This Row],[Customer_ID]],Customer_Dim!A:A,Customer_Dim!F:F,"False Data") -> Missouri | Q9: =_xlfn.XLOOKUP(Table17[[#This Row],[Customer_ID]],Customer_Dim!A:A,Customer_Dim!G:G,"False Data") -> USA | R9: =_xlfn.XLOOKUP(Table17[[#This Row],[Customer_ID]],Customer_Dim!A:A,Customer_Dim!H:H,"False Data") -> Platinum | S9: =_xlfn.XLOOKUP(Table17[[#This Row],[Store_ID]],Store_Dim!A:A,Store_Dim!B:B) -> Bean, Jones and Park | T9: =_xlfn.XLOOKUP(Table17[[#This Row],[Store_ID]],Store_Dim!A:A,Store_Dim!C:C) -> West | U9: =_xlfn.XLOOKUP(Table17[[#This Row],[Store_ID]],Store_Dim!A:A,Store_Dim!D:D) -> Thompsonborough | V9: =_xlfn.XLOOKUP(Table17[[#This Row],[Store_ID]],Store_Dim!A:A,Store_Dim!E:E) -> Online | W9: =_xlfn.XLOOKUP(Table17[[#This Row],[Product_ID]],Product_Dim!A:A,Product_Dim!B:B) -> Kitchen Storage Rack | X9: =_xlfn.XLOOKUP(Table17[[#This Row],[Product_ID]],Product_Dim!A:A,Product_Dim!C:C) -> Home | Y9: =_xlfn.XLOOKUP(Table17[[#This Row],[Product_ID]],Product_Dim!A:A,Product_Dim!D:D) -> Storage | Z9: =_xlfn.XLOOKUP(Table17[[#This Row],[Product_ID]],Product_Dim!A:A,Product_Dim!E:E) -> Duran Group | AA9: =_xlfn.XLOOKUP(Table17[[#This Row],[Product_ID]],Product_Dim!A:A,Product_Dim!F:F) -> 138.05 | AB9: =_xlfn.XLOOKUP(Table17[[#This Row],[Product_ID]],Product_Dim!A:A,Product_Dim!G:G) -> 89
A10: SALE8 | B10: 45781 | C10: CUST1187 | D10: PROD99 | E10: STORE5 | F10: 3 | G10: 448.25 | H10: 0.07 | I10: PayPal | J10: 1250.6175 | K10: =_xlfn.XLOOKUP(Table17[[#This Row],[Customer_ID]],Customer_Dim!A:A,Customer_Dim!B:B,"False Data") -> Dr. Suzanne Bullock | L10: =_xlfn.XLOOKUP(Table17[[#This Row],[Customer_ID]],Customer_Dim!A:A,Customer_Dim!C:C,"False Data") -> 60 | M10: {=_xlfn.IFS(Table9[[#This Row],[Age]]<=35,"Youth",Table9[[#This Row],[Age]]<=55,"Adult",Table9[[#This Row],[Age]]>55,"Senior")} -> Senior | N10: =_xlfn.XLOOKUP(Table17[[#This Row],[Customer_ID]],Customer_Dim!A:A,Customer_Dim!D:D,"False Data") -> Female | O10: =_xlfn.XLOOKUP(Table17[[#This Row],[Customer_ID]],Customer_Dim!A:A,Customer_Dim!E:E,"False Data") -> Lake Blaketon | P10: =_xlfn.XLOOKUP(Table17[[#This Row],[Customer_ID]],Customer_Dim!A:A,Customer_Dim!F:F,"False Data") -> Alabama | Q10: =_xlfn.XLOOKUP(Table17[[#This Row],[Customer_ID]],Customer_Dim!A:A,Customer_Dim!G:G,"False Data") -> USA | R10: =_xlfn.XLOOKUP(Table17[[#This Row],[Customer_ID]],Customer_Dim!A:A,Customer_Dim!H:H,"False Data") -> Platinum | S10: =_xlfn.XLOOKUP(Table17[[#This Row],[Store_ID]],Store_Dim!A:A,Store_Dim!B:B) -> Gray Ltd | T10: =_xlfn.XLOOKUP(Table17[[#This Row],[Store_ID]],Store_Dim!A:A,Store_Dim!C:C) -> North | U10: =_xlfn.XLOOKUP(Table17[[#This Row],[Store_ID]],Store_Dim!A:A,Store_Dim!D:D) -> New Michaelchester | V10: =_xlfn.XLOOKUP(Table17[[#This Row],[Store_ID]],Store_Dim!A:A,Store_Dim!E:E) -> Outlet | W10: =_xlfn.XLOOKUP(Table17[[#This Row],[Product_ID]],Product_Dim!A:A,Product_Dim!B:B) -> Stainless Steel Cookware Set | X10: =_xlfn.XLOOKUP(Table17[[#This Row],[Product_ID]],Product_Dim!A:A,Product_Dim!C:C) -> Home | Y10: =_xlfn.XLOOKUP(Table17[[#This Row],[Product_ID]],Product_Dim!A:A,Product_Dim!D:D) -> Kitchen | Z10: =_xlfn.XLOOKUP(Table17[[#This Row],[Product_ID]],Product_Dim!A:A,Product_Dim!E:E) -> Campbell Ltd | AA10: =_xlfn.XLOOKUP(Table17[[#This Row],[Product_ID]],Product_Dim!A:A,Product_Dim!F:F) -> 201.41 | AB10: =_xlfn.XLOOKUP(Table17[[#This Row],[Product_ID]],Product_Dim!A:A,Product_Dim!G:G) -> 146
A11: SALE9 | B11: 45869 | C11: CUST1464 | D11: PROD33 | E11: STORE0 | F11: 2 | G11: 873.17 | H11: 0.23 | I11: PayPal | J11: 1344.6818 | K11: =_xlfn.XLOOKUP(Table17[[#This Row],[Customer_ID]],Customer_Dim!A:A,Customer_Dim!B:B,"False Data") -> David Pierce | L11: =_xlfn.XLOOKUP(Table17[[#This Row],[Customer_ID]],Customer_Dim!A:A,Customer_Dim!C:C,"False Data") -> 45 | M11: {=_xlfn.IFS(Table9[[#This Row],[Age]]<=35,"Youth",Table9[[#This Row],[Age]]<=55,"Adult",Table9[[#This Row],[Age]]>55,"Senior")} -> Adult | N11: =_xlfn.XLOOKUP(Table17[[#This Row],[Customer_ID]],Customer_Dim!A:A,Customer_Dim!D:D,"False Data") -> Female | O11: =_xlfn.XLOOKUP(Table17[[#This Row],[Customer_ID]],Customer_Dim!A:A,Customer_Dim!E:E,"False Data") -> Grayland | P11: =_xlfn.XLOOKUP(Table17[[#This Row],[Customer_ID]],Customer_Dim!A:A,Customer_Dim!F:F,"False Data") -> Washington | Q11: =_xlfn.XLOOKUP(Table17[[#This Row],[Customer_ID]],Customer_Dim!A:A,Customer_Dim!G:G,"False Data") -> USA | R11: =_xlfn.XLOOKUP(Table17[[#This Row],[Customer_ID]],Customer_Dim!A:A,Customer_Dim!H:H,"False Data") -> Platinum | S11: =_xlfn.XLOOKUP(Table17[[#This Row],[Store_ID]],Store_Dim!A:A,Store_Dim!B:B) -> Rivera-Warner | T11: =_xlfn.XLOOKUP(Table17[[#This Row],[Store_ID]],Store_Dim!A:A,Store_Dim!C:C) -> East | U11: =_xlfn.XLOOKUP(Table17[[#This Row],[Store_ID]],Store_Dim!A:A,Store_Dim!D:D) -> Washingtonfurt | V11: =_xlfn.XLOOKUP(Table17[[#This Row],[Store_ID]],Store_Dim!A:A,Store_Dim!E:E) -> Flagship | W11: =_xlfn.XLOOKUP(Table17[[#This Row],[Product_ID]],Product_Dim!A:A,Product_Dim!B:B) -> Modern Wall Clock | X11: =_xlfn.XLOOKUP(Table17[[#This Row],[Product_ID]],Product_Dim!A:A,Product_Dim!C:C) -> Home | Y11: =_xlfn.XLOOKUP(Table17[[#This Row],[Product_ID]],Product_Dim!A:A,Product_Dim!D:D) -> Decor | Z11: =_xlfn.XLOOKUP(Table17[[#This Row],[Product_ID]],Product_Dim!A:A,Product_Dim!E:E) -> Weiss-Watson | AA11: =_xlfn.XLOOKUP(Table17[[#This Row],[Product_ID]],Product_Dim!A:A,Product_Dim!F:F) -> 179.77 | AB11: =_xlfn.XLOOKUP(Table17[[#This Row],[Product_ID]],Product_Dim!A:A,Product_Dim!G:G) -> 305
A12: SALE10 | B12: 45335 | C12: CUST1065 | D12: PROD24 | E12: STORE14 | F12: 1 | G12: 278.63 | H12: 0.07 | I12: Credit Card | J12: 259.1259 | K12: =_xlfn.XLOOKUP(Table17[[#This Row],[Customer_ID]],Customer_Dim!A:A,Customer_Dim!B:B,"False Data") -> Michael Thomas | L12: =_xlfn.XLOOKUP(Table17[[#This Row],[Customer_ID]],Customer_Dim!A:A,Customer_Dim!C:C,"False Data") -> 21 | M12: {=_xlfn.IFS(Table9[[#This Row],[Age]]<=35,"Youth",Table9[[#This Row],[Age]]<=55,"Adult",Table9[[#This Row],[Age]]>55,"Senior")} -> Youth | N12: =_xlfn.XLOOKUP(Table17[[#This Row],[Customer_ID]],Customer_Dim!A:A,Customer_Dim!D:D,"False Data") -> Female | O12: =_xlfn.XLOOKUP(Table17[[#This Row],[Customer_ID]],Customer_Dim!A:A,Customer_Dim!E:E,"False Data") -> Woodmouth | P12: =_xlfn.XLOOKUP(Table17[[#This Row],[Customer_ID]],Customer_Dim!A:A,Customer_Dim!F:F,"False Data") -> Nevada | Q12: =_xlfn.XLOOKUP(Table17[[#This Row],[Customer_ID]],Customer_Dim!A:A,Customer_Dim!G:G,"False Data") -> USA | R12: =_xlfn.XLOOKUP(Table17[[#This Row],[Customer_ID]],Customer_Dim!A:A,Customer_Dim!H:H,"False Data") -> Silver | S12: =_xlfn.XLOOKUP(Table17[[#This Row],[Store_ID]],Store_Dim!A:A,Store_Dim!B:B) -> Mcdonald Inc | T12: =_xlfn.XLOOKUP(Table17[[#This Row],[Store_ID]],Store_Dim!A:A,Store_Dim!C:C) -> South | U12: =_xlfn.XLOOKUP(Table17[[#This Row],[Store_ID]],Store_Dim!A:A,Store_Dim!D:D) -> Christopherland | V12: =_xlfn.XLOOKUP(Table17[[#This Row],[Store_ID]],Store_Dim!A:A,Store_Dim!E:E) -> Outlet | W12: =_xlfn.XLOOKUP(Table17[[#This Row],[Product_ID]],Product_Dim!A:A,Product_Dim!B:B) -> Foldable Camping Chair | X12: =_xlfn.XLOOKUP(Table17[[#This Row],[Product_ID]],Product_Dim!A:A,Product_Dim!C:C) -> Sports | Y12: =_xlfn.XLOOKUP(Table17[[#This Row],[Product_ID]],Product_Dim!A:A,Product_Dim!D:D) -> Outdoor | Z12: =_xlfn.XLOOKUP(Table17[[#This Row],[Product_ID]],Product_Dim!A:A,Product_Dim!E:E) -> Cook Ltd | AA12: =_xlfn.XLOOKUP(Table17[[#This Row],[Product_ID]],Product_Dim!A:A,Product_Dim!F:F) -> 166.06 | AB12: =_xlfn.XLOOKUP(Table17[[#This Row],[Product_ID]],Product_Dim!A:A,Product_Dim!G:G) -> 340
A13: SALE11 | B13: 45801 | C13: CUST1320 | D13: PROD39 | E13: STORE1 | F13: 4 | G13: 286.92 | H13: 0.17 | I13: Credit Card | J13: 952.5744 | K13: =_xlfn.XLOOKUP(Table17[[#This Row],[Customer_ID]],Customer_Dim!A:A,Customer_Dim!B:B,"False Data") -> Jessica Gonzalez | L13: =_xlfn.XLOOKUP(Table17[[#This Row],[Customer_ID]],Customer_Dim!A:A,Customer_Dim!C:C,"False Data") -> 34 | M13: {=_xlfn.IFS(Table9[[#This Row],[Age]]<=35,"Youth",Table9[[#This Row],[Age]]<=55,"Adult",Table9[[#This Row],[Age]]>55,"Senior")} -> Youth | N13: =_xlfn.XLOOKUP(Table17[[#This Row],[Customer_ID]],Customer_Dim!A:A,Customer_Dim!D:D,"False Data") -> Female | O13: =_xlfn.XLOOKUP(Table17[[#This Row],[Customer_ID]],Customer_Dim!A:A,Customer_Dim!E:E,"False Data") -> South Darrenland | P13: =_xlfn.XLOOKUP(Table17[[#This Row],[Customer_ID]],Customer_Dim!A:A,Customer_Dim!F:F,"False Data") -> Iowa | Q13: =_xlfn.XLOOKUP(Table17[[#This Row],[Customer_ID]],Customer_Dim!A:A,Customer_Dim!G:G,"False Data") -> USA | R13: =_xlfn.XLOOKUP(Table17[[#This Row],[Customer_ID]],Customer_Dim!A:A,Customer_Dim!H:H,"False Data") -> Bronze | S13: =_xlfn.XLOOKUP(Table17[[#This Row],[Store_ID]],Store_Dim!A:A,Store_Dim!B:B) -> Martinez, Adkins and Johnson | T13: =_xlfn.XLOOKUP(Table17[[#This Row],[Store_ID]],Store_Dim!A:A,Store_Dim!C:C) -> North | U13: =_xlfn.XLOOKUP(Table17[[#This Row],[Store_ID]],Store_Dim!A:A,Store_Dim!D:D) -> Danielmouth | V13: =_xlfn.XLOOKUP(Table17[[#This Row],[Store_ID]],Store_Dim!A:A,Store_Dim!E:E) -> Flagship | W13: =_xlfn.XLOOKUP(Table17[[#This Row],[Product_ID]],Product_Dim!A:A,Product_Dim!B:B) -> Portable Power Bank | X13: =_xlfn.XLOOKUP(Table17[[#This Row],[Product_ID]],Product_Dim!A:A,Product_Dim!C:C) -> Electronics | Y13: =_xlfn.XLOOKUP(Table17[[#This Row],[Product_ID]],Product_Dim!A:A,Product_Dim!D:D) -> Mobile | Z13: =_xlfn.XLOOKUP(Table17[[#This Row],[Product_ID]],Product_Dim!A:A,Product_Dim!E:E) -> Cummings and Sons | AA13: =_xlfn.XLOOKUP(Table17[[#This Row],[Product_ID]],Product_Dim!A:A,Product_Dim!F:F) -> 326.06 | AB13: =_xlfn.XLOOKUP(Table17[[#This Row],[Product_ID]],Product_Dim!A:A,Product_Dim!G:G) -> 301
... A27: SALE25 | B27: 45552 | C27: CUST1381 | D27: PROD5 | E27: STORE3 | F27: 4 | G27: 852.71 | H27: 0.14 | I27: PayPal | J27: 2933.3224 | K27: =_xlfn.XLOOKUP(Table17[[#This Row],[Customer_ID]],Customer_Dim!A:A,Customer_Dim!B:B,"False Data") -> Erika Padilla | L27: =_xlfn.XLOOKUP(Table17[[#This Row],[Customer_ID]],Customer_Dim!A:A,Customer_Dim!C:C,"False Data") -> 50 | M27: {=_xlfn.IFS(Table9[[#This Row],[Age]]<=35,"Youth",Table9[[#This Row],[Age]]<=55,"Adult",Table9[[#This Row],[Age]]>55,"Senior")} -> Adult | N27: =_xlfn.XLOOKUP(Table17[[#This Row],[Customer_ID]],Customer_Dim!A:A,Customer_Dim!D:D,"False Data") -> Male | O27: =_xlfn.XLOOKUP(Table17[[#This Row],[Customer_ID]],Customer_Dim!A:A,Customer_Dim!E:E,"False Data") -> Andrewsland | P27: =_xlfn.XLOOKUP(Table17[[#This Row],[Customer_ID]],Customer_Dim!A:A,Customer_Dim!F:F,"False Data") -> Alabama | Q27: =_xlfn.XLOOKUP(Table17[[#This Row],[Customer_ID]],Customer_Dim!A:A,Customer_Dim!G:G,"False Data") -> USA | R27: =_xlfn.XLOOKUP(Table17[[#This Row],[Customer_ID]],Customer_Dim!A:A,Customer_Dim!H:H,"False Data") -> Silver | S27: =_xlfn.XLOOKUP(Table17[[#This Row],[Store_ID]],Store_Dim!A:A,Store_Dim!B:B) -> Johnson-Wright | T27: =_xlfn.XLOOKUP(Table17[[#This Row],[Store_ID]],Store_Dim!A:A,Store_Dim!C:C) -> North | U27: =_xlfn.XLOOKUP(Table17[[#This Row],[Store_ID]],Store_Dim!A:A,Store_Dim!D:D) -> Hoodberg | V27: =_xlfn.XLOOKUP(Table17[[#This Row],[Store_ID]],Store_Dim!A:A,Store_Dim!E:E) -> Outlet | W27: =_xlfn.XLOOKUP(Table17[[#This Row],[Product_ID]],Product_Dim!A:A,Product_Dim!B:B) -> Men's Leather Belt | X27: =_xlfn.XLOOKUP(Table17[[#This Row],[Product_ID]],Product_Dim!A:A,Product_Dim!C:C) -> Clothing | Y27: =_xlfn.XLOOKUP(Table17[[#This Row],[Product_ID]],Product_Dim!A:A,Product_Dim!D:D) -> Accessories | Z27: =_xlfn.XLOOKUP(Table17[[#This Row],[Product_ID]],Product_Dim!A:A,Product_Dim!E:E) -> Baldwin, Garza and Gonzalez | AA27: =_xlfn.XLOOKUP(Table17[[#This Row],[Product_ID]],Product_Dim!A:A,Product_Dim!F:F) -> 261 | AB27: =_xlfn.XLOOKUP(Table17[[#This Row],[Product_ID]],Product_Dim!A:A,Product_Dim!G:G) -> 59
A28: SALE26 | B28: 45294 | C28: CUST1213 | D28: PROD98 | E28: STORE8 | F28: 4 | G28: 156.16 | H28: =1-(Table17[[#This Row],[Total_Amount]]/(Table17[[#This Row],[Unit_Price]]*Table17[[#This Row],[Quantity]])) -> 0.04 | I28: Credit Card | J28: 599.6544 | K28: =_xlfn.XLOOKUP(Table17[[#This Row],[Customer_ID]],Customer_Dim!A:A,Customer_Dim!B:B,"False Data") -> Stuart Johnson | L28: =_xlfn.XLOOKUP(Table17[[#This Row],[Customer_ID]],Customer_Dim!A:A,Customer_Dim!C:C,"False Data") -> 42 | M28: {=_xlfn.IFS(Table9[[#This Row],[Age]]<=35,"Youth",Table9[[#This Row],[Age]]<=55,"Adult",Table9[[#This Row],[Age]]>55,"Senior")} -> Adult | N28: =_xlfn.XLOOKUP(Table17[[#This Row],[Customer_ID]],Customer_Dim!A:A,Customer_Dim!D:D,"False Data") -> Female | O28: =_xlfn.XLOOKUP(Table17[[#This Row],[Customer_ID]],Customer_Dim!A:A,Customer_Dim!E:E,"False Data") -> West Markport | P28: =_xlfn.XLOOKUP(Table17[[#This Row],[Customer_ID]],Customer_Dim!A:A,Customer_Dim!F:F,"False Data") -> North Dakota | Q28: =_xlfn.XLOOKUP(Table17[[#This Row],[Customer_ID]],Customer_Dim!A:A,Customer_Dim!G:G,"False Data") -> USA | R28: =_xlfn.XLOOKUP(Table17[[#This Row],[Customer_ID]],Customer_Dim!A:A,Customer_Dim!H:H,"False Data") -> Platinum | S28: =_xlfn.XLOOKUP(Table17[[#This Row],[Store_ID]],Store_Dim!A:A,Store_Dim!B:B) -> Bean, Jones and Park | T28: =_xlfn.XLOOKUP(Table17[[#This Row],[Store_ID]],Store_Dim!A:A,Store_Dim!C:C) -> West | U28: =_xlfn.XLOOKUP(Table17[[#This Row],[Store_ID]],Store_Dim!A:A,Store_Dim!D:D) -> Thompsonborough | V28: =_xlfn.XLOOKUP(Table17[[#This Row],[Store_ID]],Store_Dim!A:A,Store_Dim!E:E) -> Online | W28: =_xlfn.XLOOKUP(Table17[[#This Row],[Product_ID]],Product_Dim!A:A,Product_Dim!B:B) -> Portable Bluetooth Speaker | X28: =_xlfn.XLOOKUP(Table17[[#This Row],[Product_ID]],Product_Dim!A:A,Product_Dim!C:C) -> Electronics | Y28: =_xlfn.XLOOKUP(Table17[[#This Row],[Product_ID]],Product_Dim!A:A,Product_Dim!D:D) -> Audio | Z28: =_xlfn.XLOOKUP(Table17[[#This Row],[Product_ID]],Product_Dim!A:A,Product_Dim!E:E) -> Flores-King | AA28: =_xlfn.XLOOKUP(Table17[[#This Row],[Product_ID]],Product_Dim!A:A,Product_Dim!F:F) -> 431.67 | AB28: =_xlfn.XLOOKUP(Table17[[#This Row],[Product_ID]],Product_Dim!A:A,Product_Dim!G:G) -> 73
A29: SALE27 | B29: 45710 | C29: CUST1200 | D29: PROD77 | E29: STORE8 | F29: 3 | G29: 815.49 | H29: 0.17 | I29: Credit Card | J29: 2030.5701 | K29: =_xlfn.XLOOKUP(Table17[[#This Row],[Customer_ID]],Customer_Dim!A:A,Customer_Dim!B:B,"False Data") -> Anna Perez | L29: =_xlfn.XLOOKUP(Table17[[#This Row],[Customer_ID]],Customer_Dim!A:A,Customer_Dim!C:C,"False Data") -> 30 | M29: {=_xlfn.IFS(Table9[[#This Row],[Age]]<=35,"Youth",Table9[[#This Row],[Age]]<=55,"Adult",Table9[[#This Row],[Age]]>55,"Senior")} -> Youth | N29: =_xlfn.XLOOKUP(Table17[[#This Row],[Customer_ID]],Customer_Dim!A:A,Customer_Dim!D:D,"False Data") -> Male | O29: =_xlfn.XLOOKUP(Table17[[#This Row],[Customer_ID]],Customer_Dim!A:A,Customer_Dim!E:E,"False Data") -> South Jerry | P29: =_xlfn.XLOOKUP(Table17[[#This Row],[Customer_ID]],Customer_Dim!A:A,Customer_Dim!F:F,"False Data") -> Maine | Q29: =_xlfn.XLOOKUP(Table17[[#This Row],[Customer_ID]],Customer_Dim!A:A,Customer_Dim!G:G,"False Data") -> USA | R29: =_xlfn.XLOOKUP(Table17[[#This Row],[Customer_ID]],Customer_Dim!A:A,Customer_Dim!H:H,"False Data") -> Platinum | S29: =_xlfn.XLOOKUP(Table17[[#This Row],[Store_ID]],Store_Dim!A:A,Store_Dim!B:B) -> Bean, Jones and Park | T29: =_xlfn.XLOOKUP(Table17[[#This Row],[Store_ID]],Store_Dim!A:A,Store_Dim!C:C) -> West | U29: =_xlfn.XLOOKUP(Table17[[#This Row],[Store_ID]],Store_Dim!A:A,Store_Dim!D:D) -> Thompsonborough | V29: =_xlfn.XLOOKUP(Table17[[#This Row],[Store_ID]],Store_Dim!A:A,Store_Dim!E:E) -> Online | W29: =_xlfn.XLOOKUP(Table17[[#This Row],[Product_ID]],Product_Dim!A:A,Product_Dim!B:B) -> WiFi Mesh Router | X29: =_xlfn.XLOOKUP(Table17[[#This Row],[Product_ID]],Product_Dim!A:A,Product_Dim!C:C) -> Electronics | Y29: =_xlfn.XLOOKUP(Table17[[#This Row],[Product_ID]],Product_Dim!A:A,Product_Dim!D:D) -> Appliances | Z29: =_xlfn.XLOOKUP(Table17[[#This Row],[Product_ID]],Product_Dim!A:A,Product_Dim!E:E) -> White, Reeves and Woods | AA29: =_xlfn.XLOOKUP(Table17[[#This Row],[Product_ID]],Product_Dim!A:A,Product_Dim!F:F) -> 480.9 | AB29: =_xlfn.XLOOKUP(Table17[[#This Row],[Product_ID]],Product_Dim!A:A,Product_Dim!G:G) -> 104
A30: SALE28 | B30: 45923 | C30: CUST1148 | D30: PROD13 | E30: STORE2 | F30: 2 | G30: 74.21 | H30: 0.11 | I30: PayPal | J30: 132.0938 | K30: =_xlfn.XLOOKUP(Table17[[#This Row],[Customer_ID]],Customer_Dim!A:A,Customer_Dim!B:B,"False Data") -> Theresa Campbell | L30: =_xlfn.XLOOKUP(Table17[[#This Row],[Customer_ID]],Customer_Dim!A:A,Customer_Dim!C:C,"False Data") -> 42 | M30: {=_xlfn.IFS(Table9[[#This Row],[Age]]<=35,"Youth",Table9[[#This Row],[Age]]<=55,"Adult",Table9[[#This Row],[Age]]>55,"Senior")} -> Adult | N30: =_xlfn.XLOOKUP(Table17[[#This Row],[Customer_ID]],Customer_Dim!A:A,Customer_Dim!D:D,"False Data") -> Female | O30: =_xlfn.XLOOKUP(Table17[[#This Row],[Customer_ID]],Customer_Dim!A:A,Customer_Dim!E:E,"False Data") -> New Brian | P30: =_xlfn.XLOOKUP(Table17[[#This Row],[Customer_ID]],Customer_Dim!A:A,Customer_Dim!F:F,"False Data") -> Wisconsin | Q30: =_xlfn.XLOOKUP(Table17[[#This Row],[Customer_ID]],Customer_Dim!A:A,Customer_Dim!G:G,"False Data") -> USA | R30: =_xlfn.XLOOKUP(Table17[[#This Row],[Customer_ID]],Customer_Dim!A:A,Customer_Dim!H:H,"False Data") -> Bronze | S30: =_xlfn.XLOOKUP(Table17[[#This Row],[Store_ID]],Store_Dim!A:A,Store_Dim!B:B) -> Black-Horn | T30: =_xlfn.XLOOKUP(Table17[[#This Row],[Store_ID]],Store_Dim!A:A,Store_Dim!C:C) -> South | U30: =_xlfn.XLOOKUP(Table17[[#This Row],[Store_ID]],Store_Dim!A:A,Store_Dim!D:D) -> North Nancyview | V30: =_xlfn.XLOOKUP(Table17[[#This Row],[Store_ID]],Store_Dim!A:A,Store_Dim!E:E) -> Outlet | W30: =_xlfn.XLOOKUP(Table17[[#This Row],[Product_ID]],Product_Dim!A:A,Product_Dim!B:B) -> USB-C Fast Charger | X30: =_xlfn.XLOOKUP(Table17[[#This Row],[Product_ID]],Product_Dim!A:A,Product_Dim!C:C) -> Electronics | Y30: =_xlfn.XLOOKUP(Table17[[#This Row],[Product_ID]],Product_Dim!A:A,Product_Dim!D:D) -> Accessories | Z30: =_xlfn.XLOOKUP(Table17[[#This Row],[Product_ID]],Product_Dim!A:A,Product_Dim!E:E) -> Dawson-Perkins | AA30: =_xlfn.XLOOKUP(Table17[[#This Row],[Product_ID]],Product_Dim!A:A,Product_Dim!F:F) -> 242.23 | AB30: =_xlfn.XLOOKUP(Table17[[#This Row],[Product_ID]],Product_Dim!A:A,Product_Dim!G:G) -> 453
A31: SALE29 | B31: 45302 | C31: CUST1348 | D31: PROD99 | E31: STORE3 | F31: 4 | G31: 451.67 | H31: 0.15 | I31: Credit Card | J31: 1535.678 | K31: =_xlfn.XLOOKUP(Table17[[#This Row],[Customer_ID]],Customer_Dim!A:A,Customer_Dim!B:B,"False Data") -> Sherry Cabrera | L31: =_xlfn.XLOOKUP(Table17[[#This Row],[Customer_ID]],Customer_Dim!A:A,Customer_Dim!C:C,"False Data") -> 55 | M31: {=_xlfn.IFS(Table9[[#This Row],[Age]]<=35,"Youth",Table9[[#This Row],[Age]]<=55,"Adult",Table9[[#This Row],[Age]]>55,"Senior")} -> Adult | N31: =_xlfn.XLOOKUP(Table17[[#This Row],[Customer_ID]],Customer_Dim!A:A,Customer_Dim!D:D,"False Data") -> Male | O31: =_xlfn.XLOOKUP(Table17[[#This Row],[Customer_ID]],Customer_Dim!A:A,Customer_Dim!E:E,"False Data") -> Shannonview | P31: =_xlfn.XLOOKUP(Table17[[#This Row],[Customer_ID]],Customer_Dim!A:A,Customer_Dim!F:F,"False Data") -> Pennsylvania | Q31: =_xlfn.XLOOKUP(Table17[[#This Row],[Customer_ID]],Customer_Dim!A:A,Customer_Dim!G:G,"False Data") -> USA | R31: =_xlfn.XLOOKUP(Table17[[#This Row],[Customer_ID]],Customer_Dim!A:A,Customer_Dim!H:H,"False Data") -> Silver | S31: =_xlfn.XLOOKUP(Table17[[#This Row],[Store_ID]],Store_Dim!A:A,Store_Dim!B:B) -> Johnson-Wright | T31: =_xlfn.XLOOKUP(Table17[[#This Row],[Store_ID]],Store_Dim!A:A,Store_Dim!C:C) -> North | U31: =_xlfn.XLOOKUP(Table17[[#This Row],[Store_ID]],Store_Dim!A:A,Store_Dim!D:D) -> Hoodberg | V31: =_xlfn.XLOOKUP(Table17[[#This Row],[Store_ID]],Store_Dim!A:A,Store_Dim!E:E) -> Outlet | W31: =_xlfn.XLOOKUP(Table17[[#This Row],[Product_ID]],Product_Dim!A:A,Product_Dim!B:B) -> Stainless Steel Cookware Set | X31: =_xlfn.XLOOKUP(Table17[[#This Row],[Product_ID]],Product_Dim!A:A,Product_Dim!C:C) -> Home | Y31: =_xlfn.XLOOKUP(Table17[[#This Row],[Product_ID]],Product_Dim!A:A,Product_Dim!D:D) -> Kitchen | Z31: =_xlfn.XLOOKUP(Table17[[#This Row],[Product_ID]],Product_Dim!A:A,Product_Dim!E:E) -> Campbell Ltd | AA31: =_xlfn.XLOOKUP(Table17[[#This Row],[Product_ID]],Product_Dim!A:A,Product_Dim!F:F) -> 201.41 | AB31: =_xlfn.XLOOKUP(Table17[[#This Row],[Product_ID]],Product_Dim!A:A,Product_Dim!G:G) -> 146
A32: SALE30 | B32: 45217 | C32: CUST1028 | D32: PROD5 | E32: STORE19 | F32: 1 | G32: 429.38 | H32: 0.13 | I32: PayPal | J32: 373.5606 | K32: =_xlfn.XLOOKUP(Table17[[#This Row],[Customer_ID]],Customer_Dim!A:A,Customer_Dim!B:B,"False Data") -> Joshua Ryan | L32: =_xlfn.XLOOKUP(Table17[[#This Row],[Customer_ID]],Customer_Dim!A:A,Customer_Dim!C:C,"False Data") -> 27 | M32: {=_xlfn.IFS(Table9[[#This Row],[Age]]<=35,"Youth",Table9[[#This Row],[Age]]<=55,"Adult",Table9[[#This Row],[Age]]>55,"Senior")} -> Youth | N32: =_xlfn.XLOOKUP(Table17[[#This Row],[Customer_ID]],Customer_Dim!A:A,Customer_Dim!D:D,"False Data") -> Female | O32: =_xlfn.XLOOKUP(Table17[[#This Row],[Customer_ID]],Customer_Dim!A:A,Customer_Dim!E:E,"False Data") -> New David | P32: =_xlfn.XLOOKUP(Table17[[#This Row],[Customer_ID]],Customer_Dim!A:A,Customer_Dim!F:F,"False Data") -> New Jersey | Q32: =_xlfn.XLOOKUP(Table17[[#This Row],[Customer_ID]],Customer_Dim!A:A,Customer_Dim!G:G,"False Data") -> USA | R32: =_xlfn.XLOOKUP(Table17[[#This Row],[Customer_ID]],Customer_Dim!A:A,Customer_Dim!H:H,"False Data") -> Platinum | S32: =_xlfn.XLOOKUP(Table17[[#This Row],[Store_ID]],Store_Dim!A:A,Store_Dim!B:B) -> Mann-Austin | T32: =_xlfn.XLOOKUP(Table17[[#This Row],[Store_ID]],Store_Dim!A:A,Store_Dim!C:C) -> East | U32: =_xlfn.XLOOKUP(Table17[[#This Row],[Store_ID]],Store_Dim!A:A,Store_Dim!D:D) -> Vasquezborough | V32: =_xlfn.XLOOKUP(Table17[[#This Row],[Store_ID]],Store_Dim!A:A,Store_Dim!E:E) -> Online | W32: =_xlfn.XLOOKUP(Table17[[#This Row],[Product_ID]],Product_Dim!A:A,Product_Dim!B:B) -> Men's Leather Belt | X32: =_xlfn.XLOOKUP(Table17[[#This Row],[Product_ID]],Product_Dim!A:A,Product_Dim!C:C) -> Clothing | Y32: =_xlfn.XLOOKUP(Table17[[#This Row],[Product_ID]],Product_Dim!A:A,Product_Dim!D:D) -> Accessories | Z32: =_xlfn.XLOOKUP(Table17[[#This Row],[Product_ID]],Product_Dim!A:A,Product_Dim!E:E) -> Baldwin, Garza and Gonzalez | AA32: =_xlfn.XLOOKUP(Table17[[#This Row],[Product_ID]],Product_Dim!A:A,Product_Dim!F:F) -> 261 | AB32: =_xlfn.XLOOKUP(Table17[[#This Row],[Product_ID]],Product_Dim!A:A,Product_Dim!G:G) -> 59
A33: SALE31 | B33: 45593 | C33: CUST1412 | D33: PROD53 | E33: STORE12 | F33: 2 | G33: 148.96 | H33: 0.03 | I33: COD | J33: 288.9824 | K33: =_xlfn.XLOOKUP(Table17[[#This Row],[Customer_ID]],Customer_Dim!A:A,Customer_Dim!B:B,"False Data") -> Shane Brown | L33: =_xlfn.XLOOKUP(Table17[[#This Row],[Customer_ID]],Customer_Dim!A:A,Customer_Dim!C:C,"False Data") -> 23 | M33: {=_xlfn.IFS(Table9[[#This Row],[Age]]<=35,"Youth",Table9[[#This Row],[Age]]<=55,"Adult",Table9[[#This Row],[Age]]>55,"Senior")} -> Youth | N33: =_xlfn.XLOOKUP(Table17[[#This Row],[Customer_ID]],Customer_Dim!A:A,Customer_Dim!D:D,"False Data") -> Female | O33: =_xlfn.XLOOKUP(Table17[[#This Row],[Customer_ID]],Customer_Dim!A:A,Customer_Dim!E:E,"False Data") -> East Andrea | P33: =_xlfn.XLOOKUP(Table17[[#This Row],[Customer_ID]],Customer_Dim!A:A,Customer_Dim!F:F,"False Data") -> Michigan | Q33: =_xlfn.XLOOKUP(Table17[[#This Row],[Customer_ID]],Customer_Dim!A:A,Customer_Dim!G:G,"False Data") -> USA | R33: =_xlfn.XLOOKUP(Table17[[#This Row],[Customer_ID]],Customer_Dim!A:A,Customer_Dim!H:H,"False Data") -> Gold | S33: =_xlfn.XLOOKUP(Table17[[#This Row],[Store_ID]],Store_Dim!A:A,Store_Dim!B:B) -> Thomas, Bridges and Harris | T33: =_xlfn.XLOOKUP(Table17[[#This Row],[Store_ID]],Store_Dim!A:A,Store_Dim!C:C) -> North | U33: =_xlfn.XLOOKUP(Table17[[#This Row],[Store_ID]],Store_Dim!A:A,Store_Dim!D:D) -> Sabrinatown | V33: =_xlfn.XLOOKUP(Table17[[#This Row],[Store_ID]],Store_Dim!A:A,Store_Dim!E:E) -> Online | W33: =_xlfn.XLOOKUP(Table17[[#This Row],[Product_ID]],Product_Dim!A:A,Product_Dim!B:B) -> Men's Track Pants | X33: =_xlfn.XLOOKUP(Table17[[#This Row],[Product_ID]],Product_Dim!A:A,Product_Dim!C:C) -> Clothing | Y33: =_xlfn.XLOOKUP(Table17[[#This Row],[Product_ID]],Product_Dim!A:A,Product_Dim!D:D) -> Bottoms | Z33: =_xlfn.XLOOKUP(Table17[[#This Row],[Product_ID]],Product_Dim!A:A,Product_Dim!E:E) -> Hamilton, Woods and Walker | AA33: =_xlfn.XLOOKUP(Table17[[#This Row],[Product_ID]],Product_Dim!A:A,Product_Dim!F:F) -> 386.56 | AB33: =_xlfn.XLOOKUP(Table17[[#This Row],[Product_ID]],Product_Dim!A:A,Product_Dim!G:G) -> 125
A34: SALE32 | B34: 45597 | C34: CUST1398 | D34: PROD75 | E34: STORE8 | F34: 4 | G34: 313.83 | H34: 0.08 | I34: Credit Card | J34: 1154.8944 | K34: =_xlfn.XLOOKUP(Table17[[#This Row],[Customer_ID]],Customer_Dim!A:A,Customer_Dim!B:B,"False Data") -> Jennifer Johnson | L34: =_xlfn.XLOOKUP(Table17[[#This Row],[Customer_ID]],Customer_Dim!A:A,Customer_Dim!C:C,"False Data") -> 54 | M34: {=_xlfn.IFS(Table9[[#This Row],[Age]]<=35,"Youth",Table9[[#This Row],[Age]]<=55,"Adult",Table9[[#This Row],[Age]]>55,"Senior")} -> Adult | N34: =_xlfn.XLOOKUP(Table17[[#This Row],[Customer_ID]],Customer_Dim!A:A,Customer_Dim!D:D,"False Data") -> Male | O34: =_xlfn.XLOOKUP(Table17[[#This Row],[Customer_ID]],Customer_Dim!A:A,Customer_Dim!E:E,"False Data") -> Cheyenneborough | P34: =_xlfn.XLOOKUP(Table17[[#This Row],[Customer_ID]],Customer_Dim!A:A,Customer_Dim!F:F,"False Data") -> New Hampshire | Q34: =_xlfn.XLOOKUP(Table17[[#This Row],[Customer_ID]],Customer_Dim!A:A,Customer_Dim!G:G,"False Data") -> USA | R34: =_xlfn.XLOOKUP(Table17[[#This Row],[Customer_ID]],Customer_Dim!A:A,Customer_Dim!H:H,"False Data") -> Bronze | S34: =_xlfn.XLOOKUP(Table17[[#This Row],[Store_ID]],Store_Dim!A:A,Store_Dim!B:B) -> Bean, Jones and Park | T34: =_xlfn.XLOOKUP(Table17[[#This Row],[Store_ID]],Store_Dim!A:A,Store_Dim!C:C) -> West | U34: =_xlfn.XLOOKUP(Table17[[#This Row],[Store_ID]],Store_Dim!A:A,Store_Dim!D:D) -> Thompsonborough | V34: =_xlfn.XLOOKUP(Table17[[#This Row],[Store_ID]],Store_Dim!A:A,Store_Dim!E:E) -> Online | W34: =_xlfn.XLOOKUP(Table17[[#This Row],[Product_ID]],Product_Dim!A:A,Product_Dim!B:B) -> Women's Ankle Boots | X34: =_xlfn.XLOOKUP(Table17[[#This Row],[Product_ID]],Product_Dim!A:A,Product_Dim!C:C) -> Clothing | Y34: =_xlfn.XLOOKUP(Table17[[#This Row],[Product_ID]],Product_Dim!A:A,Product_Dim!D:D) -> Footwear | Z34: =_xlfn.XLOOKUP(Table17[[#This Row],[Product_ID]],Product_Dim!A:A,Product_Dim!E:E) -> Poole PLC | AA34: =_xlfn.XLOOKUP(Table17[[#This Row],[Product_ID]],Product_Dim!A:A,Product_Dim!F:F) -> 158.14 | AB34: =_xlfn.XLOOKUP(Table17[[#This Row],[Product_ID]],Product_Dim!A:A,Product_Dim!G:G) -> 82
A35: SALE33 | B35: 45620 | C35: CUST1453 | D35: PROD12 | E35: STORE6 | F35: 2 | G35: 717.31 | H35: 0.15 | I35: Credit Card | J35: 1219.427 | K35: =_xlfn.XLOOKUP(Table17[[#This Row],[Customer_ID]],Customer_Dim!A:A,Customer_Dim!B:B,"False Data") -> April Phillips | L35: =_xlfn.XLOOKUP(Table17[[#This Row],[Customer_ID]],Customer_Dim!A:A,Customer_Dim!C:C,"False Data") -> 62 | M35: {=_xlfn.IFS(Table9[[#This Row],[Age]]<=35,"Youth",Table9[[#This Row],[Age]]<=55,"Adult",Table9[[#This Row],[Age]]>55,"Senior")} -> Senior | N35: =_xlfn.XLOOKUP(Table17[[#This Row],[Customer_ID]],Customer_Dim!A:A,Customer_Dim!D:D,"False Data") -> Female | O35: =_xlfn.XLOOKUP(Table17[[#This Row],[Customer_ID]],Customer_Dim!A:A,Customer_Dim!E:E,"False Data") -> Lake Carolyn | P35: =_xlfn.XLOOKUP(Table17[[#This Row],[Customer_ID]],Customer_Dim!A:A,Customer_Dim!F:F,"False Data") -> Hawaii | Q35: =_xlfn.XLOOKUP(Table17[[#This Row],[Customer_ID]],Customer_Dim!A:A,Customer_Dim!G:G,"False Data") -> USA | R35: =_xlfn.XLOOKUP(Table17[[#This Row],[Customer_ID]],Customer_Dim!A:A,Customer_Dim!H:H,"False Data") -> Platinum | S35: =_xlfn.XLOOKUP(Table17[[#This Row],[Store_ID]],Store_Dim!A:A,Store_Dim!B:B) -> Benson-Elliott | T35: =_xlfn.XLOOKUP(Table17[[#This Row],[Store_ID]],Store_Dim!A:A,Store_Dim!C:C) -> East | U35: =_xlfn.XLOOKUP(Table17[[#This Row],[Store_ID]],Store_Dim!A:A,Store_Dim!D:D) -> Port Josephberg | V35: =_xlfn.XLOOKUP(Table17[[#This Row],[Store_ID]],Store_Dim!A:A,Store_Dim!E:E) -> Online | W35: =_xlfn.XLOOKUP(Table17[[#This Row],[Product_ID]],Product_Dim!A:A,Product_Dim!B:B) -> Hair Strengthening Shampoo | X35: =_xlfn.XLOOKUP(Table17[[#This Row],[Product_ID]],Product_Dim!A:A,Product_Dim!C:C) -> Beauty | Y35: =_xlfn.XLOOKUP(Table17[[#This Row],[Product_ID]],Product_Dim!A:A,Product_Dim!D:D) -> Haircare | Z35: =_xlfn.XLOOKUP(Table17[[#This Row],[Product_ID]],Product_Dim!A:A,Product_Dim!E:E) -> Rice LLC | AA35: =_xlfn.XLOOKUP(Table17[[#This Row],[Product_ID]],Product_Dim!A:A,Product_Dim!F:F) -> 115.82 | AB35: =_xlfn.XLOOKUP(Table17[[#This Row],[Product_ID]],Product_Dim!A:A,Product_Dim!G:G) -> 460
A36: SALE34 | B36: 45215 | C36: CUST1344 | D36: PROD79 | E36: STORE1 | F36: 3 | G36: 873.22 | H36: 0.18 | I36: Credit Card | J36: 2148.1212 | K36: =_xlfn.XLOOKUP(Table17[[#This Row],[Customer_ID]],Customer_Dim!A:A,Customer_Dim!B:B,"False Data") -> Evelyn Brown | L36: =_xlfn.XLOOKUP(Table17[[#This Row],[Customer_ID]],Customer_Dim!A:A,Customer_Dim!C:C,"False Data") -> 39 | M36: {=_xlfn.IFS(Table9[[#This Row],[Age]]<=35,"Youth",Table9[[#This Row],[Age]]<=55,"Adult",Table9[[#This Row],[Age]]>55,"Senior")} -> Adult | N36: =_xlfn.XLOOKUP(Table17[[#This Row],[Customer_ID]],Customer_Dim!A:A,Customer_Dim!D:D,"False Data") -> Male | O36: =_xlfn.XLOOKUP(Table17[[#This Row],[Customer_ID]],Customer_Dim!A:A,Customer_Dim!E:E,"False Data") -> West Victoriaborough | P36: =_xlfn.XLOOKUP(Table17[[#This Row],[Customer_ID]],Customer_Dim!A:A,Customer_Dim!F:F,"False Data") -> New Mexico | Q36: =_xlfn.XLOOKUP(Table17[[#This Row],[Customer_ID]],Customer_Dim!A:A,Customer_Dim!G:G,"False Data") -> USA | R36: =_xlfn.XLOOKUP(Table17[[#This Row],[Customer_ID]],Customer_Dim!A:A,Customer_Dim!H:H,"False Data") -> Gold | S36: =_xlfn.XLOOKUP(Table17[[#This Row],[Store_ID]],Store_Dim!A:A,Store_Dim!B:B) -> Martinez, Adkins and Johnson | T36: =_xlfn.XLOOKUP(Table17[[#This Row],[Store_ID]],Store_Dim!A:A,Store_Dim!C:C) -> North | U36: =_xlfn.XLOOKUP(Table17[[#This Row],[Store_ID]],Store_Dim!A:A,Store_Dim!D:D) -> Danielmouth | V36: =_xlfn.XLOOKUP(Table17[[#This Row],[Store_ID]],Store_Dim!A:A,Store_Dim!E:E) -> Flagship | W36: =_xlfn.XLOOKUP(Table17[[#This Row],[Product_ID]],Product_Dim!A:A,Product_Dim!B:B) -> Decorative Lamp Shade | X36: =_xlfn.XLOOKUP(Table17[[#This Row],[Product_ID]],Product_Dim!A:A,Product_Dim!C:C) -> Home | Y36: =_xlfn.XLOOKUP(Table17[[#This Row],[Product_ID]],Product_Dim!A:A,Product_Dim!D:D) -> Lighting | Z36: =_xlfn.XLOOKUP(Table17[[#This Row],[Product_ID]],Product_Dim!A:A,Product_Dim!E:E) -> Ramirez-Hanson | AA36: =_xlfn.XLOOKUP(Table17[[#This Row],[Product_ID]],Product_Dim!A:A,Product_Dim!F:F) -> 228.53 | AB36: =_xlfn.XLOOKUP(Table17[[#This Row],[Product_ID]],Product_Dim!A:A,Product_Dim!G:G) -> 469
A37: SALE35 | B37: 45878 | C37: CUST1218 | D37: PROD16 | E37: STORE3 | F37: 4 | G37: 109.36 | H37: 0.19 | I37: COD | J37: 354.3264 | K37: =_xlfn.XLOOKUP(Table17[[#This Row],[Customer_ID]],Customer_Dim!A:A,Customer_Dim!B:B,"False Data") -> Julia Jackson | L37: =_xlfn.XLOOKUP(Table17[[#This Row],[Customer_ID]],Customer_Dim!A:A,Customer_Dim!C:C,"False Data") -> 46 | M37: {=_xlfn.IFS(Table9[[#This Row],[Age]]<=35,"Youth",Table9[[#This Row],[Age]]<=55,"Adult",Table9[[#This Row],[Age]]>55,"Senior")} -> Adult | N37: =_xlfn.XLOOKUP(Table17[[#This Row],[Customer_ID]],Customer_Dim!A:A,Customer_Dim!D:D,"False Data") -> Male | O37: =_xlfn.XLOOKUP(Table17[[#This Row],[Customer_ID]],Customer_Dim!A:A,Customer_Dim!E:E,"False Data") -> Edwardland | P37: =_xlfn.XLOOKUP(Table17[[#This Row],[Customer_ID]],Customer_Dim!A:A,Customer_Dim!F:F,"False Data") -> California | Q37: =_xlfn.XLOOKUP(Table17[[#This Row],[Customer_ID]],Customer_Dim!A:A,Customer_Dim!G:G,"False Data") -> USA | R37: =_xlfn.XLOOKUP(Table17[[#This Row],[Customer_ID]],Customer_Dim!A:A,Customer_Dim!H:H,"False Data") -> Platinum | S37: =_xlfn.XLOOKUP(Table17[[#This Row],[Store_ID]],Store_Dim!A:A,Store_Dim!B:B) -> Johnson-Wright | T37: =_xlfn.XLOOKUP(Table17[[#This Row],[Store_ID]],Store_Dim!A:A,Store_Dim!C:C) -> North | U37: =_xlfn.XLOOKUP(Table17[[#This Row],[Store_ID]],Store_Dim!A:A,Store_Dim!D:D) -> Hoodberg | V37: =_xlfn.XLOOKUP(Table17[[#This Row],[Store_ID]],Store_Dim!A:A,Store_Dim!E:E) -> Outlet | W37: =_xlfn.XLOOKUP(Table17[[#This Row],[Product_ID]],Product_Dim!A:A,Product_Dim!B:B) -> Beard Grooming Kit | X37: =_xlfn.XLOOKUP(Table17[[#This Row],[Product_ID]],Product_Dim!A:A,Product_Dim!C:C) -> Beauty | Y37: =_xlfn.XLOOKUP(Table17[[#This Row],[Product_ID]],Product_Dim!A:A,Product_Dim!D:D) -> Grooming | Z37: =_xlfn.XLOOKUP(Table17[[#This Row],[Product_ID]],Product_Dim!A:A,Product_Dim!E:E) -> Erickson-Green | AA37: =_xlfn.XLOOKUP(Table17[[#This Row],[Product_ID]],Product_Dim!A:A,Product_Dim!F:F) -> 337.42 | AB37: =_xlfn.XLOOKUP(Table17[[#This Row],[Product_ID]],Product_Dim!A:A,Product_Dim!G:G) -> 256
A38: SALE36 | B38: 45635 | C38: CUST1086 | D38: PROD5 | E38: STORE7 | F38: 3 | G38: 559.52 | H38: 0.16 | I38: PayPal | J38: 1409.9904 | K38: =_xlfn.XLOOKUP(Table17[[#This Row],[Customer_ID]],Customer_Dim!A:A,Customer_Dim!B:B,"False Data") -> Tammy Miller Md | L38: =_xlfn.XLOOKUP(Table17[[#This Row],[Customer_ID]],Customer_Dim!A:A,Customer_Dim!C:C,"False Data") -> 19 | M38: {=_xlfn.IFS(Table9[[#This Row],[Age]]<=35,"Youth",Table9[[#This Row],[Age]]<=55,"Adult",Table9[[#This Row],[Age]]>55,"Senior")} -> Youth | N38: =_xlfn.XLOOKUP(Table17[[#This Row],[Customer_ID]],Customer_Dim!A:A,Customer_Dim!D:D,"False Data") -> Female | O38: =_xlfn.XLOOKUP(Table17[[#This Row],[Customer_ID]],Customer_Dim!A:A,Customer_Dim!E:E,"False Data") -> Austinfurt | P38: =_xlfn.XLOOKUP(Table17[[#This Row],[Customer_ID]],Customer_Dim!A:A,Customer_Dim!F:F,"False Data") -> Mississippi | Q38: =_xlfn.XLOOKUP(Table17[[#This Row],[Customer_ID]],Customer_Dim!A:A,Customer_Dim!G:G,"False Data") -> USA | R38: =_xlfn.XLOOKUP(Table17[[#This Row],[Customer_ID]],Customer_Dim!A:A,Customer_Dim!H:H,"False Data") -> Gold | S38: =_xlfn.XLOOKUP(Table17[[#This Row],[Store_ID]],Store_Dim!A:A,Store_Dim!B:B) -> Martinez-Mullins | T38: =_xlfn.XLOOKUP(Table17[[#This Row],[Store_ID]],Store_Dim!A:A,Store_Dim!C:C) -> South | U38: =_xlfn.XLOOKUP(Table17[[#This Row],[Store_ID]],Store_Dim!A:A,Store_Dim!D:D) -> Williamsfurt | V38: =_xlfn.XLOOKUP(Table17[[#This Row],[Store_ID]],Store_Dim!A:A,Store_Dim!E:E) -> Online | W38: =_xlfn.XLOOKUP(Table17[[#This Row],[Product_ID]],Product_Dim!A:A,Product_Dim!B:B) -> Men's Leather Belt | X38: =_xlfn.XLOOKUP(Table17[[#This Row],[Product_ID]],Product_Dim!A:A,Product_Dim!C:C) -> Clothing | Y38: =_xlfn.XLOOKUP(Table17[[#This Row],[Product_ID]],Product_Dim!A:A,Product_Dim!D:D) -> Accessories | Z38: =_xlfn.XLOOKUP(Table17[[#This Row],[Product_ID]],Product_Dim!A:A,Product_Dim!E:E) -> Baldwin, Garza and Gonzalez | AA38: =_xlfn.XLOOKUP(Table17[[#This Row],[Product_ID]],Product_Dim!A:A,Product_Dim!F:F) -> 261 | AB38: =_xlfn.XLOOKUP(Table17[[#This Row],[Product_ID]],Product_Dim!A:A,Product_Dim!G:G) -> 59
A39: SALE37 | B39: 45329 | C39: CUST1492 | D39: PROD10 | E39: STORE17 | F39: 3 | G39: 121.76 | H39: 0.27 | I39: PayPal | J39: 266.6544 | K39: =_xlfn.XLOOKUP(Table17[[#This Row],[Customer_ID]],Customer_Dim!A:A,Customer_Dim!B:B,"False Data") -> Darrell Miller | L39: =_xlfn.XLOOKUP(Table17[[#This Row],[Customer_ID]],Customer_Dim!A:A,Customer_Dim!C:C,"False Data") -> 59 | M39: {=_xlfn.IFS(Table9[[#This Row],[Age]]<=35,"Youth",Table9[[#This Row],[Age]]<=55,"Adult",Table9[[#This Row],[Age]]>55,"Senior")} -> Senior | N39: =_xlfn.XLOOKUP(Table17[[#This Row],[Customer_ID]],Customer_Dim!A:A,Customer_Dim!D:D,"False Data") -> Female | O39: =_xlfn.XLOOKUP(Table17[[#This Row],[Customer_ID]],Customer_Dim!A:A,Customer_Dim!E:E,"False Data") -> Port Carol | P39: =_xlfn.XLOOKUP(Table17[[#This Row],[Customer_ID]],Customer_Dim!A:A,Customer_Dim!F:F,"False Data") -> Florida | Q39: =_xlfn.XLOOKUP(Table17[[#This Row],[Customer_ID]],Customer_Dim!A:A,Customer_Dim!G:G,"False Data") -> USA | R39: =_xlfn.XLOOKUP(Table17[[#This Row],[Customer_ID]],Customer_Dim!A:A,Customer_Dim!H:H,"False Data") -> Platinum | S39: =_xlfn.XLOOKUP(Table17[[#This Row],[Store_ID]],Store_Dim!A:A,Store_Dim!B:B) -> Holloway Ltd | T39: =_xlfn.XLOOKUP(Table17[[#This Row],[Store_ID]],Store_Dim!A:A,Store_Dim!C:C) -> North | U39: =_xlfn.XLOOKUP(Table17[[#This Row],[Store_ID]],Store_Dim!A:A,Store_Dim!D:D) -> Bensonhaven | V39: =_xlfn.XLOOKUP(Table17[[#This Row],[Store_ID]],Store_Dim!A:A,Store_Dim!E:E) -> Flagship | W39: =_xlfn.XLOOKUP(Table17[[#This Row],[Product_ID]],Product_Dim!A:A,Product_Dim!B:B) -> Ceramic Kitchen Bowl Set | X39: =_xlfn.XLOOKUP(Table17[[#This Row],[Product_ID]],Product_Dim!A:A,Product_Dim!C:C) -> Home | Y39: =_xlfn.XLOOKUP(Table17[[#This Row],[Product_ID]],Product_Dim!A:A,Product_Dim!D:D) -> Kitchen | Z39: =_xlfn.XLOOKUP(Table17[[#This Row],[Product_ID]],Product_Dim!A:A,Product_Dim!E:E) -> Hamilton Group | AA39: =_xlfn.XLOOKUP(Table17[[#This Row],[Product_ID]],Product_Dim!A:A,Product_Dim!F:F) -> 298.86 | AB39: =_xlfn.XLOOKUP(Table17[[#This Row],[Product_ID]],Product_Dim!A:A,Product_Dim!G:G) -> 308
A40: SALE38 | B40: 45378 | C40: CUST1189 | D40: PROD33 | E40: STORE13 | F40: 4 | G40: 735.32 | H40: 0.06 | I40: COD | J40: 2764.8032 | K40: =_xlfn.XLOOKUP(Table17[[#This Row],[Customer_ID]],Customer_Dim!A:A,Customer_Dim!B:B,"False Data") -> Daniel Austin | L40: =_xlfn.XLOOKUP(Table17[[#This Row],[Customer_ID]],Customer_Dim!A:A,Customer_Dim!C:C,"False Data") -> 29 | M40: {=_xlfn.IFS(Table9[[#This Row],[Age]]<=35,"Youth",Table9[[#This Row],[Age]]<=55,"Adult",Table9[[#This Row],[Age]]>55,"Senior")} -> Youth | N40: =_xlfn.XLOOKUP(Table17[[#This Row],[Customer_ID]],Customer_Dim!A:A,Customer_Dim!D:D,"False Data") -> Male | O40: =_xlfn.XLOOKUP(Table17[[#This Row],[Customer_ID]],Customer_Dim!A:A,Customer_Dim!E:E,"False Data") -> Lake Howardberg | P40: =_xlfn.XLOOKUP(Table17[[#This Row],[Customer_ID]],Customer_Dim!A:A,Customer_Dim!F:F,"False Data") -> Kentucky | Q40: =_xlfn.XLOOKUP(Table17[[#This Row],[Customer_ID]],Customer_Dim!A:A,Customer_Dim!G:G,"False Data") -> USA | R40: =_xlfn.XLOOKUP(Table17[[#This Row],[Customer_ID]],Customer_Dim!A:A,Customer_Dim!H:H,"False Data") -> Gold | S40: =_xlfn.XLOOKUP(Table17[[#This Row],[Store_ID]],Store_Dim!A:A,Store_Dim!B:B) -> Gardner, Humphrey and Contreras | T40: =_xlfn.XLOOKUP(Table17[[#This Row],[Store_ID]],Store_Dim!A:A,Store_Dim!C:C) -> East | U40: =_xlfn.XLOOKUP(Table17[[#This Row],[Store_ID]],Store_Dim!A:A,Store_Dim!D:D) -> Johnsonville | V40: =_xlfn.XLOOKUP(Table17[[#This Row],[Store_ID]],Store_Dim!A:A,Store_Dim!E:E) -> Flagship | W40: =_xlfn.XLOOKUP(Table17[[#This Row],[Product_ID]],Product_Dim!A:A,Product_Dim!B:B) -> Modern Wall Clock | X40: =_xlfn.XLOOKUP(Table17[[#This Row],[Product_ID]],Product_Dim!A:A,Product_Dim!C:C) -> Home | Y40: =_xlfn.XLOOKUP(Table17[[#This Row],[Product_ID]],Product_Dim!A:A,Product_Dim!D:D) -> Decor | Z40: =_xlfn.XLOOKUP(Table17[[#This Row],[Product_ID]],Product_Dim!A:A,Product_Dim!E:E) -> Weiss-Watson | AA40: =_xlfn.XLOOKUP(Table17[[#This Row],[Product_ID]],Product_Dim!A:A,Product_Dim!F:F) -> 179.77 | AB40: =_xlfn.XLOOKUP(Table17[[#This Row],[Product_ID]],Product_Dim!A:A,Product_Dim!G:G) -> 305
... A53: SALE51 | B53: 45689 | C53: CUST1142 | D53: PROD69 | E53: STORE7 | F53: 3 | G53: 76.57 | H53: 0.26 | I53: Credit Card | J53: 169.9854 | K53: =_xlfn.XLOOKUP(Table17[[#This Row],[Customer_ID]],Customer_Dim!A:A,Customer_Dim!B:B,"False Data") -> Maria Ramirez | L53: =_xlfn.XLOOKUP(Table17[[#This Row],[Customer_ID]],Customer_Dim!A:A,Customer_Dim!C:C,"False Data") -> 37 | M53: {=_xlfn.IFS(Table9[[#This Row],[Age]]<=35,"Youth",Table9[[#This Row],[Age]]<=55,"Adult",Table9[[#This Row],[Age]]>55,"Senior")} -> Adult | N53: =_xlfn.XLOOKUP(Table17[[#This Row],[Customer_ID]],Customer_Dim!A:A,Customer_Dim!D:D,"False Data") -> Male | O53: =_xlfn.XLOOKUP(Table17[[#This Row],[Customer_ID]],Customer_Dim!A:A,Customer_Dim!E:E,"False Data") -> West Brandon | P53: =_xlfn.XLOOKUP(Table17[[#This Row],[Customer_ID]],Customer_Dim!A:A,Customer_Dim!F:F,"False Data") -> Montana | Q53: =_xlfn.XLOOKUP(Table17[[#This Row],[Customer_ID]],Customer_Dim!A:A,Customer_Dim!G:G,"False Data") -> USA | R53: =_xlfn.XLOOKUP(Table17[[#This Row],[Customer_ID]],Customer_Dim!A:A,Customer_Dim!H:H,"False Data") -> Bronze | S53: =_xlfn.XLOOKUP(Table17[[#This Row],[Store_ID]],Store_Dim!A:A,Store_Dim!B:B) -> Martinez-Mullins | T53: =_xlfn.XLOOKUP(Table17[[#This Row],[Store_ID]],Store_Dim!A:A,Store_Dim!C:C) -> South | U53: =_xlfn.XLOOKUP(Table17[[#This Row],[Store_ID]],Store_Dim!A:A,Store_Dim!D:D) -> Williamsfurt | V53: =_xlfn.XLOOKUP(Table17[[#This Row],[Store_ID]],Store_Dim!A:A,Store_Dim!E:E) -> Online | W53: =_xlfn.XLOOKUP(Table17[[#This Row],[Product_ID]],Product_Dim!A:A,Product_Dim!B:B) -> Men's Sports Shorts | X53: =_xlfn.XLOOKUP(Table17[[#This Row],[Product_ID]],Product_Dim!A:A,Product_Dim!C:C) -> Clothing | Y53: =_xlfn.XLOOKUP(Table17[[#This Row],[Product_ID]],Product_Dim!A:A,Product_Dim!D:D) -> Bottoms | Z53: =_xlfn.XLOOKUP(Table17[[#This Row],[Product_ID]],Product_Dim!A:A,Product_Dim!E:E) -> Fitzpatrick Ltd | AA53: =_xlfn.XLOOKUP(Table17[[#This Row],[Product_ID]],Product_Dim!A:A,Product_Dim!F:F) -> 218.22 | AB53: =_xlfn.XLOOKUP(Table17[[#This Row],[Product_ID]],Product_Dim!A:A,Product_Dim!G:G) -> 224
A54: SALE52 | B54: 45894 | C54: CUST1148 | D54: PROD89 | E54: STORE6 | F54: 3 | G54: =Table17[[#This Row],[Total_Amount]]/3 -> 162.0211 | H54: 0 | I54: Credit Card | J54: 486.0633 | K54: =_xlfn.XLOOKUP(Table17[[#This Row],[Customer_ID]],Customer_Dim!A:A,Customer_Dim!B:B,"False Data") -> Theresa Campbell | L54: =_xlfn.XLOOKUP(Table17[[#This Row],[Customer_ID]],Customer_Dim!A:A,Customer_Dim!C:C,"False Data") -> 42 | M54: {=_xlfn.IFS(Table9[[#This Row],[Age]]<=35,"Youth",Table9[[#This Row],[Age]]<=55,"Adult",Table9[[#This Row],[Age]]>55,"Senior")} -> Adult | N54: =_xlfn.XLOOKUP(Table17[[#This Row],[Customer_ID]],Customer_Dim!A:A,Customer_Dim!D:D,"False Data") -> Female | O54: =_xlfn.XLOOKUP(Table17[[#This Row],[Customer_ID]],Customer_Dim!A:A,Customer_Dim!E:E,"False Data") -> New Brian | P54: =_xlfn.XLOOKUP(Table17[[#This Row],[Customer_ID]],Customer_Dim!A:A,Customer_Dim!F:F,"False Data") -> Wisconsin | Q54: =_xlfn.XLOOKUP(Table17[[#This Row],[Customer_ID]],Customer_Dim!A:A,Customer_Dim!G:G,"False Data") -> USA | R54: =_xlfn.XLOOKUP(Table17[[#This Row],[Customer_ID]],Customer_Dim!A:A,Customer_Dim!H:H,"False Data") -> Bronze | S54: =_xlfn.XLOOKUP(Table17[[#This Row],[Store_ID]],Store_Dim!A:A,Store_Dim!B:B) -> Benson-Elliott | T54: =_xlfn.XLOOKUP(Table17[[#This Row],[Store_ID]],Store_Dim!A:A,Store_Dim!C:C) -> East | U54: =_xlfn.XLOOKUP(Table17[[#This Row],[Store_ID]],Store_Dim!A:A,Store_Dim!D:D) -> Port Josephberg | V54: =_xlfn.XLOOKUP(Table17[[#This Row],[Store_ID]],Store_Dim!A:A,Store_Dim!E:E) -> Online | W54: =_xlfn.XLOOKUP(Table17[[#This Row],[Product_ID]],Product_Dim!A:A,Product_Dim!B:B) -> Face Foundation Kit | X54: =_xlfn.XLOOKUP(Table17[[#This Row],[Product_ID]],Product_Dim!A:A,Product_Dim!C:C) -> Beauty | Y54: =_xlfn.XLOOKUP(Table17[[#This Row],[Product_ID]],Product_Dim!A:A,Product_Dim!D:D) -> Makeup | Z54: =_xlfn.XLOOKUP(Table17[[#This Row],[Product_ID]],Product_Dim!A:A,Product_Dim!E:E) -> Taylor-Elliott | AA54: =_xlfn.XLOOKUP(Table17[[#This Row],[Product_ID]],Product_Dim!A:A,Product_Dim!F:F) -> 183.04 | AB54: =_xlfn.XLOOKUP(Table17[[#This Row],[Product_ID]],Product_Dim!A:A,Product_Dim!G:G) -> 457
A55: SALE53 | B55: 45677 | C55: CUST1324 | D55: PROD20 | E55: STORE8 | F55: 1 | G55: 900.35 | H55: 0.13 | I55: COD | J55: 783.3045 | K55: =_xlfn.XLOOKUP(Table17[[#This Row],[Customer_ID]],Customer_Dim!A:A,Customer_Dim!B:B,"False Data") -> Alex Mann Ii | L55: =_xlfn.XLOOKUP(Table17[[#This Row],[Customer_ID]],Customer_Dim!A:A,Customer_Dim!C:C,"False Data") -> 58 | M55: {=_xlfn.IFS(Table9[[#This Row],[Age]]<=35,"Youth",Table9[[#This Row],[Age]]<=55,"Adult",Table9[[#This Row],[Age]]>55,"Senior")} -> Senior | N55: =_xlfn.XLOOKUP(Table17[[#This Row],[Customer_ID]],Customer_Dim!A:A,Customer_Dim!D:D,"False Data") -> Male | O55: =_xlfn.XLOOKUP(Table17[[#This Row],[Customer_ID]],Customer_Dim!A:A,Customer_Dim!E:E,"False Data") -> South Zacharychester | P55: =_xlfn.XLOOKUP(Table17[[#This Row],[Customer_ID]],Customer_Dim!A:A,Customer_Dim!F:F,"False Data") -> Oklahoma | Q55: =_xlfn.XLOOKUP(Table17[[#This Row],[Customer_ID]],Customer_Dim!A:A,Customer_Dim!G:G,"False Data") -> USA | R55: =_xlfn.XLOOKUP(Table17[[#This Row],[Customer_ID]],Customer_Dim!A:A,Customer_Dim!H:H,"False Data") -> Bronze | S55: =_xlfn.XLOOKUP(Table17[[#This Row],[Store_ID]],Store_Dim!A:A,Store_Dim!B:B) -> Bean, Jones and Park | T55: =_xlfn.XLOOKUP(Table17[[#This Row],[Store_ID]],Store_Dim!A:A,Store_Dim!C:C) -> West | U55: =_xlfn.XLOOKUP(Table17[[#This Row],[Store_ID]],Store_Dim!A:A,Store_Dim!D:D) -> Thompsonborough | V55: =_xlfn.XLOOKUP(Table17[[#This Row],[Store_ID]],Store_Dim!A:A,Store_Dim!E:E) -> Online | W55: =_xlfn.XLOOKUP(Table17[[#This Row],[Product_ID]],Product_Dim!A:A,Product_Dim!B:B) -> Outdoor Sports Water Bottle | X55: =_xlfn.XLOOKUP(Table17[[#This Row],[Product_ID]],Product_Dim!A:A,Product_Dim!C:C) -> Sports | Y55: =_xlfn.XLOOKUP(Table17[[#This Row],[Product_ID]],Product_Dim!A:A,Product_Dim!D:D) -> Accessories | Z55: =_xlfn.XLOOKUP(Table17[[#This Row],[Product_ID]],Product_Dim!A:A,Product_Dim!E:E) -> Soto-Ellis | AA55: =_xlfn.XLOOKUP(Table17[[#This Row],[Product_ID]],Product_Dim!A:A,Product_Dim!F:F) -> 131.51 | AB55: =_xlfn.XLOOKUP(Table17[[#This Row],[Product_ID]],Product_Dim!A:A,Product_Dim!G:G) -> 0
A56: SALE54 | B56: 45706 | C56: CUST1095 | D56: PROD40 | E56: STORE10 | F56: 4 | G56: 428.09 | H56: 0.07 | I56: Credit Card | J56: 1592.4948 | K56: =_xlfn.XLOOKUP(Table17[[#This Row],[Customer_ID]],Customer_Dim!A:A,Customer_Dim!B:B,"False Data") -> Amy Fowler | L56: =_xlfn.XLOOKUP(Table17[[#This Row],[Customer_ID]],Customer_Dim!A:A,Customer_Dim!C:C,"False Data") -> 62 | M56: {=_xlfn.IFS(Table9[[#This Row],[Age]]<=35,"Youth",Table9[[#This Row],[Age]]<=55,"Adult",Table9[[#This Row],[Age]]>55,"Senior")} -> Senior | N56: =_xlfn.XLOOKUP(Table17[[#This Row],[Customer_ID]],Customer_Dim!A:A,Customer_Dim!D:D,"False Data") -> Female | O56: =_xlfn.XLOOKUP(Table17[[#This Row],[Customer_ID]],Customer_Dim!A:A,Customer_Dim!E:E,"False Data") -> West Bobbyshire | P56: =_xlfn.XLOOKUP(Table17[[#This Row],[Customer_ID]],Customer_Dim!A:A,Customer_Dim!F:F,"False Data") -> New York | Q56: =_xlfn.XLOOKUP(Table17[[#This Row],[Customer_ID]],Customer_Dim!A:A,Customer_Dim!G:G,"False Data") -> USA | R56: =_xlfn.XLOOKUP(Table17[[#This Row],[Customer_ID]],Customer_Dim!A:A,Customer_Dim!H:H,"False Data") -> Platinum | S56: =_xlfn.XLOOKUP(Table17[[#This Row],[Store_ID]],Store_Dim!A:A,Store_Dim!B:B) -> Hill, Wagner and Ballard | T56: =_xlfn.XLOOKUP(Table17[[#This Row],[Store_ID]],Store_Dim!A:A,Store_Dim!C:C) -> East | U56: =_xlfn.XLOOKUP(Table17[[#This Row],[Store_ID]],Store_Dim!A:A,Store_Dim!D:D) -> East Davidville | V56: =_xlfn.XLOOKUP(Table17[[#This Row],[Store_ID]],Store_Dim!A:A,Store_Dim!E:E) -> Online | W56: =_xlfn.XLOOKUP(Table17[[#This Row],[Product_ID]],Product_Dim!A:A,Product_Dim!B:B) -> Noise-Canceling Headphones | X56: =_xlfn.XLOOKUP(Table17[[#This Row],[Product_ID]],Product_Dim!A:A,Product_Dim!C:C) -> Electronics | Y56: =_xlfn.XLOOKUP(Table17[[#This Row],[Product_ID]],Product_Dim!A:A,Product_Dim!D:D) -> Audio | Z56: =_xlfn.XLOOKUP(Table17[[#This Row],[Product_ID]],Product_Dim!A:A,Product_Dim!E:E) -> Taylor-Hart | AA56: =_xlfn.XLOOKUP(Table17[[#This Row],[Product_ID]],Product_Dim!A:A,Product_Dim!F:F) -> 38.52 | AB56: =_xlfn.XLOOKUP(Table17[[#This Row],[Product_ID]],Product_Dim!A:A,Product_Dim!G:G) -> 378
A57: SALE55 | B57: 45589 | C57: CUST1416 | D57: PROD49 | E57: STORE11 | F57: 2 | G57: 559.71 | H57: 0.3 | I57: COD | J57: 783.594 | K57: =_xlfn.XLOOKUP(Table17[[#This Row],[Customer_ID]],Customer_Dim!A:A,Customer_Dim!B:B,"False Data") -> Jennifer Myers | L57: =_xlfn.XLOOKUP(Table17[[#This Row],[Customer_ID]],Customer_Dim!A:A,Customer_Dim!C:C,"False Data") -> 46 | M57: {=_xlfn.IFS(Table9[[#This Row],[Age]]<=35,"Youth",Table9[[#This Row],[Age]]<=55,"Adult",Table9[[#This Row],[Age]]>55,"Senior")} -> Adult | N57: =_xlfn.XLOOKUP(Table17[[#This Row],[Customer_ID]],Customer_Dim!A:A,Customer_Dim!D:D,"False Data") -> Male | O57: =_xlfn.XLOOKUP(Table17[[#This Row],[Customer_ID]],Customer_Dim!A:A,Customer_Dim!E:E,"False Data") -> Marthaborough | P57: =_xlfn.XLOOKUP(Table17[[#This Row],[Customer_ID]],Customer_Dim!A:A,Customer_Dim!F:F,"False Data") -> Wisconsin | Q57: =_xlfn.XLOOKUP(Table17[[#This Row],[Customer_ID]],Customer_Dim!A:A,Customer_Dim!G:G,"False Data") -> USA | R57: =_xlfn.XLOOKUP(Table17[[#This Row],[Customer_ID]],Customer_Dim!A:A,Customer_Dim!H:H,"False Data") -> Platinum | S57: =_xlfn.XLOOKUP(Table17[[#This Row],[Store_ID]],Store_Dim!A:A,Store_Dim!B:B) -> Aguirre-Keller | T57: =_xlfn.XLOOKUP(Table17[[#This Row],[Store_ID]],Store_Dim!A:A,Store_Dim!C:C) -> South | U57: =_xlfn.XLOOKUP(Table17[[#This Row],[Store_ID]],Store_Dim!A:A,Store_Dim!D:D) -> Lake Michael | V57: =_xlfn.XLOOKUP(Table17[[#This Row],[Store_ID]],Store_Dim!A:A,Store_Dim!E:E) -> Online | W57: =_xlfn.XLOOKUP(Table17[[#This Row],[Product_ID]],Product_Dim!A:A,Product_Dim!B:B) -> Men's Roll-On Perfume | X57: =_xlfn.XLOOKUP(Table17[[#This Row],[Product_ID]],Product_Dim!A:A,Product_Dim!C:C) -> Beauty | Y57: =_xlfn.XLOOKUP(Table17[[#This Row],[Product_ID]],Product_Dim!A:A,Product_Dim!D:D) -> Fragrance | Z57: =_xlfn.XLOOKUP(Table17[[#This Row],[Product_ID]],Product_Dim!A:A,Product_Dim!E:E) -> Sullivan and Sons | AA57: =_xlfn.XLOOKUP(Table17[[#This Row],[Product_ID]],Product_Dim!A:A,Product_Dim!F:F) -> 43.29 | AB57: =_xlfn.XLOOKUP(Table17[[#This Row],[Product_ID]],Product_Dim!A:A,Product_Dim!G:G) -> 267
A58: SALE56 | B58: 45282 | C58: CUST1080 | D58: PROD34 | E58: STORE6 | F58: 2 | G58: 833.7 | H58: 0.06 | I58: PayPal | J58: 1567.356 | K58: =_xlfn.XLOOKUP(Table17[[#This Row],[Customer_ID]],Customer_Dim!A:A,Customer_Dim!B:B,"False Data") -> Jennifer Garcia | L58: =_xlfn.XLOOKUP(Table17[[#This Row],[Customer_ID]],Customer_Dim!A:A,Customer_Dim!C:C,"False Data") -> 61 | M58: {=_xlfn.IFS(Table9[[#This Row],[Age]]<=35,"Youth",Table9[[#This Row],[Age]]<=55,"Adult",Table9[[#This Row],[Age]]>55,"Senior")} -> Senior | N58: =_xlfn.XLOOKUP(Table17[[#This Row],[Customer_ID]],Customer_Dim!A:A,Customer_Dim!D:D,"False Data") -> Female | O58: =_xlfn.XLOOKUP(Table17[[#This Row],[Customer_ID]],Customer_Dim!A:A,Customer_Dim!E:E,"False Data") -> New Sean | P58: =_xlfn.XLOOKUP(Table17[[#This Row],[Customer_ID]],Customer_Dim!A:A,Customer_Dim!F:F,"False Data") -> New Mexico | Q58: =_xlfn.XLOOKUP(Table17[[#This Row],[Customer_ID]],Customer_Dim!A:A,Customer_Dim!G:G,"False Data") -> USA | R58: =_xlfn.XLOOKUP(Table17[[#This Row],[Customer_ID]],Customer_Dim!A:A,Customer_Dim!H:H,"False Data") -> Bronze | S58: =_xlfn.XLOOKUP(Table17[[#This Row],[Store_ID]],Store_Dim!A:A,Store_Dim!B:B) -> Benson-Elliott | T58: =_xlfn.XLOOKUP(Table17[[#This Row],[Store_ID]],Store_Dim!A:A,Store_Dim!C:C) -> East | U58: =_xlfn.XLOOKUP(Table17[[#This Row],[Store_ID]],Store_Dim!A:A,Store_Dim!D:D) -> Port Josephberg | V58: =_xlfn.XLOOKUP(Table17[[#This Row],[Store_ID]],Store_Dim!A:A,Store_Dim!E:E) -> Online | W58: =_xlfn.XLOOKUP(Table17[[#This Row],[Product_ID]],Product_Dim!A:A,Product_Dim!B:B) -> Gaming Mechanical Keyboard | X58: =_xlfn.XLOOKUP(Table17[[#This Row],[Product_ID]],Product_Dim!A:A,Product_Dim!C:C) -> Electronics | Y58: =_xlfn.XLOOKUP(Table17[[#This Row],[Product_ID]],Product_Dim!A:A,Product_Dim!D:D) -> Computer | Z58: =_xlfn.XLOOKUP(Table17[[#This Row],[Product_ID]],Product_Dim!A:A,Product_Dim!E:E) -> Lucero LLC | AA58: =_xlfn.XLOOKUP(Table17[[#This Row],[Product_ID]],Product_Dim!A:A,Product_Dim!F:F) -> 419.28 | AB58: =_xlfn.XLOOKUP(Table17[[#This Row],[Product_ID]],Product_Dim!A:A,Product_Dim!G:G) -> 86
A59: SALE57 | B59: 45462 | C59: CUST1467 | D59: PROD47 | E59: STORE14 | F59: 2 | G59: 680.16 | H59: 0.28 | I59: Credit Card | J59: 979.4304 | K59: =_xlfn.XLOOKUP(Table17[[#This Row],[Customer_ID]],Customer_Dim!A:A,Customer_Dim!B:B,"False Data") -> Michael Foley | L59: =_xlfn.XLOOKUP(Table17[[#This Row],[Customer_ID]],Customer_Dim!A:A,Customer_Dim!C:C,"False Data") -> 63 | M59: {=_xlfn.IFS(Table9[[#This Row],[Age]]<=35,"Youth",Table9[[#This Row],[Age]]<=55,"Adult",Table9[[#This Row],[Age]]>55,"Senior")} -> Senior | N59: =_xlfn.XLOOKUP(Table17[[#This Row],[Customer_ID]],Customer_Dim!A:A,Customer_Dim!D:D,"False Data") -> Female | O59: =_xlfn.XLOOKUP(Table17[[#This Row],[Customer_ID]],Customer_Dim!A:A,Customer_Dim!E:E,"False Data") -> Oneillfurt | P59: =_xlfn.XLOOKUP(Table17[[#This Row],[Customer_ID]],Customer_Dim!A:A,Customer_Dim!F:F,"False Data") -> Vermont | Q59: =_xlfn.XLOOKUP(Table17[[#This Row],[Customer_ID]],Customer_Dim!A:A,Customer_Dim!G:G,"False Data") -> USA | R59: =_xlfn.XLOOKUP(Table17[[#This Row],[Customer_ID]],Customer_Dim!A:A,Customer_Dim!H:H,"False Data") -> Gold | S59: =_xlfn.XLOOKUP(Table17[[#This Row],[Store_ID]],Store_Dim!A:A,Store_Dim!B:B) -> Mcdonald Inc | T59: =_xlfn.XLOOKUP(Table17[[#This Row],[Store_ID]],Store_Dim!A:A,Store_Dim!C:C) -> South | U59: =_xlfn.XLOOKUP(Table17[[#This Row],[Store_ID]],Store_Dim!A:A,Store_Dim!D:D) -> Christopherland | V59: =_xlfn.XLOOKUP(Table17[[#This Row],[Store_ID]],Store_Dim!A:A,Store_Dim!E:E) -> Outlet | W59: =_xlfn.XLOOKUP(Table17[[#This Row],[Product_ID]],Product_Dim!A:A,Product_Dim!B:B) -> Makeup Brush Set | X59: =_xlfn.XLOOKUP(Table17[[#This Row],[Product_ID]],Product_Dim!A:A,Product_Dim!C:C) -> Beauty | Y59: =_xlfn.XLOOKUP(Table17[[#This Row],[Product_ID]],Product_Dim!A:A,Product_Dim!D:D) -> Makeup | Z59: =_xlfn.XLOOKUP(Table17[[#This Row],[Product_ID]],Product_Dim!A:A,Product_Dim!E:E) -> Cook Inc | AA59: =_xlfn.XLOOKUP(Table17[[#This Row],[Product_ID]],Product_Dim!A:A,Product_Dim!F:F) -> 241 | AB59: =_xlfn.XLOOKUP(Table17[[#This Row],[Product_ID]],Product_Dim!A:A,Product_Dim!G:G) -> 431
A60: SALE58 | B60: 45633 | C60: CUST1404 | D60: PROD15 | E60: STORE7 | F60: 4 | G60: 733.42 | H60: =1-(Table17[[#This Row],[Total_Amount]]/(Table17[[#This Row],[Unit_Price]]*Table17[[#This Row],[Quantity]])) -> 0.13 | I60: PayPal | J60: 2552.3016 | K60: =_xlfn.XLOOKUP(Table17[[#This Row],[Customer_ID]],Customer_Dim!A:A,Customer_Dim!B:B,"False Data") -> David Ross | L60: =_xlfn.XLOOKUP(Table17[[#This Row],[Customer_ID]],Customer_Dim!A:A,Customer_Dim!C:C,"False Data") -> 22 | M60: {=_xlfn.IFS(Table9[[#This Row],[Age]]<=35,"Youth",Table9[[#This Row],[Age]]<=55,"Adult",Table9[[#This Row],[Age]]>55,"Senior")} -> Youth | N60: =_xlfn.XLOOKUP(Table17[[#This Row],[Customer_ID]],Customer_Dim!A:A,Customer_Dim!D:D,"False Data") -> Female | O60: =_xlfn.XLOOKUP(Table17[[#This Row],[Customer_ID]],Customer_Dim!A:A,Customer_Dim!E:E,"False Data") -> South Angela | P60: =_xlfn.XLOOKUP(Table17[[#This Row],[Customer_ID]],Customer_Dim!A:A,Customer_Dim!F:F,"False Data") -> Arkansas | Q60: =_xlfn.XLOOKUP(Table17[[#This Row],[Customer_ID]],Customer_Dim!A:A,Customer_Dim!G:G,"False Data") -> USA | R60: =_xlfn.XLOOKUP(Table17[[#This Row],[Customer_ID]],Customer_Dim!A:A,Customer_Dim!H:H,"False Data") -> Silver | S60: =_xlfn.XLOOKUP(Table17[[#This Row],[Store_ID]],Store_Dim!A:A,Store_Dim!B:B) -> Martinez-Mullins | T60: =_xlfn.XLOOKUP(Table17[[#This Row],[Store_ID]],Store_Dim!A:A,Store_Dim!C:C) -> South | U60: =_xlfn.XLOOKUP(Table17[[#This Row],[Store_ID]],Store_Dim!A:A,Store_Dim!D:D) -> Williamsfurt | V60: =_xlfn.XLOOKUP(Table17[[#This Row],[Store_ID]],Store_Dim!A:A,Store_Dim!E:E) -> Online | W60: =_xlfn.XLOOKUP(Table17[[#This Row],[Product_ID]],Product_Dim!A:A,Product_Dim!B:B) -> 4K Home Projector | X60: =_xlfn.XLOOKUP(Table17[[#This Row],[Product_ID]],Product_Dim!A:A,Product_Dim!C:C) -> Electronics | Y60: =_xlfn.XLOOKUP(Table17[[#This Row],[Product_ID]],Product_Dim!A:A,Product_Dim!D:D) -> Appliances | Z60: =_xlfn.XLOOKUP(Table17[[#This Row],[Product_ID]],Product_Dim!A:A,Product_Dim!E:E) -> Thomas LLC | AA60: =_xlfn.XLOOKUP(Table17[[#This Row],[Product_ID]],Product_Dim!A:A,Product_Dim!F:F) -> 465.34 | AB60: =_xlfn.XLOOKUP(Table17[[#This Row],[Product_ID]],Product_Dim!A:A,Product_Dim!G:G) -> 301
A61: SALE59 | B61: 45257 | C61: CUST1367 | D61: PROD89 | E61: STORE11 | F61: 1 | G61: 996.33 | H61: 0.23 | I61: PayPal | J61: 767.1741 | K61: =_xlfn.XLOOKUP(Table17[[#This Row],[Customer_ID]],Customer_Dim!A:A,Customer_Dim!B:B,"False Data") -> Melinda Johnson | L61: =_xlfn.XLOOKUP(Table17[[#This Row],[Customer_ID]],Customer_Dim!A:A,Customer_Dim!C:C,"False Data") -> 51 | M61: {=_xlfn.IFS(Table9[[#This Row],[Age]]<=35,"Youth",Table9[[#This Row],[Age]]<=55,"Adult",Table9[[#This Row],[Age]]>55,"Senior")} -> Adult | N61: =_xlfn.XLOOKUP(Table17[[#This Row],[Customer_ID]],Customer_Dim!A:A,Customer_Dim!D:D,"False Data") -> Male | O61: =_xlfn.XLOOKUP(Table17[[#This Row],[Customer_ID]],Customer_Dim!A:A,Customer_Dim!E:E,"False Data") -> Kaufmanfurt | P61: =_xlfn.XLOOKUP(Table17[[#This Row],[Customer_ID]],Customer_Dim!A:A,Customer_Dim!F:F,"False Data") -> Ohio | Q61: =_xlfn.XLOOKUP(Table17[[#This Row],[Customer_ID]],Customer_Dim!A:A,Customer_Dim!G:G,"False Data") -> USA | R61: =_xlfn.XLOOKUP(Table17[[#This Row],[Customer_ID]],Customer_Dim!A:A,Customer_Dim!H:H,"False Data") -> Bronze | S61: =_xlfn.XLOOKUP(Table17[[#This Row],[Store_ID]],Store_Dim!A:A,Store_Dim!B:B) -> Aguirre-Keller | T61: =_xlfn.XLOOKUP(Table17[[#This Row],[Store_ID]],Store_Dim!A:A,Store_Dim!C:C) -> South | U61: =_xlfn.XLOOKUP(Table17[[#This Row],[Store_ID]],Store_Dim!A:A,Store_Dim!D:D) -> Lake Michael | V61: =_xlfn.XLOOKUP(Table17[[#This Row],[Store_ID]],Store_Dim!A:A,Store_Dim!E:E) -> Online | W61: =_xlfn.XLOOKUP(Table17[[#This Row],[Product_ID]],Product_Dim!A:A,Product_Dim!B:B) -> Face Foundation Kit | X61: =_xlfn.XLOOKUP(Table17[[#This Row],[Product_ID]],Product_Dim!A:A,Product_Dim!C:C) -> Beauty | Y61: =_xlfn.XLOOKUP(Table17[[#This Row],[Product_ID]],Product_Dim!A:A,Product_Dim!D:D) -> Makeup | Z61: =_xlfn.XLOOKUP(Table17[[#This Row],[Product_ID]],Product_Dim!A:A,Product_Dim!E:E) -> Taylor-Elliott | AA61: =_xlfn.XLOOKUP(Table17[[#This Row],[Product_ID]],Product_Dim!A:A,Product_Dim!F:F) -> 183.04 | AB61: =_xlfn.XLOOKUP(Table17[[#This Row],[Product_ID]],Product_Dim!A:A,Product_Dim!G:G) -> 457
A62: SALE60 | B62: 45854 | C62: CUST1408 | D62: PROD31 | E62: STORE10 | F62: 1 | G62: 198.83 | H62: 0.09 | I62: COD | J62: 180.9353 | K62: =_xlfn.XLOOKUP(Table17[[#This Row],[Customer_ID]],Customer_Dim!A:A,Customer_Dim!B:B,"False Data") -> Isabel Foster | L62: =_xlfn.XLOOKUP(Table17[[#This Row],[Customer_ID]],Customer_Dim!A:A,Customer_Dim!C:C,"False Data") -> 36 | M62: {=_xlfn.IFS(Table9[[#This Row],[Age]]<=35,"Youth",Table9[[#This Row],[Age]]<=55,"Adult",Table9[[#This Row],[Age]]>55,"Senior")} -> Adult | N62: =_xlfn.XLOOKUP(Table17[[#This Row],[Customer_ID]],Customer_Dim!A:A,Customer_Dim!D:D,"False Data") -> Male | O62: =_xlfn.XLOOKUP(Table17[[#This Row],[Customer_ID]],Customer_Dim!A:A,Customer_Dim!E:E,"False Data") -> Port Joshuaville | P62: =_xlfn.XLOOKUP(Table17[[#This Row],[Customer_ID]],Customer_Dim!A:A,Customer_Dim!F:F,"False Data") -> New Jersey | Q62: =_xlfn.XLOOKUP(Table17[[#This Row],[Customer_ID]],Customer_Dim!A:A,Customer_Dim!G:G,"False Data") -> USA | R62: =_xlfn.XLOOKUP(Table17[[#This Row],[Customer_ID]],Customer_Dim!A:A,Customer_Dim!H:H,"False Data") -> Gold | S62: =_xlfn.XLOOKUP(Table17[[#This Row],[Store_ID]],Store_Dim!A:A,Store_Dim!B:B) -> Hill, Wagner and Ballard | T62: =_xlfn.XLOOKUP(Table17[[#This Row],[Store_ID]],Store_Dim!A:A,Store_Dim!C:C) -> East | U62: =_xlfn.XLOOKUP(Table17[[#This Row],[Store_ID]],Store_Dim!A:A,Store_Dim!D:D) -> East Davidville | V62: =_xlfn.XLOOKUP(Table17[[#This Row],[Store_ID]],Store_Dim!A:A,Store_Dim!E:E) -> Online | W62: =_xlfn.XLOOKUP(Table17[[#This Row],[Product_ID]],Product_Dim!A:A,Product_Dim!B:B) -> Basketball | X62: =_xlfn.XLOOKUP(Table17[[#This Row],[Product_ID]],Product_Dim!A:A,Product_Dim!C:C) -> Sports | Y62: =_xlfn.XLOOKUP(Table17[[#This Row],[Product_ID]],Product_Dim!A:A,Product_Dim!D:D) -> Team Sports | Z62: =_xlfn.XLOOKUP(Table17[[#This Row],[Product_ID]],Product_Dim!A:A,Product_Dim!E:E) -> Nolan-Snow | AA62: =_xlfn.XLOOKUP(Table17[[#This Row],[Product_ID]],Product_Dim!A:A,Product_Dim!F:F) -> 204.39 | AB62: =_xlfn.XLOOKUP(Table17[[#This Row],[Product_ID]],Product_Dim!A:A,Product_Dim!G:G) -> 281
A63: SALE61 | B63: 45716 | C63: CUST1239 | D63: PROD19 | E63: STORE7 | F63: 1 | G63: 374.92 | H63: 0.18 | I63: PayPal | J63: 307.4344 | K63: =_xlfn.XLOOKUP(Table17[[#This Row],[Customer_ID]],Customer_Dim!A:A,Customer_Dim!B:B,"False Data") -> Maria Hill | L63: =_xlfn.XLOOKUP(Table17[[#This Row],[Customer_ID]],Customer_Dim!A:A,Customer_Dim!C:C,"False Data") -> 58 | M63: {=_xlfn.IFS(Table9[[#This Row],[Age]]<=35,"Youth",Table9[[#This Row],[Age]]<=55,"Adult",Table9[[#This Row],[Age]]>55,"Senior")} -> Senior | N63: =_xlfn.XLOOKUP(Table17[[#This Row],[Customer_ID]],Customer_Dim!A:A,Customer_Dim!D:D,"False Data") -> Female | O63: =_xlfn.XLOOKUP(Table17[[#This Row],[Customer_ID]],Customer_Dim!A:A,Customer_Dim!E:E,"False Data") -> Zamoraborough | P63: =_xlfn.XLOOKUP(Table17[[#This Row],[Customer_ID]],Customer_Dim!A:A,Customer_Dim!F:F,"False Data") -> Nevada | Q63: =_xlfn.XLOOKUP(Table17[[#This Row],[Customer_ID]],Customer_Dim!A:A,Customer_Dim!G:G,"False Data") -> USA | R63: =_xlfn.XLOOKUP(Table17[[#This Row],[Customer_ID]],Customer_Dim!A:A,Customer_Dim!H:H,"False Data") -> Platinum | S63: =_xlfn.XLOOKUP(Table17[[#This Row],[Store_ID]],Store_Dim!A:A,Store_Dim!B:B) -> Martinez-Mullins | T63: =_xlfn.XLOOKUP(Table17[[#This Row],[Store_ID]],Store_Dim!A:A,Store_Dim!C:C) -> South | U63: =_xlfn.XLOOKUP(Table17[[#This Row],[Store_ID]],Store_Dim!A:A,Store_Dim!D:D) -> Williamsfurt | V63: =_xlfn.XLOOKUP(Table17[[#This Row],[Store_ID]],Store_Dim!A:A,Store_Dim!E:E) -> Online | W63: =_xlfn.XLOOKUP(Table17[[#This Row],[Product_ID]],Product_Dim!A:A,Product_Dim!B:B) -> Knee Support Brace | X63: =_xlfn.XLOOKUP(Table17[[#This Row],[Product_ID]],Product_Dim!A:A,Product_Dim!C:C) -> Sports | Y63: =_xlfn.XLOOKUP(Table17[[#This Row],[Product_ID]],Product_Dim!A:A,Product_Dim!D:D) -> Equipment | Z63: =_xlfn.XLOOKUP(Table17[[#This Row],[Product_ID]],Product_Dim!A:A,Product_Dim!E:E) -> May-Reese | AA63: =_xlfn.XLOOKUP(Table17[[#This Row],[Product_ID]],Product_Dim!A:A,Product_Dim!F:F) -> 21.34 | AB63: =_xlfn.XLOOKUP(Table17[[#This Row],[Product_ID]],Product_Dim!A:A,Product_Dim!G:G) -> 65
A64: SALE62 | B64: 45515 | C64: CUST1464 | D64: PROD93 | E64: STORE16 | F64: 1 | G64: 468.94 | H64: 0.12 | I64: Credit Card | J64: 412.6672 | K64: =_xlfn.XLOOKUP(Table17[[#This Row],[Customer_ID]],Customer_Dim!A:A,Customer_Dim!B:B,"False Data") -> David Pierce | L64: =_xlfn.XLOOKUP(Table17[[#This Row],[Customer_ID]],Customer_Dim!A:A,Customer_Dim!C:C,"False Data") -> 45 | M64: {=_xlfn.IFS(Table9[[#This Row],[Age]]<=35,"Youth",Table9[[#This Row],[Age]]<=55,"Adult",Table9[[#This Row],[Age]]>55,"Senior")} -> Adult | N64: =_xlfn.XLOOKUP(Table17[[#This Row],[Customer_ID]],Customer_Dim!A:A,Customer_Dim!D:D,"False Data") -> Female | O64: =_xlfn.XLOOKUP(Table17[[#This Row],[Customer_ID]],Customer_Dim!A:A,Customer_Dim!E:E,"False Data") -> Grayland | P64: =_xlfn.XLOOKUP(Table17[[#This Row],[Customer_ID]],Customer_Dim!A:A,Customer_Dim!F:F,"False Data") -> Washington | Q64: =_xlfn.XLOOKUP(Table17[[#This Row],[Customer_ID]],Customer_Dim!A:A,Customer_Dim!G:G,"False Data") -> USA | R64: =_xlfn.XLOOKUP(Table17[[#This Row],[Customer_ID]],Customer_Dim!A:A,Customer_Dim!H:H,"False Data") -> Platinum | S64: =_xlfn.XLOOKUP(Table17[[#This Row],[Store_ID]],Store_Dim!A:A,Store_Dim!B:B) -> Frederick-Wright | T64: =_xlfn.XLOOKUP(Table17[[#This Row],[Store_ID]],Store_Dim!A:A,Store_Dim!C:C) -> West | U64: =_xlfn.XLOOKUP(Table17[[#This Row],[Store_ID]],Store_Dim!A:A,Store_Dim!D:D) -> New Jimmymouth | V64: =_xlfn.XLOOKUP(Table17[[#This Row],[Store_ID]],Store_Dim!A:A,Store_Dim!E:E) -> Flagship | W64: =_xlfn.XLOOKUP(Table17[[#This Row],[Product_ID]],Product_Dim!A:A,Product_Dim!B:B) -> USB-C Laptop Charger | X64: =_xlfn.XLOOKUP(Table17[[#This Row],[Product_ID]],Product_Dim!A:A,Product_Dim!C:C) -> Electronics | Y64: =_xlfn.XLOOKUP(Table17[[#This Row],[Product_ID]],Product_Dim!A:A,Product_Dim!D:D) -> Computer | Z64: =_xlfn.XLOOKUP(Table17[[#This Row],[Product_ID]],Product_Dim!A:A,Product_Dim!E:E) -> Martin LLC | AA64: =_xlfn.XLOOKUP(Table17[[#This Row],[Product_ID]],Product_Dim!A:A,Product_Dim!F:F) -> 377.52 | AB64: =_xlfn.XLOOKUP(Table17[[#This Row],[Product_ID]],Product_Dim!A:A,Product_Dim!G:G) -> 485
A65: SALE63 | B65: 45927 | C65: CUST1126 | D65: PROD89 | E65: STORE12 | F65: 2 | G65: 121.37 | H65: 0.05 | I65: Credit Card | J65: 230.603 | K65: =_xlfn.XLOOKUP(Table17[[#This Row],[Customer_ID]],Customer_Dim!A:A,Customer_Dim!B:B,"False Data") -> James Wolfe | L65: =_xlfn.XLOOKUP(Table17[[#This Row],[Customer_ID]],Customer_Dim!A:A,Customer_Dim!C:C,"False Data") -> 62 | M65: {=_xlfn.IFS(Table9[[#This Row],[Age]]<=35,"Youth",Table9[[#This Row],[Age]]<=55,"Adult",Table9[[#This Row],[Age]]>55,"Senior")} -> Senior | N65: =_xlfn.XLOOKUP(Table17[[#This Row],[Customer_ID]],Customer_Dim!A:A,Customer_Dim!D:D,"False Data") -> Female | O65: =_xlfn.XLOOKUP(Table17[[#This Row],[Customer_ID]],Customer_Dim!A:A,Customer_Dim!E:E,"False Data") -> Benjaminton | P65: =_xlfn.XLOOKUP(Table17[[#This Row],[Customer_ID]],Customer_Dim!A:A,Customer_Dim!F:F,"False Data") -> Arizona | Q65: =_xlfn.XLOOKUP(Table17[[#This Row],[Customer_ID]],Customer_Dim!A:A,Customer_Dim!G:G,"False Data") -> USA | R65: =_xlfn.XLOOKUP(Table17[[#This Row],[Customer_ID]],Customer_Dim!A:A,Customer_Dim!H:H,"False Data") -> Gold | S65: =_xlfn.XLOOKUP(Table17[[#This Row],[Store_ID]],Store_Dim!A:A,Store_Dim!B:B) -> Thomas, Bridges and Harris | T65: =_xlfn.XLOOKUP(Table17[[#This Row],[Store_ID]],Store_Dim!A:A,Store_Dim!C:C) -> North | U65: =_xlfn.XLOOKUP(Table17[[#This Row],[Store_ID]],Store_Dim!A:A,Store_Dim!D:D) -> Sabrinatown | V65: =_xlfn.XLOOKUP(Table17[[#This Row],[Store_ID]],Store_Dim!A:A,Store_Dim!E:E) -> Online | W65: =_xlfn.XLOOKUP(Table17[[#This Row],[Product_ID]],Product_Dim!A:A,Product_Dim!B:B) -> Face Foundation Kit | X65: =_xlfn.XLOOKUP(Table17[[#This Row],[Product_ID]],Product_Dim!A:A,Product_Dim!C:C) -> Beauty | Y65: =_xlfn.XLOOKUP(Table17[[#This Row],[Product_ID]],Product_Dim!A:A,Product_Dim!D:D) -> Makeup | Z65: =_xlfn.XLOOKUP(Table17[[#This Row],[Product_ID]],Product_Dim!A:A,Product_Dim!E:E) -> Taylor-Elliott | AA65: =_xlfn.XLOOKUP(Table17[[#This Row],[Product_ID]],Product_Dim!A:A,Product_Dim!F:F) -> 183.04 | AB65: =_xlfn.XLOOKUP(Table17[[#This Row],[Product_ID]],Product_Dim!A:A,Product_Dim!G:G) -> 457
A66: SALE64 | B66: 45914 | C66: CUST1255 | D66: PROD53 | E66: STORE10 | F66: 3 | G66: 480.06 | H66: 0.01 | I66: Credit Card | J66: =(Table17[[#This Row],[Unit_Price]]*Table17[[#This Row],[Quantity]])*(1-Table17[[#This Row],[Discount]]) -> 1425.7782 | K66: =_xlfn.XLOOKUP(Table17[[#This Row],[Customer_ID]],Customer_Dim!A:A,Customer_Dim!B:B,"False Data") -> Damon Perez | L66: =_xlfn.XLOOKUP(Table17[[#This Row],[Customer_ID]],Customer_Dim!A:A,Customer_Dim!C:C,"False Data") -> 21 | M66: {=_xlfn.IFS(Table9[[#This Row],[Age]]<=35,"Youth",Table9[[#This Row],[Age]]<=55,"Adult",Table9[[#This Row],[Age]]>55,"Senior")} -> Youth | N66: =_xlfn.XLOOKUP(Table17[[#This Row],[Customer_ID]],Customer_Dim!A:A,Customer_Dim!D:D,"False Data") -> Male | O66: =_xlfn.XLOOKUP(Table17[[#This Row],[Customer_ID]],Customer_Dim!A:A,Customer_Dim!E:E,"False Data") -> Jasonton | P66: =_xlfn.XLOOKUP(Table17[[#This Row],[Customer_ID]],Customer_Dim!A:A,Customer_Dim!F:F,"False Data") -> Ohio | Q66: =_xlfn.XLOOKUP(Table17[[#This Row],[Customer_ID]],Customer_Dim!A:A,Customer_Dim!G:G,"False Data") -> USA | R66: =_xlfn.XLOOKUP(Table17[[#This Row],[Customer_ID]],Customer_Dim!A:A,Customer_Dim!H:H,"False Data") -> Gold | S66: =_xlfn.XLOOKUP(Table17[[#This Row],[Store_ID]],Store_Dim!A:A,Store_Dim!B:B) -> Hill, Wagner and Ballard | T66: =_xlfn.XLOOKUP(Table17[[#This Row],[Store_ID]],Store_Dim!A:A,Store_Dim!C:C) -> East | U66: =_xlfn.XLOOKUP(Table17[[#This Row],[Store_ID]],Store_Dim!A:A,Store_Dim!D:D) -> East Davidville | V66: =_xlfn.XLOOKUP(Table17[[#This Row],[Store_ID]],Store_Dim!A:A,Store_Dim!E:E) -> Online | W66: =_xlfn.XLOOKUP(Table17[[#This Row],[Product_ID]],Product_Dim!A:A,Product_Dim!B:B) -> Men's Track Pants | X66: =_xlfn.XLOOKUP(Table17[[#This Row],[Product_ID]],Product_Dim!A:A,Product_Dim!C:C) -> Clothing | Y66: =_xlfn.XLOOKUP(Table17[[#This Row],[Product_ID]],Product_Dim!A:A,Product_Dim!D:D) -> Bottoms | Z66: =_xlfn.XLOOKUP(Table17[[#This Row],[Product_ID]],Product_Dim!A:A,Product_Dim!E:E) -> Hamilton, Woods and Walker | AA66: =_xlfn.XLOOKUP(Table17[[#This Row],[Product_ID]],Product_Dim!A:A,Product_Dim!F:F) -> 386.56 | AB66: =_xlfn.XLOOKUP(Table17[[#This Row],[Product_ID]],Product_Dim!A:A,Product_Dim!G:G) -> 125
A67: SALE65 | B67: 45290 | C67: CUST1162 | D67: PROD99 | E67: STORE17 | F67: 2 | G67: 856.57 | H67: 0.24 | I67: Credit Card | J67: 1301.9864 | K67: =_xlfn.XLOOKUP(Table17[[#This Row],[Customer_ID]],Customer_Dim!A:A,Customer_Dim!B:B,"False Data") -> Mariah Brown | L67: =_xlfn.XLOOKUP(Table17[[#This Row],[Customer_ID]],Customer_Dim!A:A,Customer_Dim!C:C,"False Data") -> 37 | M67: {=_xlfn.IFS(Table9[[#This Row],[Age]]<=35,"Youth",Table9[[#This Row],[Age]]<=55,"Adult",Table9[[#This Row],[Age]]>55,"Senior")} -> Adult | N67: =_xlfn.XLOOKUP(Table17[[#This Row],[Customer_ID]],Customer_Dim!A:A,Customer_Dim!D:D,"False Data") -> Male | O67: =_xlfn.XLOOKUP(Table17[[#This Row],[Customer_ID]],Customer_Dim!A:A,Customer_Dim!E:E,"False Data") -> Palmerbury | P67: =_xlfn.XLOOKUP(Table17[[#This Row],[Customer_ID]],Customer_Dim!A:A,Customer_Dim!F:F,"False Data") -> Tennessee | Q67: =_xlfn.XLOOKUP(Table17[[#This Row],[Customer_ID]],Customer_Dim!A:A,Customer_Dim!G:G,"False Data") -> United States of America | R67: =_xlfn.XLOOKUP(Table17[[#This Row],[Customer_ID]],Customer_Dim!A:A,Customer_Dim!H:H,"False Data") -> Silver | S67: =_xlfn.XLOOKUP(Table17[[#This Row],[Store_ID]],Store_Dim!A:A,Store_Dim!B:B) -> Holloway Ltd | T67: =_xlfn.XLOOKUP(Table17[[#This Row],[Store_ID]],Store_Dim!A:A,Store_Dim!C:C) -> North | U67: =_xlfn.XLOOKUP(Table17[[#This Row],[Store_ID]],Store_Dim!A:A,Store_Dim!D:D) -> Bensonhaven | V67: =_xlfn.XLOOKUP(Table17[[#This Row],[Store_ID]],Store_Dim!A:A,Store_Dim!E:E) -> Flagship | W67: =_xlfn.XLOOKUP(Table17[[#This Row],[Product_ID]],Product_Dim!A:A,Product_Dim!B:B) -> Stainless Steel Cookware Set | X67: =_xlfn.XLOOKUP(Table17[[#This Row],[Product_ID]],Product_Dim!A:A,Product_Dim!C:C) -> Home | Y67: =_xlfn.XLOOKUP(Table17[[#This Row],[Product_ID]],Product_Dim!A:A,Product_Dim!D:D) -> Kitchen | Z67: =_xlfn.XLOOKUP(Table17[[#This Row],[Product_ID]],Product_Dim!A:A,Product_Dim!E:E) -> Campbell Ltd | AA67: =_xlfn.XLOOKUP(Table17[[#This Row],[Product_ID]],Product_Dim!A:A,Product_Dim!F:F) -> 201.41 | AB67: =_xlfn.XLOOKUP(Table17[[#This Row],[Product_ID]],Product_Dim!A:A,Product_Dim!G:G) -> 146
A68: SALE66 | B68: 45213 | C68: CUST1269 | D68: PROD77 | E68: STORE2 | F68: 4 | G68: 814.25 | H68: 0.18 | I68: Credit Card | J68: 2670.74 | K68: =_xlfn.XLOOKUP(Table17[[#This Row],[Customer_ID]],Customer_Dim!A:A,Customer_Dim!B:B,"False Data") -> Tyrone Olson | L68: =_xlfn.XLOOKUP(Table17[[#This Row],[Customer_ID]],Customer_Dim!A:A,Customer_Dim!C:C,"False Data") -> 45 | M68: {=_xlfn.IFS(Table9[[#This Row],[Age]]<=35,"Youth",Table9[[#This Row],[Age]]<=55,"Adult",Table9[[#This Row],[Age]]>55,"Senior")} -> Adult | N68: =_xlfn.XLOOKUP(Table17[[#This Row],[Customer_ID]],Customer_Dim!A:A,Customer_Dim!D:D,"False Data") -> Female | O68: =_xlfn.XLOOKUP(Table17[[#This Row],[Customer_ID]],Customer_Dim!A:A,Customer_Dim!E:E,"False Data") -> Emilytown | P68: =_xlfn.XLOOKUP(Table17[[#This Row],[Customer_ID]],Customer_Dim!A:A,Customer_Dim!F:F,"False Data") -> California | Q68: =_xlfn.XLOOKUP(Table17[[#This Row],[Customer_ID]],Customer_Dim!A:A,Customer_Dim!G:G,"False Data") -> USA | R68: =_xlfn.XLOOKUP(Table17[[#This Row],[Customer_ID]],Customer_Dim!A:A,Customer_Dim!H:H,"False Data") -> Silver | S68: =_xlfn.XLOOKUP(Table17[[#This Row],[Store_ID]],Store_Dim!A:A,Store_Dim!B:B) -> Black-Horn | T68: =_xlfn.XLOOKUP(Table17[[#This Row],[Store_ID]],Store_Dim!A:A,Store_Dim!C:C) -> South | U68: =_xlfn.XLOOKUP(Table17[[#This Row],[Store_ID]],Store_Dim!A:A,Store_Dim!D:D) -> North Nancyview | V68: =_xlfn.XLOOKUP(Table17[[#This Row],[Store_ID]],Store_Dim!A:A,Store_Dim!E:E) -> Outlet | W68: =_xlfn.XLOOKUP(Table17[[#This Row],[Product_ID]],Product_Dim!A:A,Product_Dim!B:B) -> WiFi Mesh Router | X68: =_xlfn.XLOOKUP(Table17[[#This Row],[Product_ID]],Product_Dim!A:A,Product_Dim!C:C) -> Electronics | Y68: =_xlfn.XLOOKUP(Table17[[#This Row],[Product_ID]],Product_Dim!A:A,Product_Dim!D:D) -> Appliances | Z68: =_xlfn.XLOOKUP(Table17[[#This Row],[Product_ID]],Product_Dim!A:A,Product_Dim!E:E) -> White, Reeves and Woods | AA68: =_xlfn.XLOOKUP(Table17[[#This Row],[Product_ID]],Product_Dim!A:A,Product_Dim!F:F) -> 480.9 | AB68: =_xlfn.XLOOKUP(Table17[[#This Row],[Product_ID]],Product_Dim!A:A,Product_Dim!G:G) -> 104
A69: SALE67 | B69: 45255 | C69: CUST1483 | D69: PROD12 | E69: STORE2 | F69: 1 | G69: 989.17 | H69: 0.2 | I69: PayPal | J69: 791.336 | K69: =_xlfn.XLOOKUP(Table17[[#This Row],[Customer_ID]],Customer_Dim!A:A,Customer_Dim!B:B,"False Data") -> Sarah Smith | L69: =_xlfn.XLOOKUP(Table17[[#This Row],[Customer_ID]],Customer_Dim!A:A,Customer_Dim!C:C,"False Data") -> 48 | M69: {=_xlfn.IFS(Table9[[#This Row],[Age]]<=35,"Youth",Table9[[#This Row],[Age]]<=55,"Adult",Table9[[#This Row],[Age]]>55,"Senior")} -> Adult | N69: =_xlfn.XLOOKUP(Table17[[#This Row],[Customer_ID]],Customer_Dim!A:A,Customer_Dim!D:D,"False Data") -> Male | O69: =_xlfn.XLOOKUP(Table17[[#This Row],[Customer_ID]],Customer_Dim!A:A,Customer_Dim!E:E,"False Data") -> East Rodney | P69: =_xlfn.XLOOKUP(Table17[[#This Row],[Customer_ID]],Customer_Dim!A:A,Customer_Dim!F:F,"False Data") -> Nevada | Q69: =_xlfn.XLOOKUP(Table17[[#This Row],[Customer_ID]],Customer_Dim!A:A,Customer_Dim!G:G,"False Data") -> USA | R69: =_xlfn.XLOOKUP(Table17[[#This Row],[Customer_ID]],Customer_Dim!A:A,Customer_Dim!H:H,"False Data") -> Gold | S69: =_xlfn.XLOOKUP(Table17[[#This Row],[Store_ID]],Store_Dim!A:A,Store_Dim!B:B) -> Black-Horn | T69: =_xlfn.XLOOKUP(Table17[[#This Row],[Store_ID]],Store_Dim!A:A,Store_Dim!C:C) -> South | U69: =_xlfn.XLOOKUP(Table17[[#This Row],[Store_ID]],Store_Dim!A:A,Store_Dim!D:D) -> North Nancyview | V69: =_xlfn.XLOOKUP(Table17[[#This Row],[Store_ID]],Store_Dim!A:A,Store_Dim!E:E) -> Outlet | W69: =_xlfn.XLOOKUP(Table17[[#This Row],[Product_ID]],Product_Dim!A:A,Product_Dim!B:B) -> Hair Strengthening Shampoo | X69: =_xlfn.XLOOKUP(Table17[[#This Row],[Product_ID]],Product_Dim!A:A,Product_Dim!C:C) -> Beauty | Y69: =_xlfn.XLOOKUP(Table17[[#This Row],[Product_ID]],Product_Dim!A:A,Product_Dim!D:D) -> Haircare | Z69: =_xlfn.XLOOKUP(Table17[[#This Row],[Product_ID]],Product_Dim!A:A,Product_Dim!E:E) -> Rice LLC | AA69: =_xlfn.XLOOKUP(Table17[[#This Row],[Product_ID]],Product_Dim!A:A,Product_Dim!F:F) -> 115.82 | AB69: =_xlfn.XLOOKUP(Table17[[#This Row],[Product_ID]],Product_Dim!A:A,Product_Dim!G:G) -> 460
A70: SALE68 | B70: 45270 | C70: CUST1372 | D70: PROD72 | E70: STORE10 | F70: 4 | G70: 62.48 | H70: 0.18 | I70: Credit Card | J70: 204.9344 | K70: =_xlfn.XLOOKUP(Table17[[#This Row],[Customer_ID]],Customer_Dim!A:A,Customer_Dim!B:B,"False Data") -> Jacqueline Anthony | L70: =_xlfn.XLOOKUP(Table17[[#This Row],[Customer_ID]],Customer_Dim!A:A,Customer_Dim!C:C,"False Data") -> 28 | M70: {=_xlfn.IFS(Table9[[#This Row],[Age]]<=35,"Youth",Table9[[#This Row],[Age]]<=55,"Adult",Table9[[#This Row],[Age]]>55,"Senior")} -> Youth | N70: =_xlfn.XLOOKUP(Table17[[#This Row],[Customer_ID]],Customer_Dim!A:A,Customer_Dim!D:D,"False Data") -> Male | O70: =_xlfn.XLOOKUP(Table17[[#This Row],[Customer_ID]],Customer_Dim!A:A,Customer_Dim!E:E,"False Data") -> Vincentside | P70: =_xlfn.XLOOKUP(Table17[[#This Row],[Customer_ID]],Customer_Dim!A:A,Customer_Dim!F:F,"False Data") -> Ohio | Q70: =_xlfn.XLOOKUP(Table17[[#This Row],[Customer_ID]],Customer_Dim!A:A,Customer_Dim!G:G,"False Data") -> USA | R70: =_xlfn.XLOOKUP(Table17[[#This Row],[Customer_ID]],Customer_Dim!A:A,Customer_Dim!H:H,"False Data") -> Bronze | S70: =_xlfn.XLOOKUP(Table17[[#This Row],[Store_ID]],Store_Dim!A:A,Store_Dim!B:B) -> Hill, Wagner and Ballard | T70: =_xlfn.XLOOKUP(Table17[[#This Row],[Store_ID]],Store_Dim!A:A,Store_Dim!C:C) -> East | U70: =_xlfn.XLOOKUP(Table17[[#This Row],[Store_ID]],Store_Dim!A:A,Store_Dim!D:D) -> East Davidville | V70: =_xlfn.XLOOKUP(Table17[[#This Row],[Store_ID]],Store_Dim!A:A,Store_Dim!E:E) -> Online | W70: =_xlfn.XLOOKUP(Table17[[#This Row],[Product_ID]],Product_Dim!A:A,Product_Dim!B:B) -> Professional Jump Rope | X70: =_xlfn.XLOOKUP(Table17[[#This Row],[Product_ID]],Product_Dim!A:A,Product_Dim!C:C) -> Sports | Y70: =_xlfn.XLOOKUP(Table17[[#This Row],[Product_ID]],Product_Dim!A:A,Product_Dim!D:D) -> Fitness | Z70: =_xlfn.XLOOKUP(Table17[[#This Row],[Product_ID]],Product_Dim!A:A,Product_Dim!E:E) -> Davis PLC | AA70: =_xlfn.XLOOKUP(Table17[[#This Row],[Product_ID]],Product_Dim!A:A,Product_Dim!F:F) -> 477.61 | AB70: =_xlfn.XLOOKUP(Table17[[#This Row],[Product_ID]],Product_Dim!A:A,Product_Dim!G:G) -> 300
A71: SALE69 | B71: 45897 | C71: CUST1423 | D71: PROD13 | E71: STORE16 | F71: 4 | G71: 561.24 | H71: 0.24 | I71: Credit Card | J71: 1706.1696 | K71: =_xlfn.XLOOKUP(Table17[[#This Row],[Customer_ID]],Customer_Dim!A:A,Customer_Dim!B:B,"False Data") -> Rebecca Baker | L71: =_xlfn.XLOOKUP(Table17[[#This Row],[Customer_ID]],Customer_Dim!A:A,Customer_Dim!C:C,"False Data") -> 35 | M71: {=_xlfn.IFS(Table9[[#This Row],[Age]]<=35,"Youth",Table9[[#This Row],[Age]]<=55,"Adult",Table9[[#This Row],[Age]]>55,"Senior")} -> Youth | N71: =_xlfn.XLOOKUP(Table17[[#This Row],[Customer_ID]],Customer_Dim!A:A,Customer_Dim!D:D,"False Data") -> Male | O71: =_xlfn.XLOOKUP(Table17[[#This Row],[Customer_ID]],Customer_Dim!A:A,Customer_Dim!E:E,"False Data") -> New Katherine | P71: =_xlfn.XLOOKUP(Table17[[#This Row],[Customer_ID]],Customer_Dim!A:A,Customer_Dim!F:F,"False Data") -> Kansas | Q71: =_xlfn.XLOOKUP(Table17[[#This Row],[Customer_ID]],Customer_Dim!A:A,Customer_Dim!G:G,"False Data") -> USA | R71: =_xlfn.XLOOKUP(Table17[[#This Row],[Customer_ID]],Customer_Dim!A:A,Customer_Dim!H:H,"False Data") -> Silver | S71: =_xlfn.XLOOKUP(Table17[[#This Row],[Store_ID]],Store_Dim!A:A,Store_Dim!B:B) -> Frederick-Wright | T71: =_xlfn.XLOOKUP(Table17[[#This Row],[Store_ID]],Store_Dim!A:A,Store_Dim!C:C) -> West | U71: =_xlfn.XLOOKUP(Table17[[#This Row],[Store_ID]],Store_Dim!A:A,Store_Dim!D:D) -> New Jimmymouth | V71: =_xlfn.XLOOKUP(Table17[[#This Row],[Store_ID]],Store_Dim!A:A,Store_Dim!E:E) -> Flagship | W71: =_xlfn.XLOOKUP(Table17[[#This Row],[Product_ID]],Product_Dim!A:A,Product_Dim!B:B) -> USB-C Fast Charger | X71: =_xlfn.XLOOKUP(Table17[[#This Row],[Product_ID]],Product_Dim!A:A,Product_Dim!C:C) -> Electronics | Y71: =_xlfn.XLOOKUP(Table17[[#This Row],[Product_ID]],Product_Dim!A:A,Product_Dim!D:D) -> Accessories | Z71: =_xlfn.XLOOKUP(Table17[[#This Row],[Product_ID]],Product_Dim!A:A,Product_Dim!E:E) -> Dawson-Perkins | AA71: =_xlfn.XLOOKUP(Table17[[#This Row],[Product_ID]],Product_Dim!A:A,Product_Dim!F:F) -> 242.23 | AB71: =_xlfn.XLOOKUP(Table17[[#This Row],[Product_ID]],Product_Dim!A:A,Product_Dim!G:G) -> 453
A72: SALE70 | B72: 45849 | C72: CUST1058 | D72: PROD60 | E72: STORE5 | F72: 3 | G72: 92.24 | H72: 0.28 | I72: COD | J72: =(Table17[[#This Row],[Unit_Price]]*Table17[[#This Row],[Quantity]])*(1-Table17[[#This Row],[Discount]]) -> 199.2384 | K72: =_xlfn.XLOOKUP(Table17[[#This Row],[Customer_ID]],Customer_Dim!A:A,Customer_Dim!B:B,"False Data") -> Cheryl Copeland | L72: =_xlfn.XLOOKUP(Table17[[#This Row],[Customer_ID]],Customer_Dim!A:A,Customer_Dim!C:C,"False Data") -> 51 | M72: {=_xlfn.IFS(Table9[[#This Row],[Age]]<=35,"Youth",Table9[[#This Row],[Age]]<=55,"Adult",Table9[[#This Row],[Age]]>55,"Senior")} -> Adult | N72: =_xlfn.XLOOKUP(Table17[[#This Row],[Customer_ID]],Customer_Dim!A:A,Customer_Dim!D:D,"False Data") -> Male | O72: =_xlfn.XLOOKUP(Table17[[#This Row],[Customer_ID]],Customer_Dim!A:A,Customer_Dim!E:E,"False Data") -> Snowmouth | P72: =_xlfn.XLOOKUP(Table17[[#This Row],[Customer_ID]],Customer_Dim!A:A,Customer_Dim!F:F,"False Data") -> Maryland | Q72: =_xlfn.XLOOKUP(Table17[[#This Row],[Customer_ID]],Customer_Dim!A:A,Customer_Dim!G:G,"False Data") -> USA | R72: =_xlfn.XLOOKUP(Table17[[#This Row],[Customer_ID]],Customer_Dim!A:A,Customer_Dim!H:H,"False Data") -> Platinum | S72: =_xlfn.XLOOKUP(Table17[[#This Row],[Store_ID]],Store_Dim!A:A,Store_Dim!B:B) -> Gray Ltd | T72: =_xlfn.XLOOKUP(Table17[[#This Row],[Store_ID]],Store_Dim!A:A,Store_Dim!C:C) -> North | U72: =_xlfn.XLOOKUP(Table17[[#This Row],[Store_ID]],Store_Dim!A:A,Store_Dim!D:D) -> New Michaelchester | V72: =_xlfn.XLOOKUP(Table17[[#This Row],[Store_ID]],Store_Dim!A:A,Store_Dim!E:E) -> Outlet | W72: =_xlfn.XLOOKUP(Table17[[#This Row],[Product_ID]],Product_Dim!A:A,Product_Dim!B:B) -> Luxury Perfume Spray | X72: =_xlfn.XLOOKUP(Table17[[#This Row],[Product_ID]],Product_Dim!A:A,Product_Dim!C:C) -> Beauty | Y72: =_xlfn.XLOOKUP(Table17[[#This Row],[Product_ID]],Product_Dim!A:A,Product_Dim!D:D) -> Fragrance | Z72: =_xlfn.XLOOKUP(Table17[[#This Row],[Product_ID]],Product_Dim!A:A,Product_Dim!E:E) -> Gibson, Green and Lopez | AA72: =_xlfn.XLOOKUP(Table17[[#This Row],[Product_ID]],Product_Dim!A:A,Product_Dim!F:F) -> 482.75 | AB72: =_xlfn.XLOOKUP(Table17[[#This Row],[Product_ID]],Product_Dim!A:A,Product_Dim!G:G) -> 444
A73: SALE71 | B73: 45889 | C73: CUST1168 | D73: PROD72 | E73: STORE1 | F73: 2 | G73: 668.3 | H73: 0.07 | I73: Credit Card | J73: 1243.038 | K73: =_xlfn.XLOOKUP(Table17[[#This Row],[Customer_ID]],Customer_Dim!A:A,Customer_Dim!B:B,"False Data") -> Daniel Contreras | L73: =_xlfn.XLOOKUP(Table17[[#This Row],[Customer_ID]],Customer_Dim!A:A,Customer_Dim!C:C,"False Data") -> 36 | M73: {=_xlfn.IFS(Table9[[#This Row],[Age]]<=35,"Youth",Table9[[#This Row],[Age]]<=55,"Adult",Table9[[#This Row],[Age]]>55,"Senior")} -> Adult | N73: =_xlfn.XLOOKUP(Table17[[#This Row],[Customer_ID]],Customer_Dim!A:A,Customer_Dim!D:D,"False Data") -> Female | O73: =_xlfn.XLOOKUP(Table17[[#This Row],[Customer_ID]],Customer_Dim!A:A,Customer_Dim!E:E,"False Data") -> Robertview | P73: =_xlfn.XLOOKUP(Table17[[#This Row],[Customer_ID]],Customer_Dim!A:A,Customer_Dim!F:F,"False Data") -> Florida | Q73: =_xlfn.XLOOKUP(Table17[[#This Row],[Customer_ID]],Customer_Dim!A:A,Customer_Dim!G:G,"False Data") -> USA | R73: =_xlfn.XLOOKUP(Table17[[#This Row],[Customer_ID]],Customer_Dim!A:A,Customer_Dim!H:H,"False Data") -> Platinum | S73: =_xlfn.XLOOKUP(Table17[[#This Row],[Store_ID]],Store_Dim!A:A,Store_Dim!B:B) -> Martinez, Adkins and Johnson | T73: =_xlfn.XLOOKUP(Table17[[#This Row],[Store_ID]],Store_Dim!A:A,Store_Dim!C:C) -> North | U73: =_xlfn.XLOOKUP(Table17[[#This Row],[Store_ID]],Store_Dim!A:A,Store_Dim!D:D) -> Danielmouth | V73: =_xlfn.XLOOKUP(Table17[[#This Row],[Store_ID]],Store_Dim!A:A,Store_Dim!E:E) -> Flagship | W73: =_xlfn.XLOOKUP(Table17[[#This Row],[Product_ID]],Product_Dim!A:A,Product_Dim!B:B) -> Professional Jump Rope | X73: =_xlfn.XLOOKUP(Table17[[#This Row],[Product_ID]],Product_Dim!A:A,Product_Dim!C:C) -> Sports | Y73: =_xlfn.XLOOKUP(Table17[[#This Row],[Product_ID]],Product_Dim!A:A,Product_Dim!D:D) -> Fitness | Z73: =_xlfn.XLOOKUP(Table17[[#This Row],[Product_ID]],Product_Dim!A:A,Product_Dim!E:E) -> Davis PLC | AA73: =_xlfn.XLOOKUP(Table17[[#This Row],[Product_ID]],Product_Dim!A:A,Product_Dim!F:F) -> 477.61 | AB73: =_xlfn.XLOOKUP(Table17[[#This Row],[Product_ID]],Product_Dim!A:A,Product_Dim!G:G) -> 300
A74: SALE72 | B74: 45533 | C74: CUST1409 | D74: PROD38 | E74: STORE5 | F74: 1 | G74: 553.82 | H74: 0.09 | I74: Credit Card | J74: 503.9762 | K74: =_xlfn.XLOOKUP(Table17[[#This Row],[Customer_ID]],Customer_Dim!A:A,Customer_Dim!B:B,"False Data") -> Sarah Smith | L74: =_xlfn.XLOOKUP(Table17[[#This Row],[Customer_ID]],Customer_Dim!A:A,Customer_Dim!C:C,"False Data") -> 55 | M74: {=_xlfn.IFS(Table9[[#This Row],[Age]]<=35,"Youth",Table9[[#This Row],[Age]]<=55,"Adult",Table9[[#This Row],[Age]]>55,"Senior")} -> Adult | N74: =_xlfn.XLOOKUP(Table17[[#This Row],[Customer_ID]],Customer_Dim!A:A,Customer_Dim!D:D,"False Data") -> Male | O74: =_xlfn.XLOOKUP(Table17[[#This Row],[Customer_ID]],Customer_Dim!A:A,Customer_Dim!E:E,"False Data") -> Kathleenport | P74: =_xlfn.XLOOKUP(Table17[[#This Row],[Customer_ID]],Customer_Dim!A:A,Customer_Dim!F:F,"False Data") -> Wyoming | Q74: =_xlfn.XLOOKUP(Table17[[#This Row],[Customer_ID]],Customer_Dim!A:A,Customer_Dim!G:G,"False Data") -> USA | R74: =_xlfn.XLOOKUP(Table17[[#This Row],[Customer_ID]],Customer_Dim!A:A,Customer_Dim!H:H,"False Data") -> Gold | S74: =_xlfn.XLOOKUP(Table17[[#This Row],[Store_ID]],Store_Dim!A:A,Store_Dim!B:B) -> Gray Ltd | T74: =_xlfn.XLOOKUP(Table17[[#This Row],[Store_ID]],Store_Dim!A:A,Store_Dim!C:C) -> North | U74: =_xlfn.XLOOKUP(Table17[[#This Row],[Store_ID]],Store_Dim!A:A,Store_Dim!D:D) -> New Michaelchester | V74: =_xlfn.XLOOKUP(Table17[[#This Row],[Store_ID]],Store_Dim!A:A,Store_Dim!E:E) -> Outlet | W74: =_xlfn.XLOOKUP(Table17[[#This Row],[Product_ID]],Product_Dim!A:A,Product_Dim!B:B) -> Sports Water Hydration Pack | X74: =_xlfn.XLOOKUP(Table17[[#This Row],[Product_ID]],Product_Dim!A:A,Product_Dim!C:C) -> Sports | Y74: =_xlfn.XLOOKUP(Table17[[#This Row],[Product_ID]],Product_Dim!A:A,Product_Dim!D:D) -> Outdoor | Z74: =_xlfn.XLOOKUP(Table17[[#This Row],[Product_ID]],Product_Dim!A:A,Product_Dim!E:E) -> Sims-Smith | AA74: =_xlfn.XLOOKUP(Table17[[#This Row],[Product_ID]],Product_Dim!A:A,Product_Dim!F:F) -> 135.61 | AB74: =_xlfn.XLOOKUP(Table17[[#This Row],[Product_ID]],Product_Dim!A:A,Product_Dim!G:G) -> 394
A75: SALE73 | B75: 45626 | C75: CUST1037 | D75: PROD45 | E75: STORE11 | F75: 2 | G75: 556.43 | H75: 0.13 | I75: Credit Card | J75: 968.1882 | K75: =_xlfn.XLOOKUP(Table17[[#This Row],[Customer_ID]],Customer_Dim!A:A,Customer_Dim!B:B,"False Data") -> Christopher Carter | L75: =_xlfn.XLOOKUP(Table17[[#This Row],[Customer_ID]],Customer_Dim!A:A,Customer_Dim!C:C,"False Data") -> 27 | M75: {=_xlfn.IFS(Table9[[#This Row],[Age]]<=35,"Youth",Table9[[#This Row],[Age]]<=55,"Adult",Table9[[#This Row],[Age]]>55,"Senior")} -> Youth | N75: =_xlfn.XLOOKUP(Table17[[#This Row],[Customer_ID]],Customer_Dim!A:A,Customer_Dim!D:D,"False Data") -> Female | O75: =_xlfn.XLOOKUP(Table17[[#This Row],[Customer_ID]],Customer_Dim!A:A,Customer_Dim!E:E,"False Data") -> Brendastad | P75: =_xlfn.XLOOKUP(Table17[[#This Row],[Customer_ID]],Customer_Dim!A:A,Customer_Dim!F:F,"False Data") -> South Dakota | Q75: =_xlfn.XLOOKUP(Table17[[#This Row],[Customer_ID]],Customer_Dim!A:A,Customer_Dim!G:G,"False Data") -> USA | R75: =_xlfn.XLOOKUP(Table17[[#This Row],[Customer_ID]],Customer_Dim!A:A,Customer_Dim!H:H,"False Data") -> Silver | S75: =_xlfn.XLOOKUP(Table17[[#This Row],[Store_ID]],Store_Dim!A:A,Store_Dim!B:B) -> Aguirre-Keller | T75: =_xlfn.XLOOKUP(Table17[[#This Row],[Store_ID]],Store_Dim!A:A,Store_Dim!C:C) -> South | U75: =_xlfn.XLOOKUP(Table17[[#This Row],[Store_ID]],Store_Dim!A:A,Store_Dim!D:D) -> Lake Michael | V75: =_xlfn.XLOOKUP(Table17[[#This Row],[Store_ID]],Store_Dim!A:A,Store_Dim!E:E) -> Online | W75: =_xlfn.XLOOKUP(Table17[[#This Row],[Product_ID]],Product_Dim!A:A,Product_Dim!B:B) -> High-Grip Football | X75: =_xlfn.XLOOKUP(Table17[[#This Row],[Product_ID]],Product_Dim!A:A,Product_Dim!C:C) -> Sports | Y75: =_xlfn.XLOOKUP(Table17[[#This Row],[Product_ID]],Product_Dim!A:A,Product_Dim!D:D) -> Team Sports | Z75: =_xlfn.XLOOKUP(Table17[[#This Row],[Product_ID]],Product_Dim!A:A,Product_Dim!E:E) -> Bridges, Banks and Cummings | AA75: =_xlfn.XLOOKUP(Table17[[#This Row],[Product_ID]],Product_Dim!A:A,Product_Dim!F:F) -> 318.91 | AB75: =_xlfn.XLOOKUP(Table17[[#This Row],[Product_ID]],Product_Dim!A:A,Product_Dim!G:G) -> 114
A76: SALE74 | B76: 45942 | C76: CUST1273 | D76: PROD20 | E76: STORE8 | F76: 1 | G76: 184.98 | H76: 0.1 | I76: COD | J76: 166.482 | K76: =_xlfn.XLOOKUP(Table17[[#This Row],[Customer_ID]],Customer_Dim!A:A,Customer_Dim!B:B,"False Data") -> Samantha Robinson | L76: =_xlfn.XLOOKUP(Table17[[#This Row],[Customer_ID]],Customer_Dim!A:A,Customer_Dim!C:C,"False Data") -> 23 | M76: {=_xlfn.IFS(Table9[[#This Row],[Age]]<=35,"Youth",Table9[[#This Row],[Age]]<=55,"Adult",Table9[[#This Row],[Age]]>55,"Senior")} -> Youth | N76: =_xlfn.XLOOKUP(Table17[[#This Row],[Customer_ID]],Customer_Dim!A:A,Customer_Dim!D:D,"False Data") -> Male | O76: =_xlfn.XLOOKUP(Table17[[#This Row],[Customer_ID]],Customer_Dim!A:A,Customer_Dim!E:E,"False Data") -> North Roy | P76: =_xlfn.XLOOKUP(Table17[[#This Row],[Customer_ID]],Customer_Dim!A:A,Customer_Dim!F:F,"False Data") -> Mississippi | Q76: =_xlfn.XLOOKUP(Table17[[#This Row],[Customer_ID]],Customer_Dim!A:A,Customer_Dim!G:G,"False Data") -> USA | R76: =_xlfn.XLOOKUP(Table17[[#This Row],[Customer_ID]],Customer_Dim!A:A,Customer_Dim!H:H,"False Data") -> Bronze | S76: =_xlfn.XLOOKUP(Table17[[#This Row],[Store_ID]],Store_Dim!A:A,Store_Dim!B:B) -> Bean, Jones and Park | T76: =_xlfn.XLOOKUP(Table17[[#This Row],[Store_ID]],Store_Dim!A:A,Store_Dim!C:C) -> West | U76: =_xlfn.XLOOKUP(Table17[[#This Row],[Store_ID]],Store_Dim!A:A,Store_Dim!D:D) -> Thompsonborough | V76: =_xlfn.XLOOKUP(Table17[[#This Row],[Store_ID]],Store_Dim!A:A,Store_Dim!E:E) -> Online | W76: =_xlfn.XLOOKUP(Table17[[#This Row],[Product_ID]],Product_Dim!A:A,Product_Dim!B:B) -> Outdoor Sports Water Bottle | X76: =_xlfn.XLOOKUP(Table17[[#This Row],[Product_ID]],Product_Dim!A:A,Product_Dim!C:C) -> Sports | Y76: =_xlfn.XLOOKUP(Table17[[#This Row],[Product_ID]],Product_Dim!A:A,Product_Dim!D:D) -> Accessories | Z76: =_xlfn.XLOOKUP(Table17[[#This Row],[Product_ID]],Product_Dim!A:A,Product_Dim!E:E) -> Soto-Ellis | AA76: =_xlfn.XLOOKUP(Table17[[#This Row],[Product_ID]],Product_Dim!A:A,Product_Dim!F:F) -> 131.51 | AB76: =_xlfn.XLOOKUP(Table17[[#This Row],[Product_ID]],Product_Dim!A:A,Product_Dim!G:G) -> 0
A77: SALE75 | B77: 45500 | C77: CUST1035 | D77: PROD97 | E77: STORE12 | F77: 4 | G77: 700.18 | H77: 0.23 | I77: Credit Card | J77: 2156.5544 | K77: =_xlfn.XLOOKUP(Table17[[#This Row],[Customer_ID]],Customer_Dim!A:A,Customer_Dim!B:B,"False Data") -> Rachel Myers | L77: =_xlfn.XLOOKUP(Table17[[#This Row],[Customer_ID]],Customer_Dim!A:A,Customer_Dim!C:C,"False Data") -> 52 | M77: {=_xlfn.IFS(Table9[[#This Row],[Age]]<=35,"Youth",Table9[[#This Row],[Age]]<=55,"Adult",Table9[[#This Row],[Age]]>55,"Senior")} -> Adult | N77: =_xlfn.XLOOKUP(Table17[[#This Row],[Customer_ID]],Customer_Dim!A:A,Customer_Dim!D:D,"False Data") -> Male | O77: =_xlfn.XLOOKUP(Table17[[#This Row],[Customer_ID]],Customer_Dim!A:A,Customer_Dim!E:E,"False Data") -> Robertberg | P77: =_xlfn.XLOOKUP(Table17[[#This Row],[Customer_ID]],Customer_Dim!A:A,Customer_Dim!F:F,"False Data") -> North Dakota | Q77: =_xlfn.XLOOKUP(Table17[[#This Row],[Customer_ID]],Customer_Dim!A:A,Customer_Dim!G:G,"False Data") -> USA | R77: =_xlfn.XLOOKUP(Table17[[#This Row],[Customer_ID]],Customer_Dim!A:A,Customer_Dim!H:H,"False Data") -> Silver | S77: =_xlfn.XLOOKUP(Table17[[#This Row],[Store_ID]],Store_Dim!A:A,Store_Dim!B:B) -> Thomas, Bridges and Harris | T77: =_xlfn.XLOOKUP(Table17[[#This Row],[Store_ID]],Store_Dim!A:A,Store_Dim!C:C) -> North | U77: =_xlfn.XLOOKUP(Table17[[#This Row],[Store_ID]],Store_Dim!A:A,Store_Dim!D:D) -> Sabrinatown | V77: =_xlfn.XLOOKUP(Table17[[#This Row],[Store_ID]],Store_Dim!A:A,Store_Dim!E:E) -> Online | W77: =_xlfn.XLOOKUP(Table17[[#This Row],[Product_ID]],Product_Dim!A:A,Product_Dim!B:B) -> Cricket Bat | X77: =_xlfn.XLOOKUP(Table17[[#This Row],[Product_ID]],Product_Dim!A:A,Product_Dim!C:C) -> Sports | Y77: =_xlfn.XLOOKUP(Table17[[#This Row],[Product_ID]],Product_Dim!A:A,Product_Dim!D:D) -> Team Sports | Z77: =_xlfn.XLOOKUP(Table17[[#This Row],[Product_ID]],Product_Dim!A:A,Product_Dim!E:E) -> Khan LLC | AA77: =_xlfn.XLOOKUP(Table17[[#This Row],[Product_ID]],Product_Dim!A:A,Product_Dim!F:F) -> 245.98 | AB77: =_xlfn.XLOOKUP(Table17[[#This Row],[Product_ID]],Product_Dim!A:A,Product_Dim!G:G) -> 471
A78: SALE76 | B78: 45285 | C78: CUST1019 | D78: PROD76 | E78: STORE10 | F78: 2 | G78: 686.31 | H78: 0.25 | I78: Credit Card | J78: 1029.465 | K78: =_xlfn.XLOOKUP(Table17[[#This Row],[Customer_ID]],Customer_Dim!A:A,Customer_Dim!B:B,"False Data") -> Michael Torres | L78: =_xlfn.XLOOKUP(Table17[[#This Row],[Customer_ID]],Customer_Dim!A:A,Customer_Dim!C:C,"False Data") -> 46 | M78: {=_xlfn.IFS(Table9[[#This Row],[Age]]<=35,"Youth",Table9[[#This Row],[Age]]<=55,"Adult",Table9[[#This Row],[Age]]>55,"Senior")} -> Adult | N78: =_xlfn.XLOOKUP(Table17[[#This Row],[Customer_ID]],Customer_Dim!A:A,Customer_Dim!D:D,"False Data") -> Female | O78: =_xlfn.XLOOKUP(Table17[[#This Row],[Customer_ID]],Customer_Dim!A:A,Customer_Dim!E:E,"False Data") -> Gonzalezfort | P78: =_xlfn.XLOOKUP(Table17[[#This Row],[Customer_ID]],Customer_Dim!A:A,Customer_Dim!F:F,"False Data") -> New Jersey | Q78: =_xlfn.XLOOKUP(Table17[[#This Row],[Customer_ID]],Customer_Dim!A:A,Customer_Dim!G:G,"False Data") -> USA | R78: =_xlfn.XLOOKUP(Table17[[#This Row],[Customer_ID]],Customer_Dim!A:A,Customer_Dim!H:H,"False Data") -> Platinum | S78: =_xlfn.XLOOKUP(Table17[[#This Row],[Store_ID]],Store_Dim!A:A,Store_Dim!B:B) -> Hill, Wagner and Ballard | T78: =_xlfn.XLOOKUP(Table17[[#This Row],[Store_ID]],Store_Dim!A:A,Store_Dim!C:C) -> East | U78: =_xlfn.XLOOKUP(Table17[[#This Row],[Store_ID]],Store_Dim!A:A,Store_Dim!D:D) -> East Davidville | V78: =_xlfn.XLOOKUP(Table17[[#This Row],[Store_ID]],Store_Dim!A:A,Store_Dim!E:E) -> Online | W78: =_xlfn.XLOOKUP(Table17[[#This Row],[Product_ID]],Product_Dim!A:A,Product_Dim!B:B) -> Wireless Mouse | X78: =_xlfn.XLOOKUP(Table17[[#This Row],[Product_ID]],Product_Dim!A:A,Product_Dim!C:C) -> Electronics | Y78: =_xlfn.XLOOKUP(Table17[[#This Row],[Product_ID]],Product_Dim!A:A,Product_Dim!D:D) -> Computer | Z78: =_xlfn.XLOOKUP(Table17[[#This Row],[Product_ID]],Product_Dim!A:A,Product_Dim!E:E) -> Larson Ltd | AA78: =_xlfn.XLOOKUP(Table17[[#This Row],[Product_ID]],Product_Dim!A:A,Product_Dim!F:F) -> 392.89 | AB78: =_xlfn.XLOOKUP(Table17[[#This Row],[Product_ID]],Product_Dim!A:A,Product_Dim!G:G) -> 320
A79: SALE77 | B79: 45800 | C79: CUST1007 | D79: PROD67 | E79: STORE15 | F79: 1 | G79: 687.82 | H79: 0.27 | I79: COD | J79: 502.1086 | K79: =_xlfn.XLOOKUP(Table17[[#This Row],[Customer_ID]],Customer_Dim!A:A,Customer_Dim!B:B,"False Data") -> Daniel Boyd | L79: =_xlfn.XLOOKUP(Table17[[#This Row],[Customer_ID]],Customer_Dim!A:A,Customer_Dim!C:C,"False Data") -> 29 | M79: {=_xlfn.IFS(Table9[[#This Row],[Age]]<=35,"Youth",Table9[[#This Row],[Age]]<=55,"Adult",Table9[[#This Row],[Age]]>55,"Senior")} -> Youth | N79: =_xlfn.XLOOKUP(Table17[[#This Row],[Customer_ID]],Customer_Dim!A:A,Customer_Dim!D:D,"False Data") -> Female | O79: =_xlfn.XLOOKUP(Table17[[#This Row],[Customer_ID]],Customer_Dim!A:A,Customer_Dim!E:E,"False Data") -> West Pamelafurt | P79: =_xlfn.XLOOKUP(Table17[[#This Row],[Customer_ID]],Customer_Dim!A:A,Customer_Dim!F:F,"False Data") -> West Virginia | Q79: =_xlfn.XLOOKUP(Table17[[#This Row],[Customer_ID]],Customer_Dim!A:A,Customer_Dim!G:G,"False Data") -> USA | R79: =_xlfn.XLOOKUP(Table17[[#This Row],[Customer_ID]],Customer_Dim!A:A,Customer_Dim!H:H,"False Data") -> Bronze | S79: =_xlfn.XLOOKUP(Table17[[#This Row],[Store_ID]],Store_Dim!A:A,Store_Dim!B:B) -> Shelton PLC | T79: =_xlfn.XLOOKUP(Table17[[#This Row],[Store_ID]],Store_Dim!A:A,Store_Dim!C:C) -> North | U79: =_xlfn.XLOOKUP(Table17[[#This Row],[Store_ID]],Store_Dim!A:A,Store_Dim!D:D) -> East Jenniferstad | V79: =_xlfn.XLOOKUP(Table17[[#This Row],[Store_ID]],Store_Dim!A:A,Store_Dim!E:E) -> Flagship | W79: =_xlfn.XLOOKUP(Table17[[#This Row],[Product_ID]],Product_Dim!A:A,Product_Dim!B:B) -> Smart LED Light Strip | X79: =_xlfn.XLOOKUP(Table17[[#This Row],[Product_ID]],Product_Dim!A:A,Product_Dim!C:C) -> Electronics | Y79: =_xlfn.XLOOKUP(Table17[[#This Row],[Product_ID]],Product_Dim!A:A,Product_Dim!D:D) -> Accessories | Z79: =_xlfn.XLOOKUP(Table17[[#This Row],[Product_ID]],Product_Dim!A:A,Product_Dim!E:E) -> Flores-Davis | AA79: =_xlfn.XLOOKUP(Table17[[#This Row],[Product_ID]],Product_Dim!A:A,Product_Dim!F:F) -> 349.17 | AB79: =_xlfn.XLOOKUP(Table17[[#This Row],[Product_ID]],Product_Dim!A:A,Product_Dim!G:G) -> 476
A80: SALE78 | B80: 45609 | C80: CUST1221 | D80: PROD83 | E80: STORE8 | F80: 2 | G80: 900.55 | H80: 0.16 | I80: Credit Card | J80: 1512.924 | K80: =_xlfn.XLOOKUP(Table17[[#This Row],[Customer_ID]],Customer_Dim!A:A,Customer_Dim!B:B,"False Data") -> Lisa Young | L80: =_xlfn.XLOOKUP(Table17[[#This Row],[Customer_ID]],Customer_Dim!A:A,Customer_Dim!C:C,"False Data") -> 38 | M80: {=_xlfn.IFS(Table9[[#This Row],[Age]]<=35,"Youth",Table9[[#This Row],[Age]]<=55,"Adult",Table9[[#This Row],[Age]]>55,"Senior")} -> Adult | N80: =_xlfn.XLOOKUP(Table17[[#This Row],[Customer_ID]],Customer_Dim!A:A,Customer_Dim!D:D,"False Data") -> Male | O80: =_xlfn.XLOOKUP(Table17[[#This Row],[Customer_ID]],Customer_Dim!A:A,Customer_Dim!E:E,"False Data") -> Maybury | P80: =_xlfn.XLOOKUP(Table17[[#This Row],[Customer_ID]],Customer_Dim!A:A,Customer_Dim!F:F,"False Data") -> Georgia | Q80: =_xlfn.XLOOKUP(Table17[[#This Row],[Customer_ID]],Customer_Dim!A:A,Customer_Dim!G:G,"False Data") -> USA | R80: =_xlfn.XLOOKUP(Table17[[#This Row],[Customer_ID]],Customer_Dim!A:A,Customer_Dim!H:H,"False Data") -> Platinum | S80: =_xlfn.XLOOKUP(Table17[[#This Row],[Store_ID]],Store_Dim!A:A,Store_Dim!B:B) -> Bean, Jones and Park | T80: =_xlfn.XLOOKUP(Table17[[#This Row],[Store_ID]],Store_Dim!A:A,Store_Dim!C:C) -> West | U80: =_xlfn.XLOOKUP(Table17[[#This Row],[Store_ID]],Store_Dim!A:A,Store_Dim!D:D) -> Thompsonborough | V80: =_xlfn.XLOOKUP(Table17[[#This Row],[Store_ID]],Store_Dim!A:A,Store_Dim!E:E) -> Online | W80: =_xlfn.XLOOKUP(Table17[[#This Row],[Product_ID]],Product_Dim!A:A,Product_Dim!B:B) -> Hydrating Face Cleanser | X80: =_xlfn.XLOOKUP(Table17[[#This Row],[Product_ID]],Product_Dim!A:A,Product_Dim!C:C) -> Beauty | Y80: =_xlfn.XLOOKUP(Table17[[#This Row],[Product_ID]],Product_Dim!A:A,Product_Dim!D:D) -> Skincare | Z80: =_xlfn.XLOOKUP(Table17[[#This Row],[Product_ID]],Product_Dim!A:A,Product_Dim!E:E) -> Butler Group | AA80: =_xlfn.XLOOKUP(Table17[[#This Row],[Product_ID]],Product_Dim!A:A,Product_Dim!F:F) -> 305.49 | AB80: =_xlfn.XLOOKUP(Table17[[#This Row],[Product_ID]],Product_Dim!A:A,Product_Dim!G:G) -> 159
A81: SALE79 | B81: 45268 | C81: CUST1115 | D81: PROD21 | E81: STORE2 | F81: 1 | G81: 341.17 | H81: 0.15 | I81: Credit Card | J81: 289.9945 | K81: =_xlfn.XLOOKUP(Table17[[#This Row],[Customer_ID]],Customer_Dim!A:A,Customer_Dim!B:B,"False Data") -> Tyler Conrad | L81: =_xlfn.XLOOKUP(Table17[[#This Row],[Customer_ID]],Customer_Dim!A:A,Customer_Dim!C:C,"False Data") -> 53 | M81: {=_xlfn.IFS(Table9[[#This Row],[Age]]<=35,"Youth",Table9[[#This Row],[Age]]<=55,"Adult",Table9[[#This Row],[Age]]>55,"Senior")} -> Adult | N81: =_xlfn.XLOOKUP(Table17[[#This Row],[Customer_ID]],Customer_Dim!A:A,Customer_Dim!D:D,"False Data") -> Female | O81: =_xlfn.XLOOKUP(Table17[[#This Row],[Customer_ID]],Customer_Dim!A:A,Customer_Dim!E:E,"False Data") -> North Curtischester | P81: =_xlfn.XLOOKUP(Table17[[#This Row],[Customer_ID]],Customer_Dim!A:A,Customer_Dim!F:F,"False Data") -> North Dakota | Q81: =_xlfn.XLOOKUP(Table17[[#This Row],[Customer_ID]],Customer_Dim!A:A,Customer_Dim!G:G,"False Data") -> USA | R81: =_xlfn.XLOOKUP(Table17[[#This Row],[Customer_ID]],Customer_Dim!A:A,Customer_Dim!H:H,"False Data") -> Platinum | S81: =_xlfn.XLOOKUP(Table17[[#This Row],[Store_ID]],Store_Dim!A:A,Store_Dim!B:B) -> Black-Horn | T81: =_xlfn.XLOOKUP(Table17[[#This Row],[Store_ID]],Store_Dim!A:A,Store_Dim!C:C) -> South | U81: =_xlfn.XLOOKUP(Table17[[#This Row],[Store_ID]],Store_Dim!A:A,Store_Dim!D:D) -> North Nancyview | V81: =_xlfn.XLOOKUP(Table17[[#This Row],[Store_ID]],Store_Dim!A:A,Store_Dim!E:E) -> Outlet | W81: =_xlfn.XLOOKUP(Table17[[#This Row],[Product_ID]],Product_Dim!A:A,Product_Dim!B:B) -> Multi-Purpose Storage Box | X81: =_xlfn.XLOOKUP(Table17[[#This Row],[Product_ID]],Product_Dim!A:A,Product_Dim!C:C) -> Home | Y81: =_xlfn.XLOOKUP(Table17[[#This Row],[Product_ID]],Product_Dim!A:A,Product_Dim!D:D) -> Storage | Z81: =_xlfn.XLOOKUP(Table17[[#This Row],[Product_ID]],Product_Dim!A:A,Product_Dim!E:E) -> Gardner-Montes | AA81: =_xlfn.XLOOKUP(Table17[[#This Row],[Product_ID]],Product_Dim!A:A,Product_Dim!F:F) -> 123.46 | AB81: =_xlfn.XLOOKUP(Table17[[#This Row],[Product_ID]],Product_Dim!A:A,Product_Dim!G:G) -> 76
A82: SALE80 | B82: 45885 | C82: CUST1176 | D82: PROD52 | E82: STORE8 | F82: 1 | G82: 442.27 | H82: 0.06 | I82: COD | J82: 415.7338 | K82: =_xlfn.XLOOKUP(Table17[[#This Row],[Customer_ID]],Customer_Dim!A:A,Customer_Dim!B:B,"False Data") -> John Bradford | L82: =_xlfn.XLOOKUP(Table17[[#This Row],[Customer_ID]],Customer_Dim!A:A,Customer_Dim!C:C,"False Data") -> 48 | M82: {=_xlfn.IFS(Table9[[#This Row],[Age]]<=35,"Youth",Table9[[#This Row],[Age]]<=55,"Adult",Table9[[#This Row],[Age]]>55,"Senior")} -> Adult | N82: =_xlfn.XLOOKUP(Table17[[#This Row],[Customer_ID]],Customer_Dim!A:A,Customer_Dim!D:D,"False Data") -> Male | O82: =_xlfn.XLOOKUP(Table17[[#This Row],[Customer_ID]],Customer_Dim!A:A,Customer_Dim!E:E,"False Data") -> Anabury | P82: =_xlfn.XLOOKUP(Table17[[#This Row],[Customer_ID]],Customer_Dim!A:A,Customer_Dim!F:F,"False Data") -> Vermont | Q82: =_xlfn.XLOOKUP(Table17[[#This Row],[Customer_ID]],Customer_Dim!A:A,Customer_Dim!G:G,"False Data") -> USA | R82: =_xlfn.XLOOKUP(Table17[[#This Row],[Customer_ID]],Customer_Dim!A:A,Customer_Dim!H:H,"False Data") -> Silver | S82: =_xlfn.XLOOKUP(Table17[[#This Row],[Store_ID]],Store_Dim!A:A,Store_Dim!B:B) -> Bean, Jones and Park | T82: =_xlfn.XLOOKUP(Table17[[#This Row],[Store_ID]],Store_Dim!A:A,Store_Dim!C:C) -> West | U82: =_xlfn.XLOOKUP(Table17[[#This Row],[Store_ID]],Store_Dim!A:A,Store_Dim!D:D) -> Thompsonborough | V82: =_xlfn.XLOOKUP(Table17[[#This Row],[Store_ID]],Store_Dim!A:A,Store_Dim!E:E) -> Online | W82: =_xlfn.XLOOKUP(Table17[[#This Row],[Product_ID]],Product_Dim!A:A,Product_Dim!B:B) -> Rugby Ball | X82: =_xlfn.XLOOKUP(Table17[[#This Row],[Product_ID]],Product_Dim!A:A,Product_Dim!C:C) -> Sports | Y82: =_xlfn.XLOOKUP(Table17[[#This Row],[Product_ID]],Product_Dim!A:A,Product_Dim!D:D) -> Team Sports | Z82: =_xlfn.XLOOKUP(Table17[[#This Row],[Product_ID]],Product_Dim!A:A,Product_Dim!E:E) -> Harris Inc | AA82: =_xlfn.XLOOKUP(Table17[[#This Row],[Product_ID]],Product_Dim!A:A,Product_Dim!F:F) -> 212.26 | AB82: =_xlfn.XLOOKUP(Table17[[#This Row],[Product_ID]],Product_Dim!A:A,Product_Dim!G:G) -> 82
A83: SALE81 | B83: 45616 | C83: CUST1253 | D83: PROD71 | E83: STORE9 | F83: 1 | G83: 363.73 | H83: 0.25 | I83: PayPal | J83: 272.7975 | K83: =_xlfn.XLOOKUP(Table17[[#This Row],[Customer_ID]],Customer_Dim!A:A,Customer_Dim!B:B,"False Data") -> Dr. Ashley Yates Md | L83: =_xlfn.XLOOKUP(Table17[[#This Row],[Customer_ID]],Customer_Dim!A:A,Customer_Dim!C:C,"False Data") -> 32 | M83: {=_xlfn.IFS(Table9[[#This Row],[Age]]<=35,"Youth",Table9[[#This Row],[Age]]<=55,"Adult",Table9[[#This Row],[Age]]>55,"Senior")} -> Youth | N83: =_xlfn.XLOOKUP(Table17[[#This Row],[Customer_ID]],Customer_Dim!A:A,Customer_Dim!D:D,"False Data") -> Male | O83: =_xlfn.XLOOKUP(Table17[[#This Row],[Customer_ID]],Customer_Dim!A:A,Customer_Dim!E:E,"False Data") -> New Maria | P83: =_xlfn.XLOOKUP(Table17[[#This Row],[Customer_ID]],Customer_Dim!A:A,Customer_Dim!F:F,"False Data") -> Wisconsin | Q83: =_xlfn.XLOOKUP(Table17[[#This Row],[Customer_ID]],Customer_Dim!A:A,Customer_Dim!G:G,"False Data") -> USA | R83: =_xlfn.XLOOKUP(Table17[[#This Row],[Customer_ID]],Customer_Dim!A:A,Customer_Dim!H:H,"False Data") -> Bronze | S83: =_xlfn.XLOOKUP(Table17[[#This Row],[Store_ID]],Store_Dim!A:A,Store_Dim!B:B) -> Moore, Padilla and Butler | T83: =_xlfn.XLOOKUP(Table17[[#This Row],[Store_ID]],Store_Dim!A:A,Store_Dim!C:C) -> South | U83: =_xlfn.XLOOKUP(Table17[[#This Row],[Store_ID]],Store_Dim!A:A,Store_Dim!D:D) -> East Johnstad | V83: =_xlfn.XLOOKUP(Table17[[#This Row],[Store_ID]],Store_Dim!A:A,Store_Dim!E:E) -> Flagship | W83: =_xlfn.XLOOKUP(Table17[[#This Row],[Product_ID]],Product_Dim!A:A,Product_Dim!B:B) -> Hair Repair Oil Treatment | X83: =_xlfn.XLOOKUP(Table17[[#This Row],[Product_ID]],Product_Dim!A:A,Product_Dim!C:C) -> Beauty | Y83: =_xlfn.XLOOKUP(Table17[[#This Row],[Product_ID]],Product_Dim!A:A,Product_Dim!D:D) -> Haircare | Z83: =_xlfn.XLOOKUP(Table17[[#This Row],[Product_ID]],Product_Dim!A:A,Product_Dim!E:E) -> Hopkins Ltd | AA83: =_xlfn.XLOOKUP(Table17[[#This Row],[Product_ID]],Product_Dim!A:A,Product_Dim!F:F) -> 214.32 | AB83: =_xlfn.XLOOKUP(Table17[[#This Row],[Product_ID]],Product_Dim!A:A,Product_Dim!G:G) -> 383
A84: SALE82 | B84: 45518 | C84: CUST1378 | D84: PROD91 | E84: STORE17 | F84: 2 | G84: 601.33 | H84: 0.16 | I84: PayPal | J84: 1010.2344 | K84: =_xlfn.XLOOKUP(Table17[[#This Row],[Customer_ID]],Customer_Dim!A:A,Customer_Dim!B:B,"False Data") -> Frank Stewart | L84: =_xlfn.XLOOKUP(Table17[[#This Row],[Customer_ID]],Customer_Dim!A:A,Customer_Dim!C:C,"False Data") -> 44 | M84: {=_xlfn.IFS(Table9[[#This Row],[Age]]<=35,"Youth",Table9[[#This Row],[Age]]<=55,"Adult",Table9[[#This Row],[Age]]>55,"Senior")} -> Adult | N84: =_xlfn.XLOOKUP(Table17[[#This Row],[Customer_ID]],Customer_Dim!A:A,Customer_Dim!D:D,"False Data") -> Female | O84: =_xlfn.XLOOKUP(Table17[[#This Row],[Customer_ID]],Customer_Dim!A:A,Customer_Dim!E:E,"False Data") -> Fischerborough | P84: =_xlfn.XLOOKUP(Table17[[#This Row],[Customer_ID]],Customer_Dim!A:A,Customer_Dim!F:F,"False Data") -> Delaware | Q84: =_xlfn.XLOOKUP(Table17[[#This Row],[Customer_ID]],Customer_Dim!A:A,Customer_Dim!G:G,"False Data") -> USA | R84: =_xlfn.XLOOKUP(Table17[[#This Row],[Customer_ID]],Customer_Dim!A:A,Customer_Dim!H:H,"False Data") -> Bronze | S84: =_xlfn.XLOOKUP(Table17[[#This Row],[Store_ID]],Store_Dim!A:A,Store_Dim!B:B) -> Holloway Ltd | T84: =_xlfn.XLOOKUP(Table17[[#This Row],[Store_ID]],Store_Dim!A:A,Store_Dim!C:C) -> North | U84: =_xlfn.XLOOKUP(Table17[[#This Row],[Store_ID]],Store_Dim!A:A,Store_Dim!D:D) -> Bensonhaven | V84: =_xlfn.XLOOKUP(Table17[[#This Row],[Store_ID]],Store_Dim!A:A,Store_Dim!E:E) -> Flagship | W84: =_xlfn.XLOOKUP(Table17[[#This Row],[Product_ID]],Product_Dim!A:A,Product_Dim!B:B) -> Women's High Heels | X84: =_xlfn.XLOOKUP(Table17[[#This Row],[Product_ID]],Product_Dim!A:A,Product_Dim!C:C) -> Clothing | Y84: =_xlfn.XLOOKUP(Table17[[#This Row],[Product_ID]],Product_Dim!A:A,Product_Dim!D:D) -> Footwear | Z84: =_xlfn.XLOOKUP(Table17[[#This Row],[Product_ID]],Product_Dim!A:A,Product_Dim!E:E) -> Smith-Charles | AA84: =_xlfn.XLOOKUP(Table17[[#This Row],[Product_ID]],Product_Dim!A:A,Product_Dim!F:F) -> 438.25 | AB84: =_xlfn.XLOOKUP(Table17[[#This Row],[Product_ID]],Product_Dim!A:A,Product_Dim!G:G) -> 496
A85: SALE83 | B85: 45427 | C85: CUST1403 | D85: PROD17 | E85: STORE18 | F85: 4 | G85: 34.39 | H85: 0.03 | I85: PayPal | J85: 133.4332 | K85: =_xlfn.XLOOKUP(Table17[[#This Row],[Customer_ID]],Customer_Dim!A:A,Customer_Dim!B:B,"False Data") -> Justin Ingram | L85: =_xlfn.XLOOKUP(Table17[[#This Row],[Customer_ID]],Customer_Dim!A:A,Customer_Dim!C:C,"False Data") -> 34 | M85: {=_xlfn.IFS(Table9[[#This Row],[Age]]<=35,"Youth",Table9[[#This Row],[Age]]<=55,"Adult",Table9[[#This Row],[Age]]>55,"Senior")} -> Youth | N85: =_xlfn.XLOOKUP(Table17[[#This Row],[Customer_ID]],Customer_Dim!A:A,Customer_Dim!D:D,"False Data") -> Male | O85: =_xlfn.XLOOKUP(Table17[[#This Row],[Customer_ID]],Customer_Dim!A:A,Customer_Dim!E:E,"False Data") -> Lake Lisaland | P85: =_xlfn.XLOOKUP(Table17[[#This Row],[Customer_ID]],Customer_Dim!A:A,Customer_Dim!F:F,"False Data") -> Louisiana | Q85: =_xlfn.XLOOKUP(Table17[[#This Row],[Customer_ID]],Customer_Dim!A:A,Customer_Dim!G:G,"False Data") -> USA | R85: =_xlfn.XLOOKUP(Table17[[#This Row],[Customer_ID]],Customer_Dim!A:A,Customer_Dim!H:H,"False Data") -> Bronze | S85: =_xlfn.XLOOKUP(Table17[[#This Row],[Store_ID]],Store_Dim!A:A,Store_Dim!B:B) -> Guerrero-Schmitt | T85: =_xlfn.XLOOKUP(Table17[[#This Row],[Store_ID]],Store_Dim!A:A,Store_Dim!C:C) -> East | U85: =_xlfn.XLOOKUP(Table17[[#This Row],[Store_ID]],Store_Dim!A:A,Store_Dim!D:D) -> East Stevechester | V85: =_xlfn.XLOOKUP(Table17[[#This Row],[Store_ID]],Store_Dim!A:A,Store_Dim!E:E) -> Flagship | W85: =_xlfn.XLOOKUP(Table17[[#This Row],[Product_ID]],Product_Dim!A:A,Product_Dim!B:B) -> Soccer Training Cone Set | X85: =_xlfn.XLOOKUP(Table17[[#This Row],[Product_ID]],Product_Dim!A:A,Product_Dim!C:C) -> Sports | Y85: =_xlfn.XLOOKUP(Table17[[#This Row],[Product_ID]],Product_Dim!A:A,Product_Dim!D:D) -> Accessories | Z85: =_xlfn.XLOOKUP(Table17[[#This Row],[Product_ID]],Product_Dim!A:A,Product_Dim!E:E) -> Ford, Murphy and Wilson | AA85: =_xlfn.XLOOKUP(Table17[[#This Row],[Product_ID]],Product_Dim!A:A,Product_Dim!F:F) -> 144.53 | AB85: =_xlfn.XLOOKUP(Table17[[#This Row],[Product_ID]],Product_Dim!A:A,Product_Dim!G:G) -> 367
A86: SALE84 | B86: 45268 | C86: CUST1423 | D86: PROD46 | E86: STORE17 | F86: 1 | G86: 773.57 | H86: 0.05 | I86: COD | J86: =(Table17[[#This Row],[Unit_Price]]*Table17[[#This Row],[Quantity]])*(1-Table17[[#This Row],[Discount]]) -> 734.8915 | K86: =_xlfn.XLOOKUP(Table17[[#This Row],[Customer_ID]],Customer_Dim!A:A,Customer_Dim!B:B,"False Data") -> Rebecca Baker | L86: =_xlfn.XLOOKUP(Table17[[#This Row],[Customer_ID]],Customer_Dim!A:A,Customer_Dim!C:C,"False Data") -> 35 | M86: {=_xlfn.IFS(Table9[[#This Row],[Age]]<=35,"Youth",Table9[[#This Row],[Age]]<=55,"Adult",Table9[[#This Row],[Age]]>55,"Senior")} -> Youth | N86: =_xlfn.XLOOKUP(Table17[[#This Row],[Customer_ID]],Customer_Dim!A:A,Customer_Dim!D:D,"False Data") -> Male | O86: =_xlfn.XLOOKUP(Table17[[#This Row],[Customer_ID]],Customer_Dim!A:A,Customer_Dim!E:E,"False Data") -> New Katherine | P86: =_xlfn.XLOOKUP(Table17[[#This Row],[Customer_ID]],Customer_Dim!A:A,Customer_Dim!F:F,"False Data") -> Kansas | Q86: =_xlfn.XLOOKUP(Table17[[#This Row],[Customer_ID]],Customer_Dim!A:A,Customer_Dim!G:G,"False Data") -> USA | R86: =_xlfn.XLOOKUP(Table17[[#This Row],[Customer_ID]],Customer_Dim!A:A,Customer_Dim!H:H,"False Data") -> Silver | S86: =_xlfn.XLOOKUP(Table17[[#This Row],[Store_ID]],Store_Dim!A:A,Store_Dim!B:B) -> Holloway Ltd | T86: =_xlfn.XLOOKUP(Table17[[#This Row],[Store_ID]],Store_Dim!A:A,Store_Dim!C:C) -> North | U86: =_xlfn.XLOOKUP(Table17[[#This Row],[Store_ID]],Store_Dim!A:A,Store_Dim!D:D) -> Bensonhaven | V86: =_xlfn.XLOOKUP(Table17[[#This Row],[Store_ID]],Store_Dim!A:A,Store_Dim!E:E) -> Flagship | W86: =_xlfn.XLOOKUP(Table17[[#This Row],[Product_ID]],Product_Dim!A:A,Product_Dim!B:B) -> Men's Winter Jacket | X86: =_xlfn.XLOOKUP(Table17[[#This Row],[Product_ID]],Product_Dim!A:A,Product_Dim!C:C) -> Clothing | Y86: =_xlfn.XLOOKUP(Table17[[#This Row],[Product_ID]],Product_Dim!A:A,Product_Dim!D:D) -> Outerwear | Z86: =_xlfn.XLOOKUP(Table17[[#This Row],[Product_ID]],Product_Dim!A:A,Product_Dim!E:E) -> Kelly, Smith and Perez | AA86: =_xlfn.XLOOKUP(Table17[[#This Row],[Product_ID]],Product_Dim!A:A,Product_Dim!F:F) -> 167.34 | AB86: =_xlfn.XLOOKUP(Table17[[#This Row],[Product_ID]],Product_Dim!A:A,Product_Dim!G:G) -> 296
A87: SALE85 | B87: 45282 | C87: CUST1054 | D87: PROD88 | E87: STORE7 | F87: 4 | G87: 127.1 | H87: 0.24 | I87: COD | J87: 386.384 | K87: =_xlfn.XLOOKUP(Table17[[#This Row],[Customer_ID]],Customer_Dim!A:A,Customer_Dim!B:B,"False Data") -> Katherine Dorsey | L87: =_xlfn.XLOOKUP(Table17[[#This Row],[Customer_ID]],Customer_Dim!A:A,Customer_Dim!C:C,"False Data") -> 24 | M87: {=_xlfn.IFS(Table9[[#This Row],[Age]]<=35,"Youth",Table9[[#This Row],[Age]]<=55,"Adult",Table9[[#This Row],[Age]]>55,"Senior")} -> Youth | N87: =_xlfn.XLOOKUP(Table17[[#This Row],[Customer_ID]],Customer_Dim!A:A,Customer_Dim!D:D,"False Data") -> Male | O87: =_xlfn.XLOOKUP(Table17[[#This Row],[Customer_ID]],Customer_Dim!A:A,Customer_Dim!E:E,"False Data") -> Christopherland | P87: =_xlfn.XLOOKUP(Table17[[#This Row],[Customer_ID]],Customer_Dim!A:A,Customer_Dim!F:F,"False Data") -> Oklahoma | Q87: =_xlfn.XLOOKUP(Table17[[#This Row],[Customer_ID]],Customer_Dim!A:A,Customer_Dim!G:G,"False Data") -> USA | R87: =_xlfn.XLOOKUP(Table17[[#This Row],[Customer_ID]],Customer_Dim!A:A,Customer_Dim!H:H,"False Data") -> Platinum | S87: =_xlfn.XLOOKUP(Table17[[#This Row],[Store_ID]],Store_Dim!A:A,Store_Dim!B:B) -> Martinez-Mullins | T87: =_xlfn.XLOOKUP(Table17[[#This Row],[Store_ID]],Store_Dim!A:A,Store_Dim!C:C) -> South | U87: =_xlfn.XLOOKUP(Table17[[#This Row],[Store_ID]],Store_Dim!A:A,Store_Dim!D:D) -> Williamsfurt | V87: =_xlfn.XLOOKUP(Table17[[#This Row],[Store_ID]],Store_Dim!A:A,Store_Dim!E:E) -> Online | W87: =_xlfn.XLOOKUP(Table17[[#This Row],[Product_ID]],Product_Dim!A:A,Product_Dim!B:B) -> Sports Wrist Sweatbands | X87: =_xlfn.XLOOKUP(Table17[[#This Row],[Product_ID]],Product_Dim!A:A,Product_Dim!C:C) -> Sports | Y87: =_xlfn.XLOOKUP(Table17[[#This Row],[Product_ID]],Product_Dim!A:A,Product_Dim!D:D) -> Accessories | Z87: =_xlfn.XLOOKUP(Table17[[#This Row],[Product_ID]],Product_Dim!A:A,Product_Dim!E:E) -> Olsen-Daniels | AA87: =_xlfn.XLOOKUP(Table17[[#This Row],[Product_ID]],Product_Dim!A:A,Product_Dim!F:F) -> 131.24 | AB87: =_xlfn.XLOOKUP(Table17[[#This Row],[Product_ID]],Product_Dim!A:A,Product_Dim!G:G) -> 232
A88: SALE86 | B88: 45545 | C88: CUST1303 | D88: PROD20 | E88: STORE3 | F88: 3 | G88: 899.58 | H88: 0.28 | I88: PayPal | J88: 1943.0928 | K88: =_xlfn.XLOOKUP(Table17[[#This Row],[Customer_ID]],Customer_Dim!A:A,Customer_Dim!B:B,"False Data") -> John Sloan | L88: =_xlfn.XLOOKUP(Table17[[#This Row],[Customer_ID]],Customer_Dim!A:A,Customer_Dim!C:C,"False Data") -> 23 | M88: {=_xlfn.IFS(Table9[[#This Row],[Age]]<=35,"Youth",Table9[[#This Row],[Age]]<=55,"Adult",Table9[[#This Row],[Age]]>55,"Senior")} -> Youth | N88: =_xlfn.XLOOKUP(Table17[[#This Row],[Customer_ID]],Customer_Dim!A:A,Customer_Dim!D:D,"False Data") -> Female | O88: =_xlfn.XLOOKUP(Table17[[#This Row],[Customer_ID]],Customer_Dim!A:A,Customer_Dim!E:E,"False Data") -> East Johntown | P88: =_xlfn.XLOOKUP(Table17[[#This Row],[Customer_ID]],Customer_Dim!A:A,Customer_Dim!F:F,"False Data") -> Delaware | Q88: =_xlfn.XLOOKUP(Table17[[#This Row],[Customer_ID]],Customer_Dim!A:A,Customer_Dim!G:G,"False Data") -> USA | R88: =_xlfn.XLOOKUP(Table17[[#This Row],[Customer_ID]],Customer_Dim!A:A,Customer_Dim!H:H,"False Data") -> Platinum | S88: =_xlfn.XLOOKUP(Table17[[#This Row],[Store_ID]],Store_Dim!A:A,Store_Dim!B:B) -> Johnson-Wright | T88: =_xlfn.XLOOKUP(Table17[[#This Row],[Store_ID]],Store_Dim!A:A,Store_Dim!C:C) -> North | U88: =_xlfn.XLOOKUP(Table17[[#This Row],[Store_ID]],Store_Dim!A:A,Store_Dim!D:D) -> Hoodberg | V88: =_xlfn.XLOOKUP(Table17[[#This Row],[Store_ID]],Store_Dim!A:A,Store_Dim!E:E) -> Outlet | W88: =_xlfn.XLOOKUP(Table17[[#This Row],[Product_ID]],Product_Dim!A:A,Product_Dim!B:B) -> Outdoor Sports Water Bottle | X88: =_xlfn.XLOOKUP(Table17[[#This Row],[Product_ID]],Product_Dim!A:A,Product_Dim!C:C) -> Sports | Y88: =_xlfn.XLOOKUP(Table17[[#This Row],[Product_ID]],Product_Dim!A:A,Product_Dim!D:D) -> Accessories | Z88: =_xlfn.XLOOKUP(Table17[[#This Row],[Product_ID]],Product_Dim!A:A,Product_Dim!E:E) -> Soto-Ellis | AA88: =_xlfn.XLOOKUP(Table17[[#This Row],[Product_ID]],Product_Dim!A:A,Product_Dim!F:F) -> 131.51 | AB88: =_xlfn.XLOOKUP(Table17[[#This Row],[Product_ID]],Product_Dim!A:A,Product_Dim!G:G) -> 0
A89: SALE87 | B89: 45755 | C89: CUST1327 | D89: PROD1 | E89: STORE10 | F89: 3 | G89: 964.39 | H89: 0.04 | I89: Credit Card | J89: 2777.4432 | K89: =_xlfn.XLOOKUP(Table17[[#This Row],[Customer_ID]],Customer_Dim!A:A,Customer_Dim!B:B,"False Data") -> Reginald Willis | L89: =_xlfn.XLOOKUP(Table17[[#This Row],[Customer_ID]],Customer_Dim!A:A,Customer_Dim!C:C,"False Data") -> 62 | M89: {=_xlfn.IFS(Table9[[#This Row],[Age]]<=35,"Youth",Table9[[#This Row],[Age]]<=55,"Adult",Table9[[#This Row],[Age]]>55,"Senior")} -> Senior | N89: =_xlfn.XLOOKUP(Table17[[#This Row],[Customer_ID]],Customer_Dim!A:A,Customer_Dim!D:D,"False Data") -> Female | O89: =_xlfn.XLOOKUP(Table17[[#This Row],[Customer_ID]],Customer_Dim!A:A,Customer_Dim!E:E,"False Data") -> Kellybury | P89: =_xlfn.XLOOKUP(Table17[[#This Row],[Customer_ID]],Customer_Dim!A:A,Customer_Dim!F:F,"False Data") -> New York | Q89: =_xlfn.XLOOKUP(Table17[[#This Row],[Customer_ID]],Customer_Dim!A:A,Customer_Dim!G:G,"False Data") -> USA | R89: =_xlfn.XLOOKUP(Table17[[#This Row],[Customer_ID]],Customer_Dim!A:A,Customer_Dim!H:H,"False Data") -> Bronze | S89: =_xlfn.XLOOKUP(Table17[[#This Row],[Store_ID]],Store_Dim!A:A,Store_Dim!B:B) -> Hill, Wagner and Ballard | T89: =_xlfn.XLOOKUP(Table17[[#This Row],[Store_ID]],Store_Dim!A:A,Store_Dim!C:C) -> East | U89: =_xlfn.XLOOKUP(Table17[[#This Row],[Store_ID]],Store_Dim!A:A,Store_Dim!D:D) -> East Davidville | V89: =_xlfn.XLOOKUP(Table17[[#This Row],[Store_ID]],Store_Dim!A:A,Store_Dim!E:E) -> Online | W89: =_xlfn.XLOOKUP(Table17[[#This Row],[Product_ID]],Product_Dim!A:A,Product_Dim!B:B) -> Men's Graphic T-Shirt | X89: =_xlfn.XLOOKUP(Table17[[#This Row],[Product_ID]],Product_Dim!A:A,Product_Dim!C:C) -> Clothing | Y89: =_xlfn.XLOOKUP(Table17[[#This Row],[Product_ID]],Product_Dim!A:A,Product_Dim!D:D) -> Tops | Z89: =_xlfn.XLOOKUP(Table17[[#This Row],[Product_ID]],Product_Dim!A:A,Product_Dim!E:E) -> Terry-Moore | AA89: =_xlfn.XLOOKUP(Table17[[#This Row],[Product_ID]],Product_Dim!A:A,Product_Dim!F:F) -> 342.56 | AB89: =_xlfn.XLOOKUP(Table17[[#This Row],[Product_ID]],Product_Dim!A:A,Product_Dim!G:G) -> 181
A90: SALE88 | B90: 45588 | C90: CUST1183 | D90: PROD38 | E90: STORE0 | F90: 2 | G90: 217.83 | H90: 0.14 | I90: PayPal | J90: 374.6676 | K90: =_xlfn.XLOOKUP(Table17[[#This Row],[Customer_ID]],Customer_Dim!A:A,Customer_Dim!B:B,"False Data") -> Mario Jacobs | L90: =_xlfn.XLOOKUP(Table17[[#This Row],[Customer_ID]],Customer_Dim!A:A,Customer_Dim!C:C,"False Data") -> 18 | M90: {=_xlfn.IFS(Table9[[#This Row],[Age]]<=35,"Youth",Table9[[#This Row],[Age]]<=55,"Adult",Table9[[#This Row],[Age]]>55,"Senior")} -> Youth | N90: =_xlfn.XLOOKUP(Table17[[#This Row],[Customer_ID]],Customer_Dim!A:A,Customer_Dim!D:D,"False Data") -> Male | O90: =_xlfn.XLOOKUP(Table17[[#This Row],[Customer_ID]],Customer_Dim!A:A,Customer_Dim!E:E,"False Data") -> Port James | P90: =_xlfn.XLOOKUP(Table17[[#This Row],[Customer_ID]],Customer_Dim!A:A,Customer_Dim!F:F,"False Data") -> New York | Q90: =_xlfn.XLOOKUP(Table17[[#This Row],[Customer_ID]],Customer_Dim!A:A,Customer_Dim!G:G,"False Data") -> USA | R90: =_xlfn.XLOOKUP(Table17[[#This Row],[Customer_ID]],Customer_Dim!A:A,Customer_Dim!H:H,"False Data") -> Platinum | S90: =_xlfn.XLOOKUP(Table17[[#This Row],[Store_ID]],Store_Dim!A:A,Store_Dim!B:B) -> Rivera-Warner | T90: =_xlfn.XLOOKUP(Table17[[#This Row],[Store_ID]],Store_Dim!A:A,Store_Dim!C:C) -> East | U90: =_xlfn.XLOOKUP(Table17[[#This Row],[Store_ID]],Store_Dim!A:A,Store_Dim!D:D) -> Washingtonfurt | V90: =_xlfn.XLOOKUP(Table17[[#This Row],[Store_ID]],Store_Dim!A:A,Store_Dim!E:E) -> Flagship | W90: =_xlfn.XLOOKUP(Table17[[#This Row],[Product_ID]],Product_Dim!A:A,Product_Dim!B:B) -> Sports Water Hydration Pack | X90: =_xlfn.XLOOKUP(Table17[[#This Row],[Product_ID]],Product_Dim!A:A,Product_Dim!C:C) -> Sports | Y90: =_xlfn.XLOOKUP(Table17[[#This Row],[Product_ID]],Product_Dim!A:A,Product_Dim!D:D) -> Outdoor | Z90: =_xlfn.XLOOKUP(Table17[[#This Row],[Product_ID]],Product_Dim!A:A,Product_Dim!E:E) -> Sims-Smith | AA90: =_xlfn.XLOOKUP(Table17[[#This Row],[Product_ID]],Product_Dim!A:A,Product_Dim!F:F) -> 135.61 | AB90: =_xlfn.XLOOKUP(Table17[[#This Row],[Product_ID]],Product_Dim!A:A,Product_Dim!G:G) -> 394
A91: SALE89 | B91: 45848 | C91: CUST1143 | D91: PROD17 | E91: STORE1 | F91: 4 | G91: 187.71 | H91: 0.06 | I91: COD | J91: 705.7896 | K91: =_xlfn.XLOOKUP(Table17[[#This Row],[Customer_ID]],Customer_Dim!A:A,Customer_Dim!B:B,"False Data") -> Carlos Skinner | L91: =_xlfn.XLOOKUP(Table17[[#This Row],[Customer_ID]],Customer_Dim!A:A,Customer_Dim!C:C,"False Data") -> 46 | M91: {=_xlfn.IFS(Table9[[#This Row],[Age]]<=35,"Youth",Table9[[#This Row],[Age]]<=55,"Adult",Table9[[#This Row],[Age]]>55,"Senior")} -> Adult | N91: =_xlfn.XLOOKUP(Table17[[#This Row],[Customer_ID]],Customer_Dim!A:A,Customer_Dim!D:D,"False Data") -> Male | O91: =_xlfn.XLOOKUP(Table17[[#This Row],[Customer_ID]],Customer_Dim!A:A,Customer_Dim!E:E,"False Data") -> Dwaynemouth | P91: =_xlfn.XLOOKUP(Table17[[#This Row],[Customer_ID]],Customer_Dim!A:A,Customer_Dim!F:F,"False Data") -> Alabama | Q91: =_xlfn.XLOOKUP(Table17[[#This Row],[Customer_ID]],Customer_Dim!A:A,Customer_Dim!G:G,"False Data") -> USA | R91: =_xlfn.XLOOKUP(Table17[[#This Row],[Customer_ID]],Customer_Dim!A:A,Customer_Dim!H:H,"False Data") -> Bronze | S91: =_xlfn.XLOOKUP(Table17[[#This Row],[Store_ID]],Store_Dim!A:A,Store_Dim!B:B) -> Martinez, Adkins and Johnson | T91: =_xlfn.XLOOKUP(Table17[[#This Row],[Store_ID]],Store_Dim!A:A,Store_Dim!C:C) -> North | U91: =_xlfn.XLOOKUP(Table17[[#This Row],[Store_ID]],Store_Dim!A:A,Store_Dim!D:D) -> Danielmouth | V91: =_xlfn.XLOOKUP(Table17[[#This Row],[Store_ID]],Store_Dim!A:A,Store_Dim!E:E) -> Flagship | W91: =_xlfn.XLOOKUP(Table17[[#This Row],[Product_ID]],Product_Dim!A:A,Product_Dim!B:B) -> Soccer Training Cone Set | X91: =_xlfn.XLOOKUP(Table17[[#This Row],[Product_ID]],Product_Dim!A:A,Product_Dim!C:C) -> Sports | Y91: =_xlfn.XLOOKUP(Table17[[#This Row],[Product_ID]],Product_Dim!A:A,Product_Dim!D:D) -> Accessories | Z91: =_xlfn.XLOOKUP(Table17[[#This Row],[Product_ID]],Product_Dim!A:A,Product_Dim!E:E) -> Ford, Murphy and Wilson | AA91: =_xlfn.XLOOKUP(Table17[[#This Row],[Product_ID]],Product_Dim!A:A,Product_Dim!F:F) -> 144.53 | AB91: =_xlfn.XLOOKUP(Table17[[#This Row],[Product_ID]],Product_Dim!A:A,Product_Dim!G:G) -> 367
A92: SALE90 | B92: 45577 | C92: CUST1010 | D92: PROD33 | E92: STORE18 | F92: 2 | G92: 350.12 | H92: 0.12 | I92: COD | J92: 616.2112 | K92: =_xlfn.XLOOKUP(Table17[[#This Row],[Customer_ID]],Customer_Dim!A:A,Customer_Dim!B:B,"False Data") -> Dominic Page | L92: =_xlfn.XLOOKUP(Table17[[#This Row],[Customer_ID]],Customer_Dim!A:A,Customer_Dim!C:C,"False Data") -> 53 | M92: {=_xlfn.IFS(Table9[[#This Row],[Age]]<=35,"Youth",Table9[[#This Row],[Age]]<=55,"Adult",Table9[[#This Row],[Age]]>55,"Senior")} -> Adult | N92: =_xlfn.XLOOKUP(Table17[[#This Row],[Customer_ID]],Customer_Dim!A:A,Customer_Dim!D:D,"False Data") -> Male | O92: =_xlfn.XLOOKUP(Table17[[#This Row],[Customer_ID]],Customer_Dim!A:A,Customer_Dim!E:E,"False Data") -> Port Michaelburgh | P92: =_xlfn.XLOOKUP(Table17[[#This Row],[Customer_ID]],Customer_Dim!A:A,Customer_Dim!F:F,"False Data") -> Pennsylvania | Q92: =_xlfn.XLOOKUP(Table17[[#This Row],[Customer_ID]],Customer_Dim!A:A,Customer_Dim!G:G,"False Data") -> USA | R92: =_xlfn.XLOOKUP(Table17[[#This Row],[Customer_ID]],Customer_Dim!A:A,Customer_Dim!H:H,"False Data") -> Bronze | S92: =_xlfn.XLOOKUP(Table17[[#This Row],[Store_ID]],Store_Dim!A:A,Store_Dim!B:B) -> Guerrero-Schmitt | T92: =_xlfn.XLOOKUP(Table17[[#This Row],[Store_ID]],Store_Dim!A:A,Store_Dim!C:C) -> East | U92: =_xlfn.XLOOKUP(Table17[[#This Row],[Store_ID]],Store_Dim!A:A,Store_Dim!D:D) -> East Stevechester | V92: =_xlfn.XLOOKUP(Table17[[#This Row],[Store_ID]],Store_Dim!A:A,Store_Dim!E:E) -> Flagship | W92: =_xlfn.XLOOKUP(Table17[[#This Row],[Product_ID]],Product_Dim!A:A,Product_Dim!B:B) -> Modern Wall Clock | X92: =_xlfn.XLOOKUP(Table17[[#This Row],[Product_ID]],Product_Dim!A:A,Product_Dim!C:C) -> Home | Y92: =_xlfn.XLOOKUP(Table17[[#This Row],[Product_ID]],Product_Dim!A:A,Product_Dim!D:D) -> Decor | Z92: =_xlfn.XLOOKUP(Table17[[#This Row],[Product_ID]],Product_Dim!A:A,Product_Dim!E:E) -> Weiss-Watson | AA92: =_xlfn.XLOOKUP(Table17[[#This Row],[Product_ID]],Product_Dim!A:A,Product_Dim!F:F) -> 179.77 | AB92: =_xlfn.XLOOKUP(Table17[[#This Row],[Product_ID]],Product_Dim!A:A,Product_Dim!G:G) -> 305
A93: SALE91 | B93: 45312 | C93: CUST1406 | D93: PROD16 | E93: STORE1 | F93: 4 | G93: 102.19 | H93: 0.17 | I93: PayPal | J93: 339.2708 | K93: =_xlfn.XLOOKUP(Table17[[#This Row],[Customer_ID]],Customer_Dim!A:A,Customer_Dim!B:B,"False Data") -> David Lozano | L93: =_xlfn.XLOOKUP(Table17[[#This Row],[Customer_ID]],Customer_Dim!A:A,Customer_Dim!C:C,"False Data") -> 23 | M93: {=_xlfn.IFS(Table9[[#This Row],[Age]]<=35,"Youth",Table9[[#This Row],[Age]]<=55,"Adult",Table9[[#This Row],[Age]]>55,"Senior")} -> Youth | N93: =_xlfn.XLOOKUP(Table17[[#This Row],[Customer_ID]],Customer_Dim!A:A,Customer_Dim!D:D,"False Data") -> Female | O93: =_xlfn.XLOOKUP(Table17[[#This Row],[Customer_ID]],Customer_Dim!A:A,Customer_Dim!E:E,"False Data") -> North Michaelfurt | P93: =_xlfn.XLOOKUP(Table17[[#This Row],[Customer_ID]],Customer_Dim!A:A,Customer_Dim!F:F,"False Data") -> Wisconsin | Q93: =_xlfn.XLOOKUP(Table17[[#This Row],[Customer_ID]],Customer_Dim!A:A,Customer_Dim!G:G,"False Data") -> USA | R93: =_xlfn.XLOOKUP(Table17[[#This Row],[Customer_ID]],Customer_Dim!A:A,Customer_Dim!H:H,"False Data") -> Gold | S93: =_xlfn.XLOOKUP(Table17[[#This Row],[Store_ID]],Store_Dim!A:A,Store_Dim!B:B) -> Martinez, Adkins and Johnson | T93: =_xlfn.XLOOKUP(Table17[[#This Row],[Store_ID]],Store_Dim!A:A,Store_Dim!C:C) -> North | U93: =_xlfn.XLOOKUP(Table17[[#This Row],[Store_ID]],Store_Dim!A:A,Store_Dim!D:D) -> Danielmouth | V93: =_xlfn.XLOOKUP(Table17[[#This Row],[Store_ID]],Store_Dim!A:A,Store_Dim!E:E) -> Flagship | W93: =_xlfn.XLOOKUP(Table17[[#This Row],[Product_ID]],Product_Dim!A:A,Product_Dim!B:B) -> Beard Grooming Kit | X93: =_xlfn.XLOOKUP(Table17[[#This Row],[Product_ID]],Product_Dim!A:A,Product_Dim!C:C) -> Beauty | Y93: =_xlfn.XLOOKUP(Table17[[#This Row],[Product_ID]],Product_Dim!A:A,Product_Dim!D:D) -> Grooming | Z93: =_xlfn.XLOOKUP(Table17[[#This Row],[Product_ID]],Product_Dim!A:A,Product_Dim!E:E) -> Erickson-Green | AA93: =_xlfn.XLOOKUP(Table17[[#This Row],[Product_ID]],Product_Dim!A:A,Product_Dim!F:F) -> 337.42 | AB93: =_xlfn.XLOOKUP(Table17[[#This Row],[Product_ID]],Product_Dim!A:A,Product_Dim!G:G) -> 256
A94: SALE92 | B94: 45350 | C94: CUST1007 | D94: PROD86 | E94: STORE4 | F94: 1 | G94: 696.53 | H94: 0.17 | I94: Credit Card | J94: 578.1199 | K94: =_xlfn.XLOOKUP(Table17[[#This Row],[Customer_ID]],Customer_Dim!A:A,Customer_Dim!B:B,"False Data") -> Daniel Boyd | L94: =_xlfn.XLOOKUP(Table17[[#This Row],[Customer_ID]],Customer_Dim!A:A,Customer_Dim!C:C,"False Data") -> 29 | M94: {=_xlfn.IFS(Table9[[#This Row],[Age]]<=35,"Youth",Table9[[#This Row],[Age]]<=55,"Adult",Table9[[#This Row],[Age]]>55,"Senior")} -> Youth | N94: =_xlfn.XLOOKUP(Table17[[#This Row],[Customer_ID]],Customer_Dim!A:A,Customer_Dim!D:D,"False Data") -> Female | O94: =_xlfn.XLOOKUP(Table17[[#This Row],[Customer_ID]],Customer_Dim!A:A,Customer_Dim!E:E,"False Data") -> West Pamelafurt | P94: =_xlfn.XLOOKUP(Table17[[#This Row],[Customer_ID]],Customer_Dim!A:A,Customer_Dim!F:F,"False Data") -> West Virginia | Q94: =_xlfn.XLOOKUP(Table17[[#This Row],[Customer_ID]],Customer_Dim!A:A,Customer_Dim!G:G,"False Data") -> USA | R94: =_xlfn.XLOOKUP(Table17[[#This Row],[Customer_ID]],Customer_Dim!A:A,Customer_Dim!H:H,"False Data") -> Bronze | S94: =_xlfn.XLOOKUP(Table17[[#This Row],[Store_ID]],Store_Dim!A:A,Store_Dim!B:B) -> Alexander Group | T94: =_xlfn.XLOOKUP(Table17[[#This Row],[Store_ID]],Store_Dim!A:A,Store_Dim!C:C) -> South | U94: =_xlfn.XLOOKUP(Table17[[#This Row],[Store_ID]],Store_Dim!A:A,Store_Dim!D:D) -> Port Sharon | V94: =_xlfn.XLOOKUP(Table17[[#This Row],[Store_ID]],Store_Dim!A:A,Store_Dim!E:E) -> Online | W94: =_xlfn.XLOOKUP(Table17[[#This Row],[Product_ID]],Product_Dim!A:A,Product_Dim!B:B) -> Kitchen Cutting Board | X94: =_xlfn.XLOOKUP(Table17[[#This Row],[Product_ID]],Product_Dim!A:A,Product_Dim!C:C) -> Home | Y94: =_xlfn.XLOOKUP(Table17[[#This Row],[Product_ID]],Product_Dim!A:A,Product_Dim!D:D) -> Kitchen | Z94: =_xlfn.XLOOKUP(Table17[[#This Row],[Product_ID]],Product_Dim!A:A,Product_Dim!E:E) -> Taylor, Dodson and Johnston | AA94: =_xlfn.XLOOKUP(Table17[[#This Row],[Product_ID]],Product_Dim!A:A,Product_Dim!F:F) -> 176.07 | AB94: =_xlfn.XLOOKUP(Table17[[#This Row],[Product_ID]],Product_Dim!A:A,Product_Dim!G:G) -> 82
A95: SALE93 | B95: 45657 | C95: CUST1065 | D95: PROD19 | E95: STORE4 | F95: 2 | G95: 327.52 | H95: 0.15 | I95: PayPal | J95: 556.784 | K95: =_xlfn.XLOOKUP(Table17[[#This Row],[Customer_ID]],Customer_Dim!A:A,Customer_Dim!B:B,"False Data") -> Michael Thomas | L95: =_xlfn.XLOOKUP(Table17[[#This Row],[Customer_ID]],Customer_Dim!A:A,Customer_Dim!C:C,"False Data") -> 21 | M95: {=_xlfn.IFS(Table9[[#This Row],[Age]]<=35,"Youth",Table9[[#This Row],[Age]]<=55,"Adult",Table9[[#This Row],[Age]]>55,"Senior")} -> Youth | N95: =_xlfn.XLOOKUP(Table17[[#This Row],[Customer_ID]],Customer_Dim!A:A,Customer_Dim!D:D,"False Data") -> Female | O95: =_xlfn.XLOOKUP(Table17[[#This Row],[Customer_ID]],Customer_Dim!A:A,Customer_Dim!E:E,"False Data") -> Woodmouth | P95: =_xlfn.XLOOKUP(Table17[[#This Row],[Customer_ID]],Customer_Dim!A:A,Customer_Dim!F:F,"False Data") -> Nevada | Q95: =_xlfn.XLOOKUP(Table17[[#This Row],[Customer_ID]],Customer_Dim!A:A,Customer_Dim!G:G,"False Data") -> USA | R95: =_xlfn.XLOOKUP(Table17[[#This Row],[Customer_ID]],Customer_Dim!A:A,Customer_Dim!H:H,"False Data") -> Silver | S95: =_xlfn.XLOOKUP(Table17[[#This Row],[Store_ID]],Store_Dim!A:A,Store_Dim!B:B) -> Alexander Group | T95: =_xlfn.XLOOKUP(Table17[[#This Row],[Store_ID]],Store_Dim!A:A,Store_Dim!C:C) -> South | U95: =_xlfn.XLOOKUP(Table17[[#This Row],[Store_ID]],Store_Dim!A:A,Store_Dim!D:D) -> Port Sharon | V95: =_xlfn.XLOOKUP(Table17[[#This Row],[Store_ID]],Store_Dim!A:A,Store_Dim!E:E) -> Online | W95: =_xlfn.XLOOKUP(Table17[[#This Row],[Product_ID]],Product_Dim!A:A,Product_Dim!B:B) -> Knee Support Brace | X95: =_xlfn.XLOOKUP(Table17[[#This Row],[Product_ID]],Product_Dim!A:A,Product_Dim!C:C) -> Sports | Y95: =_xlfn.XLOOKUP(Table17[[#This Row],[Product_ID]],Product_Dim!A:A,Product_Dim!D:D) -> Equipment | Z95: =_xlfn.XLOOKUP(Table17[[#This Row],[Product_ID]],Product_Dim!A:A,Product_Dim!E:E) -> May-Reese | AA95: =_xlfn.XLOOKUP(Table17[[#This Row],[Product_ID]],Product_Dim!A:A,Product_Dim!F:F) -> 21.34 | AB95: =_xlfn.XLOOKUP(Table17[[#This Row],[Product_ID]],Product_Dim!A:A,Product_Dim!G:G) -> 65
A96: SALE94 | B96: 45530 | C96: CUST1298 | D96: PROD97 | E96: STORE19 | F96: 2 | G96: 569.36 | H96: 0.01 | I96: PayPal | J96: =(Table17[[#This Row],[Unit_Price]]*Table17[[#This Row],[Quantity]])*(1-Table17[[#This Row],[Discount]]) -> 1127.3328 | K96: =_xlfn.XLOOKUP(Table17[[#This Row],[Customer_ID]],Customer_Dim!A:A,Customer_Dim!B:B,"False Data") -> Tracy Stephens | L96: =_xlfn.XLOOKUP(Table17[[#This Row],[Customer_ID]],Customer_Dim!A:A,Customer_Dim!C:C,"False Data") -> 64 | M96: {=_xlfn.IFS(Table9[[#This Row],[Age]]<=35,"Youth",Table9[[#This Row],[Age]]<=55,"Adult",Table9[[#This Row],[Age]]>55,"Senior")} -> Senior | N96: =_xlfn.XLOOKUP(Table17[[#This Row],[Customer_ID]],Customer_Dim!A:A,Customer_Dim!D:D,"False Data") -> Male | O96: =_xlfn.XLOOKUP(Table17[[#This Row],[Customer_ID]],Customer_Dim!A:A,Customer_Dim!E:E,"False Data") -> New Joshuatown | P96: =_xlfn.XLOOKUP(Table17[[#This Row],[Customer_ID]],Customer_Dim!A:A,Customer_Dim!F:F,"False Data") -> Maine | Q96: =_xlfn.XLOOKUP(Table17[[#This Row],[Customer_ID]],Customer_Dim!A:A,Customer_Dim!G:G,"False Data") -> USA | R96: =_xlfn.XLOOKUP(Table17[[#This Row],[Customer_ID]],Customer_Dim!A:A,Customer_Dim!H:H,"False Data") -> Platinum | S96: =_xlfn.XLOOKUP(Table17[[#This Row],[Store_ID]],Store_Dim!A:A,Store_Dim!B:B) -> Mann-Austin | T96: =_xlfn.XLOOKUP(Table17[[#This Row],[Store_ID]],Store_Dim!A:A,Store_Dim!C:C) -> East | U96: =_xlfn.XLOOKUP(Table17[[#This Row],[Store_ID]],Store_Dim!A:A,Store_Dim!D:D) -> Vasquezborough | V96: =_xlfn.XLOOKUP(Table17[[#This Row],[Store_ID]],Store_Dim!A:A,Store_Dim!E:E) -> Online | W96: =_xlfn.XLOOKUP(Table17[[#This Row],[Product_ID]],Product_Dim!A:A,Product_Dim!B:B) -> Cricket Bat | X96: =_xlfn.XLOOKUP(Table17[[#This Row],[Product_ID]],Product_Dim!A:A,Product_Dim!C:C) -> Sports | Y96: =_xlfn.XLOOKUP(Table17[[#This Row],[Product_ID]],Product_Dim!A:A,Product_Dim!D:D) -> Team Sports | Z96: =_xlfn.XLOOKUP(Table17[[#This Row],[Product_ID]],Product_Dim!A:A,Product_Dim!E:E) -> Khan LLC | AA96: =_xlfn.XLOOKUP(Table17[[#This Row],[Product_ID]],Product_Dim!A:A,Product_Dim!F:F) -> 245.98 | AB96: =_xlfn.XLOOKUP(Table17[[#This Row],[Product_ID]],Product_Dim!A:A,Product_Dim!G:G) -> 471
A97: SALE95 | B97: 45556 | C97: CUST1321 | D97: PROD99 | E97: STORE6 | F97: 2 | G97: 68.29 | H97: 0.14 | I97: COD | J97: 117.4588 | K97: =_xlfn.XLOOKUP(Table17[[#This Row],[Customer_ID]],Customer_Dim!A:A,Customer_Dim!B:B,"False Data") -> Darren Burton | L97: =_xlfn.XLOOKUP(Table17[[#This Row],[Customer_ID]],Customer_Dim!A:A,Customer_Dim!C:C,"False Data") -> 21 | M97: {=_xlfn.IFS(Table9[[#This Row],[Age]]<=35,"Youth",Table9[[#This Row],[Age]]<=55,"Adult",Table9[[#This Row],[Age]]>55,"Senior")} -> Youth | N97: =_xlfn.XLOOKUP(Table17[[#This Row],[Customer_ID]],Customer_Dim!A:A,Customer_Dim!D:D,"False Data") -> Female | O97: =_xlfn.XLOOKUP(Table17[[#This Row],[Customer_ID]],Customer_Dim!A:A,Customer_Dim!E:E,"False Data") -> Lake Alice | P97: =_xlfn.XLOOKUP(Table17[[#This Row],[Customer_ID]],Customer_Dim!A:A,Customer_Dim!F:F,"False Data") -> Tennessee | Q97: =_xlfn.XLOOKUP(Table17[[#This Row],[Customer_ID]],Customer_Dim!A:A,Customer_Dim!G:G,"False Data") -> USA | R97: =_xlfn.XLOOKUP(Table17[[#This Row],[Customer_ID]],Customer_Dim!A:A,Customer_Dim!H:H,"False Data") -> Bronze | S97: =_xlfn.XLOOKUP(Table17[[#This Row],[Store_ID]],Store_Dim!A:A,Store_Dim!B:B) -> Benson-Elliott | T97: =_xlfn.XLOOKUP(Table17[[#This Row],[Store_ID]],Store_Dim!A:A,Store_Dim!C:C) -> East | U97: =_xlfn.XLOOKUP(Table17[[#This Row],[Store_ID]],Store_Dim!A:A,Store_Dim!D:D) -> Port Josephberg | V97: =_xlfn.XLOOKUP(Table17[[#This Row],[Store_ID]],Store_Dim!A:A,Store_Dim!E:E) -> Online | W97: =_xlfn.XLOOKUP(Table17[[#This Row],[Product_ID]],Product_Dim!A:A,Product_Dim!B:B) -> Stainless Steel Cookware Set | X97: =_xlfn.XLOOKUP(Table17[[#This Row],[Product_ID]],Product_Dim!A:A,Product_Dim!C:C) -> Home | Y97: =_xlfn.XLOOKUP(Table17[[#This Row],[Product_ID]],Product_Dim!A:A,Product_Dim!D:D) -> Kitchen | Z97: =_xlfn.XLOOKUP(Table17[[#This Row],[Product_ID]],Product_Dim!A:A,Product_Dim!E:E) -> Campbell Ltd | AA97: =_xlfn.XLOOKUP(Table17[[#This Row],[Product_ID]],Product_Dim!A:A,Product_Dim!F:F) -> 201.41 | AB97: =_xlfn.XLOOKUP(Table17[[#This Row],[Product_ID]],Product_Dim!A:A,Product_Dim!G:G) -> 146
A98: SALE96 | B98: 45523 | C98: CUST1244 | D98: PROD50 | E98: STORE10 | F98: 1 | G98: 842.9 | H98: 0.06 | I98: COD | J98: 792.326 | K98: =_xlfn.XLOOKUP(Table17[[#This Row],[Customer_ID]],Customer_Dim!A:A,Customer_Dim!B:B,"False Data") -> Nancy Page | L98: =_xlfn.XLOOKUP(Table17[[#This Row],[Customer_ID]],Customer_Dim!A:A,Customer_Dim!C:C,"False Data") -> 19 | M98: {=_xlfn.IFS(Table9[[#This Row],[Age]]<=35,"Youth",Table9[[#This Row],[Age]]<=55,"Adult",Table9[[#This Row],[Age]]>55,"Senior")} -> Youth | N98: =_xlfn.XLOOKUP(Table17[[#This Row],[Customer_ID]],Customer_Dim!A:A,Customer_Dim!D:D,"False Data") -> Male | O98: =_xlfn.XLOOKUP(Table17[[#This Row],[Customer_ID]],Customer_Dim!A:A,Customer_Dim!E:E,"False Data") -> West Julia | P98: =_xlfn.XLOOKUP(Table17[[#This Row],[Customer_ID]],Customer_Dim!A:A,Customer_Dim!F:F,"False Data") -> Utah | Q98: =_xlfn.XLOOKUP(Table17[[#This Row],[Customer_ID]],Customer_Dim!A:A,Customer_Dim!G:G,"False Data") -> USA | R98: =_xlfn.XLOOKUP(Table17[[#This Row],[Customer_ID]],Customer_Dim!A:A,Customer_Dim!H:H,"False Data") -> Bronze | S98: =_xlfn.XLOOKUP(Table17[[#This Row],[Store_ID]],Store_Dim!A:A,Store_Dim!B:B) -> Hill, Wagner and Ballard | T98: =_xlfn.XLOOKUP(Table17[[#This Row],[Store_ID]],Store_Dim!A:A,Store_Dim!C:C) -> East | U98: =_xlfn.XLOOKUP(Table17[[#This Row],[Store_ID]],Store_Dim!A:A,Store_Dim!D:D) -> East Davidville | V98: =_xlfn.XLOOKUP(Table17[[#This Row],[Store_ID]],Store_Dim!A:A,Store_Dim!E:E) -> Online | W98: =_xlfn.XLOOKUP(Table17[[#This Row],[Product_ID]],Product_Dim!A:A,Product_Dim!B:B) -> Boxing Hand Wraps | X98: =_xlfn.XLOOKUP(Table17[[#This Row],[Product_ID]],Product_Dim!A:A,Product_Dim!C:C) -> Sports | Y98: =_xlfn.XLOOKUP(Table17[[#This Row],[Product_ID]],Product_Dim!A:A,Product_Dim!D:D) -> Fitness | Z98: =_xlfn.XLOOKUP(Table17[[#This Row],[Product_ID]],Product_Dim!A:A,Product_Dim!E:E) -> Smith-King | AA98: =_xlfn.XLOOKUP(Table17[[#This Row],[Product_ID]],Product_Dim!A:A,Product_Dim!F:F) -> 190.29 | AB98: =_xlfn.XLOOKUP(Table17[[#This Row],[Product_ID]],Product_Dim!A:A,Product_Dim!G:G) -> 260
A99: SALE97 | B99: 45587 | C99: CUST1287 | D99: PROD3 | E99: STORE3 | F99: 3 | G99: 751.94 | H99: 0.26 | I99: PayPal | J99: 1669.3068 | K99: =_xlfn.XLOOKUP(Table17[[#This Row],[Customer_ID]],Customer_Dim!A:A,Customer_Dim!B:B,"False Data") -> Cynthia Roberts | L99: =_xlfn.XLOOKUP(Table17[[#This Row],[Customer_ID]],Customer_Dim!A:A,Customer_Dim!C:C,"False Data") -> 22 | M99: {=_xlfn.IFS(Table9[[#This Row],[Age]]<=35,"Youth",Table9[[#This Row],[Age]]<=55,"Adult",Table9[[#This Row],[Age]]>55,"Senior")} -> Youth | N99: =_xlfn.XLOOKUP(Table17[[#This Row],[Customer_ID]],Customer_Dim!A:A,Customer_Dim!D:D,"False Data") -> Female | O99: =_xlfn.XLOOKUP(Table17[[#This Row],[Customer_ID]],Customer_Dim!A:A,Customer_Dim!E:E,"False Data") -> Millerfort | P99: =_xlfn.XLOOKUP(Table17[[#This Row],[Customer_ID]],Customer_Dim!A:A,Customer_Dim!F:F,"False Data") -> Vermont | Q99: =_xlfn.XLOOKUP(Table17[[#This Row],[Customer_ID]],Customer_Dim!A:A,Customer_Dim!G:G,"False Data") -> USA | R99: =_xlfn.XLOOKUP(Table17[[#This Row],[Customer_ID]],Customer_Dim!A:A,Customer_Dim!H:H,"False Data") -> Gold | S99: =_xlfn.XLOOKUP(Table17[[#This Row],[Store_ID]],Store_Dim!A:A,Store_Dim!B:B) -> Johnson-Wright | T99: =_xlfn.XLOOKUP(Table17[[#This Row],[Store_ID]],Store_Dim!A:A,Store_Dim!C:C) -> North | U99: =_xlfn.XLOOKUP(Table17[[#This Row],[Store_ID]],Store_Dim!A:A,Store_Dim!D:D) -> Hoodberg | V99: =_xlfn.XLOOKUP(Table17[[#This Row],[Store_ID]],Store_Dim!A:A,Store_Dim!E:E) -> Outlet | W99: =_xlfn.XLOOKUP(Table17[[#This Row],[Product_ID]],Product_Dim!A:A,Product_Dim!B:B) -> Men's Running Jacket | X99: =_xlfn.XLOOKUP(Table17[[#This Row],[Product_ID]],Product_Dim!A:A,Product_Dim!C:C) -> Clothing | Y99: =_xlfn.XLOOKUP(Table17[[#This Row],[Product_ID]],Product_Dim!A:A,Product_Dim!D:D) -> Outerwear | Z99: =_xlfn.XLOOKUP(Table17[[#This Row],[Product_ID]],Product_Dim!A:A,Product_Dim!E:E) -> Pineda Ltd | AA99: =_xlfn.XLOOKUP(Table17[[#This Row],[Product_ID]],Product_Dim!A:A,Product_Dim!F:F) -> 364.67 | AB99: =_xlfn.XLOOKUP(Table17[[#This Row],[Product_ID]],Product_Dim!A:A,Product_Dim!G:G) -> 452
A100: SALE98 | B100: 45580 | C100: CUST1131 | D100: PROD56 | E100: STORE7 | F100: 4 | G100: 476.28 | H100: 0.17 | I100: Credit Card | J100: 1581.2496 | K100: =_xlfn.XLOOKUP(Table17[[#This Row],[Customer_ID]],Customer_Dim!A:A,Customer_Dim!B:B,"False Data") -> Joseph Richards | L100: =_xlfn.XLOOKUP(Table17[[#This Row],[Customer_ID]],Customer_Dim!A:A,Customer_Dim!C:C,"False Data") -> 34 | M100: {=_xlfn.IFS(Table9[[#This Row],[Age]]<=35,"Youth",Table9[[#This Row],[Age]]<=55,"Adult",Table9[[#This Row],[Age]]>55,"Senior")} -> Youth | N100: =_xlfn.XLOOKUP(Table17[[#This Row],[Customer_ID]],Customer_Dim!A:A,Customer_Dim!D:D,"False Data") -> Female | O100: =_xlfn.XLOOKUP(Table17[[#This Row],[Customer_ID]],Customer_Dim!A:A,Customer_Dim!E:E,"False Data") -> Wigginsville | P100: =_xlfn.XLOOKUP(Table17[[#This Row],[Customer_ID]],Customer_Dim!A:A,Customer_Dim!F:F,"False Data") -> Alabama | Q100: =_xlfn.XLOOKUP(Table17[[#This Row],[Customer_ID]],Customer_Dim!A:A,Customer_Dim!G:G,"False Data") -> USA | R100: =_xlfn.XLOOKUP(Table17[[#This Row],[Customer_ID]],Customer_Dim!A:A,Customer_Dim!H:H,"False Data") -> Bronze | S100: =_xlfn.XLOOKUP(Table17[[#This Row],[Store_ID]],Store_Dim!A:A,Store_Dim!B:B) -> Martinez-Mullins | T100: =_xlfn.XLOOKUP(Table17[[#This Row],[Store_ID]],Store_Dim!A:A,Store_Dim!C:C) -> South | U100: =_xlfn.XLOOKUP(Table17[[#This Row],[Store_ID]],Store_Dim!A:A,Store_Dim!D:D) -> Williamsfurt | V100: =_xlfn.XLOOKUP(Table17[[#This Row],[Store_ID]],Store_Dim!A:A,Store_Dim!E:E) -> Online | W100: =_xlfn.XLOOKUP(Table17[[#This Row],[Product_ID]],Product_Dim!A:A,Product_Dim!B:B) -> Premium Blanket Throw | X100: =_xlfn.XLOOKUP(Table17[[#This Row],[Product_ID]],Product_Dim!A:A,Product_Dim!C:C) -> Home | Y100: =_xlfn.XLOOKUP(Table17[[#This Row],[Product_ID]],Product_Dim!A:A,Product_Dim!D:D) -> Decor | Z100: =_xlfn.XLOOKUP(Table17[[#This Row],[Product_ID]],Product_Dim!A:A,Product_Dim!E:E) -> Hernandez, Kennedy and Porter | AA100: =_xlfn.XLOOKUP(Table17[[#This Row],[Product_ID]],Product_Dim!A:A,Product_Dim!F:F) -> 461.47 | AB100: =_xlfn.XLOOKUP(Table17[[#This Row],[Product_ID]],Product_Dim!A:A,Product_Dim!G:G) -> 190
A101: SALE99 | B101: 45479 | C101: CUST1325 | D101: PROD54 | E101: STORE3 | F101: 3 | G101: 541.99 | H101: 0.24 | I101: COD | J101: 1235.7372 | K101: =_xlfn.XLOOKUP(Table17[[#This Row],[Customer_ID]],Customer_Dim!A:A,Customer_Dim!B:B,"False Data") -> Andrew Smith | L101: =_xlfn.XLOOKUP(Table17[[#This Row],[Customer_ID]],Customer_Dim!A:A,Customer_Dim!C:C,"False Data") -> 60 | M101: {=_xlfn.IFS(Table9[[#This Row],[Age]]<=35,"Youth",Table9[[#This Row],[Age]]<=55,"Adult",Table9[[#This Row],[Age]]>55,"Senior")} -> Senior | N101: =_xlfn.XLOOKUP(Table17[[#This Row],[Customer_ID]],Customer_Dim!A:A,Customer_Dim!D:D,"False Data") -> Male | O101: =_xlfn.XLOOKUP(Table17[[#This Row],[Customer_ID]],Customer_Dim!A:A,Customer_Dim!E:E,"False Data") -> East Matthew | P101: =_xlfn.XLOOKUP(Table17[[#This Row],[Customer_ID]],Customer_Dim!A:A,Customer_Dim!F:F,"False Data") -> Wisconsin | Q101: =_xlfn.XLOOKUP(Table17[[#This Row],[Customer_ID]],Customer_Dim!A:A,Customer_Dim!G:G,"False Data") -> USA | R101: =_xlfn.XLOOKUP(Table17[[#This Row],[Customer_ID]],Customer_Dim!A:A,Customer_Dim!H:H,"False Data") -> Bronze | S101: =_xlfn.XLOOKUP(Table17[[#This Row],[Store_ID]],Store_Dim!A:A,Store_Dim!B:B) -> Johnson-Wright | T101: =_xlfn.XLOOKUP(Table17[[#This Row],[Store_ID]],Store_Dim!A:A,Store_Dim!C:C) -> North | U101: =_xlfn.XLOOKUP(Table17[[#This Row],[Store_ID]],Store_Dim!A:A,Store_Dim!D:D) -> Hoodberg | V101: =_xlfn.XLOOKUP(Table17[[#This Row],[Store_ID]],Store_Dim!A:A,Store_Dim!E:E) -> Outlet | W101: =_xlfn.XLOOKUP(Table17[[#This Row],[Product_ID]],Product_Dim!A:A,Product_Dim!B:B) -> Sports Stopwatch Pro | X101: =_xlfn.XLOOKUP(Table17[[#This Row],[Product_ID]],Product_Dim!A:A,Product_Dim!C:C) -> Sports | Y101: =_xlfn.XLOOKUP(Table17[[#This Row],[Product_ID]],Product_Dim!A:A,Product_Dim!D:D) -> Accessories | Z101: =_xlfn.XLOOKUP(Table17[[#This Row],[Product_ID]],Product_Dim!A:A,Product_Dim!E:E) -> Thompson-French | AA101: =_xlfn.XLOOKUP(Table17[[#This Row],[Product_ID]],Product_Dim!A:A,Product_Dim!F:F) -> 434.84 | AB101: =_xlfn.XLOOKUP(Table17[[#This Row],[Product_ID]],Product_Dim!A:A,Product_Dim!G:G) -> 185
A102: SALE100 | B102: 45677 | C102: CUST1369 | D102: PROD33 | E102: STORE5 | F102: 2 | G102: 401.5 | H102: 0.18 | I102: Credit Card | J102: 658.46 | K102: =_xlfn.XLOOKUP(Table17[[#This Row],[Customer_ID]],Customer_Dim!A:A,Customer_Dim!B:B,"False Data") -> Gregory Allen | L102: =_xlfn.XLOOKUP(Table17[[#This Row],[Customer_ID]],Customer_Dim!A:A,Customer_Dim!C:C,"False Data") -> 20 | M102: {=_xlfn.IFS(Table9[[#This Row],[Age]]<=35,"Youth",Table9[[#This Row],[Age]]<=55,"Adult",Table9[[#This Row],[Age]]>55,"Senior")} -> Youth | N102: =_xlfn.XLOOKUP(Table17[[#This Row],[Customer_ID]],Customer_Dim!A:A,Customer_Dim!D:D,"False Data") -> Female | O102: =_xlfn.XLOOKUP(Table17[[#This Row],[Customer_ID]],Customer_Dim!A:A,Customer_Dim!E:E,"False Data") -> West Bruce | P102: =_xlfn.XLOOKUP(Table17[[#This Row],[Customer_ID]],Customer_Dim!A:A,Customer_Dim!F:F,"False Data") -> Vermont | Q102: =_xlfn.XLOOKUP(Table17[[#This Row],[Customer_ID]],Customer_Dim!A:A,Customer_Dim!G:G,"False Data") -> USA | R102: =_xlfn.XLOOKUP(Table17[[#This Row],[Customer_ID]],Customer_Dim!A:A,Customer_Dim!H:H,"False Data") -> Platinum | S102: =_xlfn.XLOOKUP(Table17[[#This Row],[Store_ID]],Store_Dim!A:A,Store_Dim!B:B) -> Gray Ltd | T102: =_xlfn.XLOOKUP(Table17[[#This Row],[Store_ID]],Store_Dim!A:A,Store_Dim!C:C) -> North | U102: =_xlfn.XLOOKUP(Table17[[#This Row],[Store_ID]],Store_Dim!A:A,Store_Dim!D:D) -> New Michaelchester | V102: =_xlfn.XLOOKUP(Table17[[#This Row],[Store_ID]],Store_Dim!A:A,Store_Dim!E:E) -> Outlet | W102: =_xlfn.XLOOKUP(Table17[[#This Row],[Product_ID]],Product_Dim!A:A,Product_Dim!B:B) -> Modern Wall Clock | X102: =_xlfn.XLOOKUP(Table17[[#This Row],[Product_ID]],Product_Dim!A:A,Product_Dim!C:C) -> Home | Y102: =_xlfn.XLOOKUP(Table17[[#This Row],[Product_ID]],Product_Dim!A:A,Product_Dim!D:D) -> Decor | Z102: =_xlfn.XLOOKUP(Table17[[#This Row],[Product_ID]],Product_Dim!A:A,Product_Dim!E:E) -> Weiss-Watson | AA102: =_xlfn.XLOOKUP(Table17[[#This Row],[Product_ID]],Product_Dim!A:A,Product_Dim!F:F) -> 179.77 | AB102: =_xlfn.XLOOKUP(Table17[[#This Row],[Product_ID]],Product_Dim!A:A,Product_Dim!G:G) -> 305
A103: SALE101 | B103: 45453 | C103: CUST1084 | D103: PROD25 | E103: STORE13 | F103: 3 | G103: 359.56 | H103: 0.17 | I103: PayPal | J103: 895.3044 | K103: =_xlfn.XLOOKUP(Table17[[#This Row],[Customer_ID]],Customer_Dim!A:A,Customer_Dim!B:B,"False Data") -> Christy Hoffman | L103: =_xlfn.XLOOKUP(Table17[[#This Row],[Customer_ID]],Customer_Dim!A:A,Customer_Dim!C:C,"False Data") -> 26 | M103: {=_xlfn.IFS(Table9[[#This Row],[Age]]<=35,"Youth",Table9[[#This Row],[Age]]<=55,"Adult",Table9[[#This Row],[Age]]>55,"Senior")} -> Youth | N103: =_xlfn.XLOOKUP(Table17[[#This Row],[Customer_ID]],Customer_Dim!A:A,Customer_Dim!D:D,"False Data") -> Female | O103: =_xlfn.XLOOKUP(Table17[[#This Row],[Customer_ID]],Customer_Dim!A:A,Customer_Dim!E:E,"False Data") -> Garyberg | P103: =_xlfn.XLOOKUP(Table17[[#This Row],[Customer_ID]],Customer_Dim!A:A,Customer_Dim!F:F,"False Data") -> Indiana | Q103: =_xlfn.XLOOKUP(Table17[[#This Row],[Customer_ID]],Customer_Dim!A:A,Customer_Dim!G:G,"False Data") -> USA | R103: =_xlfn.XLOOKUP(Table17[[#This Row],[Customer_ID]],Customer_Dim!A:A,Customer_Dim!H:H,"False Data") -> Platinum | S103: =_xlfn.XLOOKUP(Table17[[#This Row],[Store_ID]],Store_Dim!A:A,Store_Dim!B:B) -> Gardner, Humphrey and Contreras | T103: =_xlfn.XLOOKUP(Table17[[#This Row],[Store_ID]],Store_Dim!A:A,Store_Dim!C:C) -> East | U103: =_xlfn.XLOOKUP(Table17[[#This Row],[Store_ID]],Store_Dim!A:A,Store_Dim!D:D) -> Johnsonville | V103: =_xlfn.XLOOKUP(Table17[[#This Row],[Store_ID]],Store_Dim!A:A,Store_Dim!E:E) -> Flagship | W103: =_xlfn.XLOOKUP(Table17[[#This Row],[Product_ID]],Product_Dim!A:A,Product_Dim!B:B) -> Women's Scarf Set | X103: =_xlfn.XLOOKUP(Table17[[#This Row],[Product_ID]],Product_Dim!A:A,Product_Dim!C:C) -> Clothing | Y103: =_xlfn.XLOOKUP(Table17[[#This Row],[Product_ID]],Product_Dim!A:A,Product_Dim!D:D) -> Accessories | Z103: =_xlfn.XLOOKUP(Table17[[#This Row],[Product_ID]],Product_Dim!A:A,Product_Dim!E:E) -> Brown and Sons | AA103: =_xlfn.XLOOKUP(Table17[[#This Row],[Product_ID]],Product_Dim!A:A,Product_Dim!F:F) -> 174.02 | AB103: =_xlfn.XLOOKUP(Table17[[#This Row],[Product_ID]],Product_Dim!A:A,Product_Dim!G:G) -> 268
A104: SALE102 | B104: 45552 | C104: CUST1097 | D104: PROD80 | E104: STORE12 | F104: 2 | G104: 471.88 | H104: 0.24 | I104: PayPal | J104: 717.2576 | K104: =_xlfn.XLOOKUP(Table17[[#This Row],[Customer_ID]],Customer_Dim!A:A,Customer_Dim!B:B,"False Data") -> David Cobb | L104: =_xlfn.XLOOKUP(Table17[[#This Row],[Customer_ID]],Customer_Dim!A:A,Customer_Dim!C:C,"False Data") -> 36 | M104: {=_xlfn.IFS(Table9[[#This Row],[Age]]<=35,"Youth",Table9[[#This Row],[Age]]<=55,"Adult",Table9[[#This Row],[Age]]>55,"Senior")} -> Adult | N104: =_xlfn.XLOOKUP(Table17[[#This Row],[Customer_ID]],Customer_Dim!A:A,Customer_Dim!D:D,"False Data") -> Male | O104: =_xlfn.XLOOKUP(Table17[[#This Row],[Customer_ID]],Customer_Dim!A:A,Customer_Dim!E:E,"False Data") -> Lake Thomas | P104: =_xlfn.XLOOKUP(Table17[[#This Row],[Customer_ID]],Customer_Dim!A:A,Customer_Dim!F:F,"False Data") -> South Dakota | Q104: =_xlfn.XLOOKUP(Table17[[#This Row],[Customer_ID]],Customer_Dim!A:A,Customer_Dim!G:G,"False Data") -> USA | R104: =_xlfn.XLOOKUP(Table17[[#This Row],[Customer_ID]],Customer_Dim!A:A,Customer_Dim!H:H,"False Data") -> Silver | S104: =_xlfn.XLOOKUP(Table17[[#This Row],[Store_ID]],Store_Dim!A:A,Store_Dim!B:B) -> Thomas, Bridges and Harris | T104: =_xlfn.XLOOKUP(Table17[[#This Row],[Store_ID]],Store_Dim!A:A,Store_Dim!C:C) -> North | U104: =_xlfn.XLOOKUP(Table17[[#This Row],[Store_ID]],Store_Dim!A:A,Store_Dim!D:D) -> Sabrinatown | V104: =_xlfn.XLOOKUP(Table17[[#This Row],[Store_ID]],Store_Dim!A:A,Store_Dim!E:E) -> Online | W104: =_xlfn.XLOOKUP(Table17[[#This Row],[Product_ID]],Product_Dim!A:A,Product_Dim!B:B) -> Wall-Mounted Spice Rack | X104: =_xlfn.XLOOKUP(Table17[[#This Row],[Product_ID]],Product_Dim!A:A,Product_Dim!C:C) -> Home | Y104: =_xlfn.XLOOKUP(Table17[[#This Row],[Product_ID]],Product_Dim!A:A,Product_Dim!D:D) -> Kitchen | Z104: =_xlfn.XLOOKUP(Table17[[#This Row],[Product_ID]],Product_Dim!A:A,Product_Dim!E:E) -> Allison Ltd | AA104: =_xlfn.XLOOKUP(Table17[[#This Row],[Product_ID]],Product_Dim!A:A,Product_Dim!F:F) -> 143.43 | AB104: =_xlfn.XLOOKUP(Table17[[#This Row],[Product_ID]],Product_Dim!A:A,Product_Dim!G:G) -> 58
A105: SALE103 | B105: 45907 | C105: CUST1182 | D105: PROD34 | E105: STORE4 | F105: 4 | G105: 925.19 | H105: 0.19 | I105: PayPal | J105: 2997.6156 | K105: =_xlfn.XLOOKUP(Table17[[#This Row],[Customer_ID]],Customer_Dim!A:A,Customer_Dim!B:B,"False Data") -> Melissa Hamilton | L105: =_xlfn.XLOOKUP(Table17[[#This Row],[Customer_ID]],Customer_Dim!A:A,Customer_Dim!C:C,"False Data") -> 23 | M105: {=_xlfn.IFS(Table9[[#This Row],[Age]]<=35,"Youth",Table9[[#This Row],[Age]]<=55,"Adult",Table9[[#This Row],[Age]]>55,"Senior")} -> Youth | N105: =_xlfn.XLOOKUP(Table17[[#This Row],[Customer_ID]],Customer_Dim!A:A,Customer_Dim!D:D,"False Data") -> Female | O105: =_xlfn.XLOOKUP(Table17[[#This Row],[Customer_ID]],Customer_Dim!A:A,Customer_Dim!E:E,"False Data") -> Hutchinsonville | P105: =_xlfn.XLOOKUP(Table17[[#This Row],[Customer_ID]],Customer_Dim!A:A,Customer_Dim!F:F,"False Data") -> Oklahoma | Q105: =_xlfn.XLOOKUP(Table17[[#This Row],[Customer_ID]],Customer_Dim!A:A,Customer_Dim!G:G,"False Data") -> USA | R105: =_xlfn.XLOOKUP(Table17[[#This Row],[Customer_ID]],Customer_Dim!A:A,Customer_Dim!H:H,"False Data") -> Silver | S105: =_xlfn.XLOOKUP(Table17[[#This Row],[Store_ID]],Store_Dim!A:A,Store_Dim!B:B) -> Alexander Group | T105: =_xlfn.XLOOKUP(Table17[[#This Row],[Store_ID]],Store_Dim!A:A,Store_Dim!C:C) -> South | U105: =_xlfn.XLOOKUP(Table17[[#This Row],[Store_ID]],Store_Dim!A:A,Store_Dim!D:D) -> Port Sharon | V105: =_xlfn.XLOOKUP(Table17[[#This Row],[Store_ID]],Store_Dim!A:A,Store_Dim!E:E) -> Online | W105: =_xlfn.XLOOKUP(Table17[[#This Row],[Product_ID]],Product_Dim!A:A,Product_Dim!B:B) -> Gaming Mechanical Keyboard | X105: =_xlfn.XLOOKUP(Table17[[#This Row],[Product_ID]],Product_Dim!A:A,Product_Dim!C:C) -> Electronics | Y105: =_xlfn.XLOOKUP(Table17[[#This Row],[Product_ID]],Product_Dim!A:A,Product_Dim!D:D) -> Computer | Z105: =_xlfn.XLOOKUP(Table17[[#This Row],[Product_ID]],Product_Dim!A:A,Product_Dim!E:E) -> Lucero LLC | AA105: =_xlfn.XLOOKUP(Table17[[#This Row],[Product_ID]],Product_Dim!A:A,Product_Dim!F:F) -> 419.28 | AB105: =_xlfn.XLOOKUP(Table17[[#This Row],[Product_ID]],Product_Dim!A:A,Product_Dim!G:G) -> 86
A106: SALE104 | B106: 45330 | C106: CUST1029 | D106: PROD86 | E106: STORE11 | F106: 2 | G106: 879.63 | H106: 0.07 | I106: COD | J106: 1636.1118 | K106: =_xlfn.XLOOKUP(Table17[[#This Row],[Customer_ID]],Customer_Dim!A:A,Customer_Dim!B:B,"False Data") -> David Arnold | L106: =_xlfn.XLOOKUP(Table17[[#This Row],[Customer_ID]],Customer_Dim!A:A,Customer_Dim!C:C,"False Data") -> 54 | M106: {=_xlfn.IFS(Table9[[#This Row],[Age]]<=35,"Youth",Table9[[#This Row],[Age]]<=55,"Adult",Table9[[#This Row],[Age]]>55,"Senior")} -> Adult | N106: =_xlfn.XLOOKUP(Table17[[#This Row],[Customer_ID]],Customer_Dim!A:A,Customer_Dim!D:D,"False Data") -> Female | O106: =_xlfn.XLOOKUP(Table17[[#This Row],[Customer_ID]],Customer_Dim!A:A,Customer_Dim!E:E,"False Data") -> East Jennifer | P106: =_xlfn.XLOOKUP(Table17[[#This Row],[Customer_ID]],Customer_Dim!A:A,Customer_Dim!F:F,"False Data") -> California | Q106: =_xlfn.XLOOKUP(Table17[[#This Row],[Customer_ID]],Customer_Dim!A:A,Customer_Dim!G:G,"False Data") -> USA | R106: =_xlfn.XLOOKUP(Table17[[#This Row],[Customer_ID]],Customer_Dim!A:A,Customer_Dim!H:H,"False Data") -> Silver | S106: =_xlfn.XLOOKUP(Table17[[#This Row],[Store_ID]],Store_Dim!A:A,Store_Dim!B:B) -> Aguirre-Keller | T106: =_xlfn.XLOOKUP(Table17[[#This Row],[Store_ID]],Store_Dim!A:A,Store_Dim!C:C) -> South | U106: =_xlfn.XLOOKUP(Table17[[#This Row],[Store_ID]],Store_Dim!A:A,Store_Dim!D:D) -> Lake Michael | V106: =_xlfn.XLOOKUP(Table17[[#This Row],[Store_ID]],Store_Dim!A:A,Store_Dim!E:E) -> Online | W106: =_xlfn.XLOOKUP(Table17[[#This Row],[Product_ID]],Product_Dim!A:A,Product_Dim!B:B) -> Kitchen Cutting Board | X106: =_xlfn.XLOOKUP(Table17[[#This Row],[Product_ID]],Product_Dim!A:A,Product_Dim!C:C) -> Home | Y106: =_xlfn.XLOOKUP(Table17[[#This Row],[Product_ID]],Product_Dim!A:A,Product_Dim!D:D) -> Kitchen | Z106: =_xlfn.XLOOKUP(Table17[[#This Row],[Product_ID]],Product_Dim!A:A,Product_Dim!E:E) -> Taylor, Dodson and Johnston | AA106: =_xlfn.XLOOKUP(Table17[[#This Row],[Product_ID]],Product_Dim!A:A,Product_Dim!F:F) -> 176.07 | AB106: =_xlfn.XLOOKUP(Table17[[#This Row],[Product_ID]],Product_Dim!A:A,Product_Dim!G:G) -> 82
A107: SALE105 | B107: 45214 | C107: CUST1002 | D107: PROD79 | E107: STORE17 | F107: 2 | G107: 418.23 | H107: 0.28 | I107: Credit Card | J107: 602.2512 | K107: =_xlfn.XLOOKUP(Table17[[#This Row],[Customer_ID]],Customer_Dim!A:A,Customer_Dim!B:B,"False Data") -> Dr. Benjamin Price | L107: =_xlfn.XLOOKUP(Table17[[#This Row],[Customer_ID]],Customer_Dim!A:A,Customer_Dim!C:C,"False Data") -> 29 | M107: {=_xlfn.IFS(Table9[[#This Row],[Age]]<=35,"Youth",Table9[[#This Row],[Age]]<=55,"Adult",Table9[[#This Row],[Age]]>55,"Senior")} -> Youth | N107: =_xlfn.XLOOKUP(Table17[[#This Row],[Customer_ID]],Customer_Dim!A:A,Customer_Dim!D:D,"False Data") -> Female | O107: =_xlfn.XLOOKUP(Table17[[#This Row],[Customer_ID]],Customer_Dim!A:A,Customer_Dim!E:E,"False Data") -> Kylebury | P107: =_xlfn.XLOOKUP(Table17[[#This Row],[Customer_ID]],Customer_Dim!A:A,Customer_Dim!F:F,"False Data") -> Alabama | Q107: =_xlfn.XLOOKUP(Table17[[#This Row],[Customer_ID]],Customer_Dim!A:A,Customer_Dim!G:G,"False Data") -> USA | R107: =_xlfn.XLOOKUP(Table17[[#This Row],[Customer_ID]],Customer_Dim!A:A,Customer_Dim!H:H,"False Data") -> Platinum | S107: =_xlfn.XLOOKUP(Table17[[#This Row],[Store_ID]],Store_Dim!A:A,Store_Dim!B:B) -> Holloway Ltd | T107: =_xlfn.XLOOKUP(Table17[[#This Row],[Store_ID]],Store_Dim!A:A,Store_Dim!C:C) -> North | U107: =_xlfn.XLOOKUP(Table17[[#This Row],[Store_ID]],Store_Dim!A:A,Store_Dim!D:D) -> Bensonhaven | V107: =_xlfn.XLOOKUP(Table17[[#This Row],[Store_ID]],Store_Dim!A:A,Store_Dim!E:E) -> Flagship | W107: =_xlfn.XLOOKUP(Table17[[#This Row],[Product_ID]],Product_Dim!A:A,Product_Dim!B:B) -> Decorative Lamp Shade | X107: =_xlfn.XLOOKUP(Table17[[#This Row],[Product_ID]],Product_Dim!A:A,Product_Dim!C:C) -> Home | Y107: =_xlfn.XLOOKUP(Table17[[#This Row],[Product_ID]],Product_Dim!A:A,Product_Dim!D:D) -> Lighting | Z107: =_xlfn.XLOOKUP(Table17[[#This Row],[Product_ID]],Product_Dim!A:A,Product_Dim!E:E) -> Ramirez-Hanson | AA107: =_xlfn.XLOOKUP(Table17[[#This Row],[Product_ID]],Product_Dim!A:A,Product_Dim!F:F) -> 228.53 | AB107: =_xlfn.XLOOKUP(Table17[[#This Row],[Product_ID]],Product_Dim!A:A,Product_Dim!G:G) -> 469
